Workbook

Sheet 0. Read me
A1: ↑ | B1: SR26 data collection master spreadsheet
B2: 2026 Sustainability Report – data collection master
B4: Purpose | C4: Central record of SR26 data requirements, owners, reporting requests, responses and evidence. Adapted from the 2025 end-year reporting master spreadsheet (V0.2) and the Sustainability 2030 updated targets (Qual and Quan worksheets).
B5: Status | C5: DRAFT v0.1 – pilot with 4 faculties (ABP, Arts, FBE, Science) and 5 central units (CI&S, CFOG, ESG, CIOG, MRE).
B6: Reporting approach | C6: Transition year: cover all of CY2026, distinguishing former Sustainability Plan 2030 activity from foundations and early actions after the Sustainability 2030 launch (~20 Oct 2026). Databook is the authoritative quantitative source. Target status (Met/Partially met/Not met) retained for now for internal management reporting – rating framework under review.
B7: Key dates (TBC) | C7: Requests issued: Nov–Dec 2026 | Highlighted stories due: Friday 4 December 2026 (TBC) | Reporting template due: Friday 15 January 2027 (TBC) | Support meetings: January 2027 | Sustainability Reporting Review Group: ~15 Feb 2027 | VCAG: 16 Feb & ~2 Mar 2027
B8: Tabs | C8: 1. Requirements matrix – every S2030 qualitative indicator, owner and request 2. Quant – Databook mapping – quantitative indicators to confirm with the Databook/central data owners 3. Stakeholder map & RASCI – SR25 → SR26 unit mapping and who is asked for what 4. Request tracker – sent/chased/received/confirmed status and response rate Faculties / CI&S / CFOG / ESG / CIOG / MRE – consolidated responses (copy in from returned request workbooks; same layout) Highlighted stories – consolidated optional stories and case-study shortlist A1. Data scoring – auto-pulls every unit's responses per indicator and scores target status (SR25 method) 0.5 Target Check – which units were asked about each indicator T2. Single target review – pick an indicator and see all units' responses and the scored status Request wording log – original S2030 wording vs tailored faculty request wording Evidence register – source, evidence, limitations and owner confirmation for every material claim Issues log – open questions, TBCs and decisions
B9: Refs | C9: Refs are new SR26 codes: priority-area code + target number + indicator letter (e.g. EE1(a) = Exceptional education, target 1, indicator a). 'Related SR25 ref' links to the closest SP2030 (2025) target where one exists.
B10: Regenerating | C10: Workbooks are generated by build.py in the repository. Edit the settings at the top (due dates, pilot faculties, unit mapping) and re-run to produce request workbooks for additional faculties/units.
B11: Request wording | C11: Faculty requests are rewritten in the SR25 style and point to each faculty's end-2025 response (see Request wording log). Central-unit requests use the S2030 'Qual' worksheet wording as-is.
B12: Formulas | C12: Responses must be pasted into the Faculties/central-unit tabs keeping the same rows – A1, 0.5 and T2 look them up by Ref. Do not insert rows inside a block; add new units by re-running build.py.

Sheet 1. Requirements matrix
A1: ↑ | B1: End-2026 target status assessment and reporting
B2: 1. Requirements matrix (qualitative)
B5: Ref | C5: Domain | D5: Priority area | E5: Target | F5: Indicator | G5: Reporting requirement (S2030 Qual sheet) | H5: Key stakeholders (S2030 sheet) | I5: SR26 request issued to | J5: Specific projects we are aware of (area & person) | K5: Internal vs External | L5: Flag for continuous improvement | M5: Notes | N5: Related SR25 ref | O5: Channel | P5: Owner confirmed?
B6: EE1(a) | C6: Education and research | D6: Exceptional education | E6: Provide our students with learning experiences that help them build the knowledge, skills and relationships to lead change for sustainable societies. | F6: Evidence of innovative approaches to sustainability teaching and learning | G6: Please describe any innovative approaches used within your Faculty/Portfolio to embed sustainability in teaching and learning. This could include examples of subjects, curriculum design, pedagogies, assessment approaches or learning resources. Please provide links or supporting evidence where available. | H6: Faculties, CI&S | I6: Faculties (pilot), CI&S | K6: Both | L6: No | N6: 4a(ii) | O6: Tailored request
B7: EE1(b) | C7: Education and research | D7: Exceptional education | E7: Provide our students with learning experiences that help them build the knowledge, skills and relationships to lead change for sustainable societies. | F7: Pilots of possible approaches for understanding and developing students’ sustainability self-efficacy | G7: Please describe any pilots or trials undertaken within your Faculty/Portfolio to understand or strengthen students’ sustainability self-efficacy. This could include the approach used, participating cohorts, what was assessed or learned, and any planned next steps. | H7: Faculties, CI&S | I7: Faculties (pilot), CI&S | J7: * Living Lab project (case study): Personalising Sustainability Pathways for students - Sustainability Strengths Compass. Project lead: Dianne Vella Brodrick. Funded partly by the Campus Living Lab Accelerator Program (CLLAP) (SST) | K7: Both | L7: No | O7: Tailored request
B8: EE1(c) | C8: Education and research | D8: Exceptional education | E8: Provide our students with learning experiences that help them build the knowledge, skills and relationships to lead change for sustainable societies. | F8: Evidence of sustainability focused experiential and co curricular learning (eg Wattle Fellowship; Melbourne Plus) | G8: Please provide examples of sustainability-focused experiential or co-curricular learning offered or supported by your Faculty/Portfolio (e.g. Wattle Fellowship, Melbourne Plus or similar), could include participation where available and a brief description of the learning experience and outcomes. | H8: Faculties, CI&S | I8: Faculties (pilot), CI&S | J8: * Wattle Fellowship (Linh Do); Wattle Fellowship could provide case studies and have an annual report. * Student and Scholarly Services (SASS - Melbourne Plus - Jess Trevitt) - how would we frame the ask differently for these data owners since we already know they offer experiential/co-curriculuar learning? SASS and Melbourne Plus can provide number of completions of students in the Sustainability Advocacy stream, and case studies. | K8: Both | L8: No | O8: Tailored request
B9: EE1(d) | C9: Education and research | D9: Exceptional education | E9: Provide our students with learning experiences that help them build the knowledge, skills and relationships to lead change for sustainable societies. | F9: Alumni profiles demonstrating how graduates contribute to sustainability through their careers or communities. | G9: Please provide examples or profiles of graduates or alumni from your Faculty who demonstrate how they apply sustainability knowledge, skills or capabilities through their careers, communities or other activities. Where available, include any evidence used by the Faculty to understand graduate outcomes related to sustainability. | H9: Faculties, CI&S | I9: Faculties (pilot), CI&S | K9: Both | L9: No | N9: 4b(i) | O9: Tailored request
B10: TR1(a) | C10: Education and research | D10: Transformational research | E10: Utilise the expertise of the University’s researchers through mutually beneficial partnerships to help address the University’s operational sustainability challenges. | F10: Expert-reviewed evidence of researchers contributing to operational sustainability priorities through partnerships, advisory input, living labs, applied projects or decision-support | G10: Please provide examples of researchers within your Faculty/Portfolio contributing to University operational sustainability priorities through partnerships, advisory input, living labs, applied projects or decision-support. Briefly describe the operational challenge, researcher contribution and resulting or expected outcome. | H10: Faculties, CI&S | I10: Faculties (pilot), CI&S | J10: MRE Campus Living Lab Accelerator Program (CLLAP) case studies (CI&S). Also Enterprise Services Group - Campus Operations and Delivery (COD) might have collaborations we're not aware of (e.g. Rachael Miller) | K10: Both | L10: No | N10: 2a | O10: Tailored request
B11: TR1(b) | C11: Education and research | D11: Transformational research | E11: Utilise the expertise of the University’s researchers through mutually beneficial partnerships to help address the University’s operational sustainability challenges. | F11: Evidence of institutional pathways that enable ongoing collaboration between academic and professional staff | G11: Please describe any pathways, mechanisms or processes within your Faculty/Portfolio that enable ongoing collaboration between academic and professional staff on operational sustainability challenges, could include formal programs, governance arrangements, funding mechanisms or coordination channels. | H11: Faculties | I11: Faculties (pilot) | J11: MRE | K11: Both | L11: No | O11: Tailored request
B12: TR1(c) | C12: Education and research | D12: Transformational research | E12: Utilise the expertise of the University’s researchers through mutually beneficial partnerships to help address the University’s operational sustainability challenges. | F12: Expert assessment of the quality, relevance and continuity of these collaborations | G12: Please provide an assessment of the quality, relevance and continuity of sustainability-related collaborations involving your Faculty/Portfolio, could include evidence of whether collaborations are sustained, useful to operational priorities and producing relevant outcomes. | H12: Faculties | I12: Faculties (pilot) | J12: MRE | K12: Both | L12: No | O12: Tailored request
B13: TR1(d) | C13: Education and research | D13: Transformational research | E13: Utilise the expertise of the University’s researchers through mutually beneficial partnerships to help address the University’s operational sustainability challenges. | F13: Periodic feedback from participants on the effectiveness and mutual benefit of collaboration mechanisms. | G13: Please provide any participant feedback or other evidence from your Faculty/Portfolio on the effectiveness and mutual benefit of collaboration mechanisms between researchers and operational teams, could include key findings and any improvements identified. | H13: Faculties | I13: Faculties (pilot) | J13: MRE | K13: Both | L13: No | O13: Tailored request
B14: TR2(a) | C14: Education and research | D14: Transformational research | E14: Deliver high-quality research and partnerships that contribute to sustainability outcomes and demonstrable societal benefit. | F14: Evidence of sustainability-related research impact across diverse pathways, could include policy, industry, community, practice, cultural and institutional outcomes | G14: Please provide examples of sustainability-related research impact from your Faculty/Portfolio across policy, industry, community, practice, cultural or institutional pathways. For key examples, briefly describe the research contribution, partner/user and resulting outcome or influence. | H14: Faculties | I14: Faculties (pilot) | J14: Melbourne Research and Enterprise (Nishi Raja-Stranger and Ivan Marusic) Strategic Communications - Research lead will be able to identify examples of impactful sustainability-related research; also Pursuit (may be via Strat Comms too) Melbourne Climate Futures (Ben Neville, Beth Barber, Belle Workman) - MCF produce an annual impact report we could refer to. Melbourne Biodiversity Insitute (Brendan Wintle, Alanta Colley, Rachel Morgain) Possibly Melbourne Energy Institute. MDHS Climate CATCH Lab and other specific research centres could be approached and asked about their impact, or we could flag specific research centres in faculty requests. | K14: Both | L14: No | N14: 5b(i) | O14: Tailored request
B15: TR2(b) | C15: Education and research | D15: Transformational research | E15: Deliver high-quality research and partnerships that contribute to sustainability outcomes and demonstrable societal benefit. | F15: Documented progress of relevant strategic initiatives, including Impact Accelerators | G15: Please provide case studies demonstrating how University research has contributed to meaningful sustainability outcomes. For each case, briefly describe the research, stakeholders involved, pathway to impact and evidence of the resulting sustainability outcome. | I15: TBC – no owner identified | K15: Both | L15: No | M15: documented progress imply that university have good governance over the management of initiatives and therefore could provide percentage of milestone completion | O15: Databook / central data owner
B16: TR2(c) | C16: Education and research | D16: Transformational research | E16: Deliver high-quality research and partnerships that contribute to sustainability outcomes and demonstrable societal benefit. | F16: Expert-reviewed summary of sustainability-related research outputs, outcomes and influence using available institutional evidence sources | G16: currently mapped to the SDGs using SciVal | H16: MRE | I16: MRE | K16: Both | L16: No | O16: Tailored request
B17: TR2(d) | C17: Education and research | D17: Transformational research | E17: Deliver high-quality research and partnerships that contribute to sustainability outcomes and demonstrable societal benefit. | F17: Case-based evidence demonstrating how research has contributed to meaningful sustainability outcomes. | G17: Please provide case studies from your Faculty/Portfolio demonstrating how research has contributed to meaningful sustainability outcomes. Briefly describe the research, stakeholders involved, pathway to impact and evidence of the resulting sustainability outcome. | H17: Faculties, CI&S | I17: Faculties (pilot), CI&S | J17: Strategic Communications - Research lead will be able to identify examples of impactful sustainability-related research; also Pursuit (may be via Strat Comms too) Melbourne Climate Futures (Ben Neville, Beth Barber, Belle Workman) Melbourne Biodiversity Insitute (Brendan Wintle, Alanta Colley, Rachel Morgain) Possibly Melbourne Energy Institute. | K17: Both | L17: No | N17: 5b(i) | O17: Tailored request
B18: TR3(a) | C18: Education and research | D18: Transformational research | E18: Embed sustainability within research systems, processes, capability and culture, so research is conducted responsibly, efficiently and with reduced environmental impact. | F18: Evidence that sustainability considerations are integrated into relevant research systems, planning processes, guidance, training, induction or support services | G18: Please describe how sustainability considerations are integrated into research systems, planning processes, guidance, training, induction or support services within your Faculty/Portfolio, could include examples of any new or improved processes. | H18: Faculties, CI&S | I18: Faculties (pilot), CI&S | K18: Both | L18: No | N18: 5c(ii) | O18: Tailored request
B19: TR3(b) | C19: Education and research | D19: Transformational research | E19: Embed sustainability within research systems, processes, capability and culture, so research is conducted responsibly, efficiently and with reduced environmental impact. | F19: Demonstrated examples of more sustainable research practices in laboratories, fieldwork, procurement, travel or infrastructure use | G19: Please describe any efforts within your Faculty/Portfolio to make research practices more sustainable, could include examples from laboratories, fieldwork, procurement, research travel or infrastructure use. Where available, provide evidence of uptake, resource savings, emissions reductions or other outcomes. | H19: Faculties, CI&S, CFOG | I19: Faculties (pilot), CI&S, CFOG | K19: Both | L19: No | N19: 5c(ii) | O19: Tailored request
B20: TR3(c) | C20: Education and research | D20: Transformational research | E20: Embed sustainability within research systems, processes, capability and culture, so research is conducted responsibly, efficiently and with reduced environmental impact. | F20: Evidence of progress in sustainability-related research culture, capability and awareness, informed by periodic staff and graduate researcher surveys | G20: Please provide evidence of progress in sustainability-related research culture, capability and awareness within your Faculty/Portfolio. This could include relevant staff and/or graduate researcher survey findings, participation in capability-building activities, or other indicators of change over time. | H20: Faculties | I20: Faculties (pilot) | J20: Melbourne Research and Enterprise (Nishi Raja-Stranger; Ivan Marusic) - MRE will be a key reporter for all research targets. | K20: Both | L20: No | O20: Tailored request
B21: TR3(d) | C21: Education and research | D21: Transformational research | E21: Embed sustainability within research systems, processes, capability and culture, so research is conducted responsibly, efficiently and with reduced environmental impact. | F21: Expert assessment of progress in embedding sustainable research practices across the institution. | G21: Faculty/Portfolio’s assessment of progress in embedding sustainable research practices, highlighting areas of strong progress, remaining gaps and priority actions for further improvement. | H21: Faculties | I21: Faculties (pilot) | K21: Both | L21: No | O21: Tailored request
B22: CL1(a) | C22: Sustainability leadership | D22: Climate leadership | E22: Achieve net zero emissions by 2050: Interim target Reduce emissions by 20% across all emissions scopes by CY2030 on the CY2023 re-baseline including: • Scopes 1 and 2: 66% reduction • Scope 3: 12% reduction. Long-term target Reduce emissions by 90% across all emissions scopes by CY2050 on the CY2023 re-baseline and invest in carbon removal credits for residual emissions from hard-to-abate sources (up to 10%). | F22: Annual Greenhouse Gas Inventory (including emissions scopes 1, 2 and 3) demonstrates carbon emission reductions, including maintaining procurement of 100% renewable electricity for all scope 2 sources[1] | G22: Total scope 1,2 and 3 emissions (tCO2-e); emissions by scope; % reduction from previous baseline; % renewable electircity produced | I22: TBC – no owner identified | K22: Both | L22: No | M22: Directly measures progress against the stated emission reduction targets and allows annual comparison against the baseline and trajectory | O22: Databook / central data owner
B23: CL1(b) | C23: Sustainability leadership | D23: Climate leadership | E23: Achieve net zero emissions by 2050: Interim target Reduce emissions by 20% across all emissions scopes by CY2030 on the CY2023 re-baseline including: • Scopes 1 and 2: 66% reduction • Scope 3: 12% reduction. Long-term target Reduce emissions by 90% across all emissions scopes by CY2050 on the CY2023 re-baseline and invest in carbon removal credits for residual emissions from hard-to-abate sources (up to 10%). | F23: Development of Greenhouse Gas intensity metrics | G23: Greenhouse gas emissions by FTE, EFTSL, and Gross floor area (https://www.unimelb.edu.au/sustainabilityreport/2025/data-tables#GHGe-scope) | I23: TBC – no owner identified | K23: Both | L23: Yes | M23: Quantiative indicator | O23: Databook / central data owner
B24: CL1(c) | C24: Sustainability leadership | D24: Climate leadership | E24: Achieve net zero emissions by 2050: Interim target Reduce emissions by 20% across all emissions scopes by CY2030 on the CY2023 re-baseline including: • Scopes 1 and 2: 66% reduction • Scope 3: 12% reduction. Long-term target Reduce emissions by 90% across all emissions scopes by CY2050 on the CY2023 re-baseline and invest in carbon removal credits for residual emissions from hard-to-abate sources (up to 10%). | F24: Review of Climate Leadership targets by 2030.[2] | H24: CI&S | I24: CI&S | K24: Both | L24: Yes | M24: Need to review again on 2030. The climate target itself is still two months old | O24: Tailored request
B25: CL2(a) | C25: Sustainability leadership | D25: Climate leadership | E25: Develop understanding of our research and education programs that contribute to accelerating global decarbonisation and our own climate transition. | F25: By 2028, develop and document institutional mapping of research and education activities that are designed to contribute to global decarbonisation | G25: Please list and describe examples of communications from your Faculty/Portfolio that demonstrate climate action, research and learning and aim to inform policy, sector or community decarbonisation efforts. Could include links, intended audiences and any available evidence of reach or influence. | H25: Faculties, CI&S | I25: Faculties (pilot), CI&S | K25: Both | L25: No | O25: Tailored request
B26: CL2(b) | C26: Sustainability leadership | D26: Climate leadership | E26: Develop understanding of our research and education programs that contribute to accelerating global decarbonisation and our own climate transition. | F26: Prioritised pipeline of decarbonisation focused research and education opportunities aligned with University emissions reduction priorities from 2028 | G26: Number of pipelined projects or research transitioned from opportunity to active per year | I26: TBC – no owner identified | K26: Both | L26: No | M26: Pipeline can be quantitatively tracked through volume and progression, but since the target is prioritised pipeline, showing number of sucessful pipeline transitioned is more desirable | O26: Databook / central data owner
B27: CL2(c) | C27: Sustainability leadership | D27: Climate leadership | E27: Develop understanding of our research and education programs that contribute to accelerating global decarbonisation and our own climate transition. | F27: Ongoing communications that evidence the University’s climate action, research and learning to inform policy, sector and community decarbonisation efforts. | G27: List and describe communications from the faculty in terms of climate action, research and learning to inform policy, sector and community decarbonisation efforts | H27: Faculties, | I27: Faculties (pilot) | K27: Both | L27: No | O27: Tailored request
B28: CL3(a) | C28: Sustainability leadership | D28: Climate leadership | E28: Reach and maintain high levels of climate-change resilience maturity | F28: Maturity assessment of the University’s preparedness for climate-related impacts and capability to respond, assessed across relevant organisational functions: o Governance and strategy o Health and safety o Business continuity o Emergency management and critical incidence management o Estate and buildings o Water management o Financial planning and reporting. | G28: Provide update of University maturity assesment. Include maturity ratings, key gaps and priority improvement actions.when available | H28: CI&S | I28: CI&S | K28: Both | L28: No | M28: Could check with Gerard. Gerard is the one who manage this indicator | O28: Tailored request
B29: NB1(a) | C29: Sustainability leadership | D29: Nature and biodiversity | E29: Achieve an increase of biodiversity relative to defined baseline years for each campus. | F29: Monitoring of biodiversity metrics from the Biodiversity Baseline Data Project | G29: 7 diversity metrics from https://sustainablecampus.unimelb.edu.au/biodiversity/biodiversity-baseline-data-project#main-content | I29: TBC – no owner identified | K29: Both | L29: No | M29: Quantitative indicator | O29: Databook / central data owner
B30: NB1(b) | C30: Sustainability leadership | D30: Nature and biodiversity | E30: Achieve an increase of biodiversity relative to defined baseline years for each campus. | F30: Size, health and diversity of remnant vegetation at the Dookie and Creswick campuses | H30: Rachel | I30: ESG | K30: Internal | L30: No | M30: Havent been previously disclose publicly | O30: Tailored request
B31: NB1(c) | C31: Sustainability leadership | D31: Nature and biodiversity | E31: Achieve an increase of biodiversity relative to defined baseline years for each campus. | F31: Defined quality measurement framework | H31: ESG | I31: ESG | K31: Both | L31: No | M31: Follow up with Rachel | O31: Tailored request
B32: NB1(d) | C32: Sustainability leadership | D32: Nature and biodiversity | E32: Achieve an increase of biodiversity relative to defined baseline years for each campus. | F32: Defined and quantified campus connectivity | G32: Please provide the current definition and quantified assessment of campus ecological connectivity, could include the methodology used, campuses covered, baseline or benchmark values, and any material change over the reporting period. | H32: ESG | I32: ESG | K32: Both | L32: No | O32: Tailored request
B33: NB2(a) | C33: Sustainability leadership | D33: Nature and biodiversity | E33: Improve our understanding of our supply chain impacts on nature. | F33: Documented baseline nature footprint analysis | G33: Impact Encore Measurement | H33: MBI | I33: MRE | K33: Both | L33: No | O33: Tailored request
B34: NB2(b) | C34: Sustainability leadership | D34: Nature and biodiversity | E34: Improve our understanding of our supply chain impacts on nature. | F34: Evidence of established framework to monitor and track supply-chain nature impacts over time | G34: Please describe the framework established to monitor and track supply-chain impacts on nature over time, could include metrics, data sources, governance/ownership, reporting frequency and current implementation status. | H34: ESG | I34: ESG | J34: Melbourne Biodiversity Institute (MBI) - Brendan Wintle and August Wylynko | K34: Both | L34: No | O34: Tailored request
B35: NB2(c) | C35: Sustainability leadership | D35: Nature and biodiversity | E35: Improve our understanding of our supply chain impacts on nature. | F35: Evidence of prioritised high risk procurement categories or suppliers for nature impact management | G35: Please provide the prioritised high-risk procurement categories and/or suppliers identified for nature-impact management, could include the basis for prioritisation and any risk-management, engagement or mitigation actions undertaken or planned. | H35: ESG, CFOG | I35: CFOG, ESG | J35: MBI | K35: Both | L35: No | O35: Tailored request
B36: AI1(a) | C36: Sustainability leadership | D36: Responsible AI | E36: Improve understanding of our sustainability-related risks and opportunities of AI technologies by 2028. | F36: Established measurement of estimated operational impacts and opportunities (eg operational impacts could include energy, water, emissions and intensity measures) | H36: CI&S, CIOG | I36: CI&S, CIOG | K36: Both | L36: Yes | M36: Rose & Sally currently actively managing this target and indicator. High level overview on 2026, will work on the detailed measurement next year | O36: Tailored request
B37: AI1(b) | C37: Sustainability leadership | D37: Responsible AI | E37: Improve understanding of our sustainability-related risks and opportunities of AI technologies by 2028. | F37: Case studies of sustainability and AI-related education, research and collaboration activities. | G37: Please provide case studies from your Faculty/Portfolio of sustainability and AI-related education, research or collaboration activities, describing the activity, participants or partners, sustainability issue addressed and key outcomes or lessons. | H37: CI&S, CIOG | I37: CI&S, CIOG | J37: AI Steering Committee - developing AI roadmap, which includes responsible AI as a key pillar. | K37: Both | L37: No | O37: Tailored request
B38: EI1(a) | C38: Resilient University | D38: Estate and infrastructure | E38: Integrate environmental sustainability in the way that the University achieves strategic and operational objectives for our estate and infrastructure. | F38: Evidence of increased maturity of estate and infrastructure planning, development and operations to support the other priority areas in Sustainability 2030 | G38: Case study evidence of increased sustainability maturity in estate and infrastructure planning, development and operations, could include examples of changes to standards, processes, governance, decision-making or project requirements that support Sustainability 2030 priority areas. | H38: CI&S | I38: CI&S | J38: CI&S - Estate Planning and Development teams | K38: Both | L38: No | M38: Facilitated by Gerard | O38: Tailored request
B39: EI1(b) | C39: Resilient University | D39: Estate and infrastructure | E39: Integrate environmental sustainability in the way that the University achieves strategic and operational objectives for our estate and infrastructure. | F39: Estimated sustainability impacts of the University’s estate and infrastructure capital plan to inform progress towards emissions reduction targets and other priority areas (to the extent enabled by available information) | G39: Please provide any available information on sustainability impacts associated with estate and infrastructure projects or capital works relevant to your Faculty/Portfolio. This could include impacts related to emissions and other Sustainability 2030 priority areas. | H39: CI&S | I39: CI&S | J39: CI&S - Estate Planning and Development teams | K39: Both | L39: No | O39: Tailored request
B40: EI1(c) | C40: Resilient University | D40: Estate and infrastructure | E40: Integrate environmental sustainability in the way that the University achieves strategic and operational objectives for our estate and infrastructure. | F40: Reporting on relevant activities and impacts for the University’s major estate and infrastructure projects and programs aligned with the other priority areas in Sustainability 2030 | G40: Please provide an update on sustainability-related activities and impacts for major estate and infrastructure projects or programs relevant to your Faculty/Portfolio. This could include key initiatives, relevant performance measures and alignment with Sustainability 2030 priority areas. | H40: CI&S | I40: CI&S | J40: CI&S - Estate Planning and Development teams | K40: Both | L40: No | O40: Tailored request
B41: EI1(d) | C41: Resilient University | D41: Estate and infrastructure | E41: Integrate environmental sustainability in the way that the University achieves strategic and operational objectives for our estate and infrastructure. | F41: Evidence of understanding and integration of Indigenous approaches to sustainability in estate planning and development programs and projects. | G41: Please provide examples showing how Indigenous approaches, knowledges or perspectives on sustainability have informed estate planning, development programs or projects relevant to your Faculty/Portfolio. This could include how Indigenous stakeholders were engaged and what changed as a result. | H41: CI&S | I41: CI&S | J41: CI&S - Estate Planning and Development teams | K41: Both | L41: No | O41: Tailored request
B42: CE1(a) | C42: Resilient University | D42: Circular economy | E42: Reduce waste to landfill by 10% by CY2030 on the CY2025 baseline. | F42: Comparison of year-to-year tonnes of waste (absolute). | G42: tonnes of waste; % change against previous baseline | I42: TBC – no owner identified | K42: Both | L42: No | M42: Quantitative indicator | O42: Databook / central data owner
B43: CE2(a) | C43: Resilient University | D43: Circular economy | E43: Increase diversion of recyclable materials from landfill by 10% by CY2030 on the CY2025 baseline. | F43: Comparison of year-to-year tonnes of recyclables (absolute). | G43: waste diversion rate; tonnes diverted from landfill; % change against previous baseline | I43: TBC – no owner identified | K43: Both | L43: No | M43: Quantitative indicator | O43: Databook / central data owner
B44: RP1(a) | C44: Resilient University | D44: Responsible procurement | E44: Strengthen our ethical and sustainable procurement approach. | F44: Case studies of maturity improvement related to responsible procurement process and systems. | G44: Maturity score if framework established; % procurement staff trained | I44: CFOG | K44: Both | L44: No | M44: Quantitative metrics could support qualitative case studies to demonstrate system/process improvements | O44: Tailored request
B45: RP2(a) | C45: Resilient University | D45: Responsible procurement | E45: Increase our Indigenous and social spend, reaching 3% Indigenous and 1% social spend of addressable procurement by 2030. | F45: Percentage of Indigenous spend of total addressable procurement spend | G45: Percentage of Indigenous spend of total addressable procurement spend | I45: TBC – no owner identified | K45: Both | L45: No | M45: Quantitative indicator | O45: Databook / central data owner
B46: RP2(b) | C46: Resilient University | D46: Responsible procurement | E46: Increase our Indigenous and social spend, reaching 3% Indigenous and 1% social spend of addressable procurement by 2030. | F46: Percentage of social spend of total addressable procurement spend. | G46: Percentage of social spend of total addressable procurement spend. | I46: TBC – no owner identified | K46: Both | L46: No | M46: Quantitative indicator | O46: Databook / central data owner
B47: MS1(a) | C47: Resilient University | D47: Modern slavery and human rights | E47: Manage our approach to modern slavery and human rights-related risks and opportunities. | F47: Annual progress reporting via the Modern Slavery Statement | G47: Annual Modern Slavery Statement, with case studies | H47: CFOG, CI&S | I47: CI&S, CFOG | J47: CFOG - Procurement; Modern Slavery Working Group (existing). | K47: External | L47: No | O47: Tailored request
B48: RI1(a) | C48: Resilient University | D48: Responsible investments | E48: Achieve net zero financed emissions for the University’s investment portfolio by 2050. | F48: Annual monitoring and reporting on the investment portfolio’s net zero transition progress, including tracking the percentage of assets under management (AUM) managed by investment managers aligned with (or committed to) net zero by 2050 | G48: Percentage of AUM managed by investment managers aligned with net zero by 2050 | I48: TBC – no owner identified | K48: Both | L48: No | M48: Quantitative indicator | O48: Databook / central data owner
B49: RI1(b) | C49: Resilient University | D49: Responsible investments | E49: Achieve net zero financed emissions for the University’s investment portfolio by 2050. | F49: Continuous improvement of the reporting of the University’s sustainability-related investment profile metrics, could include investment in climate mitigation and transition solutions, and compliance with related obligations (eg UNPRI). | G49: Report on relevant sustainability-related investment portfolio metrics and report on how the University has complied with its related obligations | H49: CFOG, CI&S | I49: CI&S, CFOG | K49: Both | L49: No | O49: Tailored request
B50: EN1(a) | C50: Enablers | D50: Enablers | E50: Enablers | F50: Evidence of sustainability outcomes informed by Indigenous knowledges | G50: Please provide examples or case studies from your Faculty/Portfolio of sustainability outcomes informed by Indigenous knowledges. Describe the activity or decision, how Indigenous knowledges were incorporated or co-created, who was involved, and the resulting sustainability outcome. | H50: Faculties | I50: Faculties (pilot) | J50: For discussion - it would be good to chat about the nuances of this one | K50: Both | L50: No | N50: 6a | O50: Tailored request
B51: EN1(b) | C51: Enablers | D51: Enablers | E51: Enablers | F51: Living laboratories enabling applied learning, research and operational sustainability outcomes | G51: Comment on living labs in the Faculty - outputs, outcomes, and impact | H51: Faculties, CI&S | I51: Faculties (pilot), CI&S | J51: SST is a key data owner: Can report on projects and outcomes from the Campus Living Lab Accelerator Program. Also will gather case studies from individual projects (4) | K51: Both | L51: No | N51: 2a | O51: Tailored request
B52: EN1(c) | C52: Enablers | D52: Enablers | E52: Enablers | F52: Coordinated internal engagement and external partnerships contributing to delivery of sustainability outcomes across priority areas. | G52: Please provide examples of internal engagement or external partnerships involving your Faculty/Portfolio that contributed to Sustainability 2030 outcomes, could include the priority area addressed, participating groups/partners, nature of the collaboration and key outcomes. | H52: Faculties, CIOG, CFOG, CI&S, ESG | I52: Faculties (pilot), CI&S, CFOG, ESG, CIOG | J52: Noting a gap - we used to collect data from Advancement on the number of sustainability-focused events and attendees. We don't have an indicator that captures that now but it would fit under Engagement and Partnerships. For discussion: Should we collect this data and find a place to report it? (Data owners: Advancement, Karl Brown) The Global, Culture and Engagement team also provided us with case studies where sustainability is embedded in partnerships, or where students are engaging with sustainability in learning opportunities. They will have a case study this year about the winter school they ran which was focused on the SDGs. Main data owners/contacts: Charmaine Monteiro (Global); Padmini Sebastian (Engagement); also - we haven't engaged the 'Culture' part of GCE - should we engage them this year for case studies? | K52: Both | L52: No | N52: 3a(ii) | O52: Tailored request
B53: EN1(d) | C53: Enablers | D53: Enablers | E53: Enablers | F53: Sustainability objectives integrated into governance and decision‑making processes, supported by transparent reporting. | G53: Please provide evidence of how sustainability objectives are integrated into governance and decision-making within your Faculty/Portfolio, could include relevant committees, policies, planning or approval processes, accountability mechanisms and examples of transparent reporting. | H53: Faculties, CIOG, CFOG, CI&S, ESG | I53: Faculties (pilot), CI&S, CFOG, ESG, CIOG | J53: Reporting working group set up - talking about potential alignment with ASRS in future. Collaboration of SST, FBE (Accounting) and the Finance team in CFOG. Sally is the key contact for more info. | K53: Both | L53: No | O53: Tailored request

Sheet 2. Quant – Databook mapping
A1: ↑ | B1: End-2026 target status assessment and reporting
B2: 2. Quantitative indicators – Databook mapping
B3: Databook is the authoritative quantitative source – confirm coverage first and only request data separately where an indicator is not covered. Per the SR26 approach: map Sep–Oct; confirm provisional data in January; finalise by February.
B5: Ref | C5: Priority area | D5: Indicator | E5: Quant? (Y/M) | F5: Suggested metric | G5: Key person to follow up | H5: Internal vs External | I5: Analysis notes | J5: Covered by Databook? | K5: Definition | L5: Reporting boundary | M5: Period | N5: Source system | O5: End-2026 figure | P5: Quality note / limitations | Q5: Data owner | R5: Owner confirmed? | S5: Confirmation date
B6: EE1(c) | C6: Exceptional education | D6: Evidence of sustainability focused experiential and co curricular learning (eg Wattle Fellowship; Melbourne Plus) | E6: M | F6: Number of experiential learning projects; number of participating students | H6: Both | I6: Quantitative metrics could help shows the reach of projects, especially the student metrics
B7: EE1(d) | C7: Exceptional education | D7: Alumni profiles demonstrating how graduates contribute to sustainability through their careers or communities. | E7: M | F7: Number of alumni that contribute to sustainability; % profiles demonstrating sustainability contribution; insights form different industries that influenced by alumni | H7: Both | I7: Number and percentage of profiles could be underwhelming, but it helps to track the trajectory. I supposed qualitative case of selected profiles would still be the primary metrics.
B8: TR2(b) | C8: Transformational research | D8: Documented progress of relevant strategic initiatives, including Impact Accelerators | E8: Y | F8: Percentage of milestone completion rate to the set annual target of strategic initiatives; number of initiatives on track; number of initiatives delivered | H8: Both | I8: documented progress imply that university have good governance over the management of initiatives and therefore could provide percentage of milestone completion
B9: TR2(c) | C9: Transformational research | D9: Expert-reviewed summary of sustainability-related research outputs, outcomes and influence using available institutional evidence sources | E9: Y | F9: currently mapped to the SDGs using SciVal, old metrics explorer (publication mapped to SDG whether they mentioned in mews, media, policy,etc), | G9: MRE, Gerard | H9: Both | I9: To discuss contatct of researchers with Gerad
B10: TR3(b) | C10: Transformational research | D10: Demonstrated examples of more sustainable research practices in laboratories, fieldwork, procurement, travel or infrastructure use | E10: M | F10: Number of laboratories achieving green lab certification; number of new sustainable activity; number of sustainability fieldwork | G10: MRE, Gerard | H10: Both | I10: To discuss contatct of researchers with Gerad
B11: CL1(a) | C11: Climate leadership | D11: Annual Greenhouse Gas Inventory (including emissions scopes 1, 2 and 3) demonstrates carbon emission reductions, including maintaining procurement of 100% renewable electricity for all scope 2 sources[1] | E11: Y | F11: Total scope 1,2 and 3 emissions (tCO2-e); emissions by scope; % reduction from previous baseline; % renewable electircity produced | H11: Both | I11: Directly measures progress against the stated emission reduction targets and allows annual comparison against the baseline and trajectory
B12: CL1(b) | C12: Climate leadership | D12: Development of Greenhouse Gas intensity metrics | E12: Y | F12: Greenhouse gas emissions by FTE, EFTSL, and Gross floor area (https://www.unimelb.edu.au/sustainabilityreport/2025/data-tables#GHGe-scope) | H12: Both | I12: Quantiative indicator
B13: CL1(c) | C13: Climate leadership | D13: Review of Climate Leadership targets by 2030.[2] | E13: M | H13: Both | I13: Will be re-assesed in 2030
B14: CL2(a) | C14: Climate leadership | D14: By 2028, develop and document institutional mapping of research and education activities that are designed to contribute to global decarbonisation | E14: M | F14: Number of relevant research projects/programs mapped; number of relevant subjects mapped | H14: Both | I14: Although the core commitment is completion of the mapping (binary), quantitative measures still useful to show its coverage and comprehensiveness
B15: CL2(b) | C15: Climate leadership | D15: Prioritised pipeline of decarbonisation focused research and education opportunities aligned with University emissions reduction priorities from 2028 | E15: Y | F15: Number of pipelined projects or research transitioned from opportunity to active per year | H15: Both | I15: Pipeline can be quantitatively tracked through volume and progression, but since the target is prioritised pipeline, showing number of sucessful pipeline transitioned is more desirable
B16: CL2(c) | C16: Climate leadership | D16: Ongoing communications that evidence the University’s climate action, research and learning to inform policy, sector and community decarbonisation efforts. | E16: M | F16: Annual count of published documents, policy briefs, or public engagement events; number of policy/sector engagement; # views of communication material | G16: MCF; MEI | H16: Both | I16: Brainstorm with MCF and MEI
B17: CL3(a) | C17: Climate leadership | D17: Maturity assessment of the University’s preparedness for climate-related impacts and capability to respond, assessed across relevant organisational functions: o Governance and strategy o Health and safety o Business continuity o Emergency management and critical incidence management o Estate and buildings o Water management o Financial planning and reporting. | E17: M | F17: Maturity score by function; overall/average maturity score; % functions raching target maturity level | H17: Both | I17: If defined maturity is already available, then it is desirable to have quantitative metrics, especially since the target mentioned maturity assesment
B18: NB1(a) | C18: Nature and biodiversity | D18: Monitoring of biodiversity metrics from the Biodiversity Baseline Data Project | E18: Y | F18: 7 diversity metrics from https://sustainablecampus.unimelb.edu.au/biodiversity/biodiversity-baseline-data-project#main-content | H18: Both | I18: Quantitative indicator
B19: NB1(b) | C19: Nature and biodiversity | D19: Size, health and diversity of remnant vegetation at the Dookie and Creswick campuses | E19: Y | G19: Rachel | H19: Both
B20: NB1(c) | C20: Nature and biodiversity | D20: Defined quality measurement framework | E20: M | G20: Rachel | H20: Both
B21: NB1(d) | C21: Nature and biodiversity | D21: Defined and quantified campus connectivity | E21: M | G21: Rachel | H21: Both
B22: NB2(a) | C22: Nature and biodiversity | D22: Documented baseline nature footprint analysis | E22: Y | F22: Impact Encore Measurement | G22: August, MBI | H22: Both
B23: AI1(a) | C23: Responsible AI | D23: Established measurement of estimated operational impacts and opportunities (eg operational impacts including energy, water, emissions and intensity measures) | E23: M | F23: Pending denominator | H23: Both | I23: Will start with qual on 2026, then move on to quan
B24: EI1(a) | C24: Estate and infrastructure | D24: Evidence of increased maturity of estate and infrastructure planning, development and operations to support the other priority areas in Sustainability 2030 | E24: M | F24: qual, climate resilience?, | G24: Gerard | H24: Both
B25: EI1(b) | C25: Estate and infrastructure | D25: Estimated sustainability impacts of the University’s estate and infrastructure capital plan to inform progress towards emissions reduction targets and other priority areas (to the extent enabled by available information) | E25: M | F25: Forecast operational emission (tCO2-e); expected energy consumptions/savings; expected water impact; expected waste material impact; potential biodiversity impact | G25: Gerard | H25: Both | I25: Quantitative estimates/forecast (impact estimation) allow better planning and management to achieve the overall sustainability plan and targets (follow up with Gerard)
B26: EI1(c) | C26: Estate and infrastructure | D26: Reporting on relevant activities and impacts for the University’s major estate and infrastructure projects and programs aligned with the other priority areas in Sustainability 2030 | E26: M | F26: case by case | G26: Gerard | H26: Both
B27: CE1(a) | C27: Circular economy | D27: Comparison of year-to-year tonnes of waste (absolute). | E27: Y | F27: tonnes of waste; % change against previous baseline | H27: Both | I27: Quantitative indicator
B28: CE2(a) | C28: Circular economy | D28: Comparison of year-to-year tonnes of recyclables (absolute). | E28: Y | F28: waste diversion rate; tonnes diverted from landfill; % change against previous baseline | H28: Both | I28: Quantitative indicator
B29: RP1(a) | C29: Responsible procurement | D29: Case studies of maturity improvement related to responsible procurement process and systems. | E29: Y | F29: Maturity score if framework established; % procurement staff trained | H29: Both | I29: Quantitative metrics could support qualitative case studies to demonstrate system/process improvements
B30: RP2(a) | C30: Responsible procurement | D30: Percentage of Indigenous spend of total addressable procurement spend | E30: Y | F30: Percentage of Indigenous spend of total addressable procurement spend | H30: Both | I30: Quantitative indicator
B31: RP2(b) | C31: Responsible procurement | D31: Percentage of social spend of total addressable procurement spend. | E31: Y | F31: Percentage of social spend of total addressable procurement spend. | H31: Both | I31: Quantitative indicator
B32: RI1(a) | C32: Responsible investments | D32: Annual monitoring and reporting on the investment portfolio’s net zero transition progress, including tracking the percentage of assets under management (AUM) managed by investment managers aligned with (or committed to) net zero by 2050 | E32: Y | F32: Percentage of AUM managed by investment managers aligned with net zero by 2050 | H32: Both | I32: Quantitative indicator
B33: RI1(b) | C33: Responsible investments | D33: Continuous improvement of the reporting of the University’s sustainability-related investment profile metrics, including investment in climate mitigation and transition solutions, and compliance with related obligations (eg UNPRI). | E33: M | F33: $ and % AUM invested in climate/transition solution | H33: Both | I33: "Continuous improvement" wording makes it desirable to have a quantitative comparison metrics. However i also acknowledge that this target is mainly a qualitative target
B34: EN1(b) | C34: Enablers | D34: Living laboratories enabling applied learning, research and operational sustainability outcomes | E34: M | F34: Number of projects funded; $ project funding | H34: Both | I34: Qualitative case evidence is better to articulate the impact of living laboratories in learning, research, and operational sustainability outcomes

Sheet 3. Stakeholder map & RASCI
A1: ↑ | B1: End-2026 target status assessment and reporting
B2: 3. Stakeholder map & RASCI
B4: SR26 unit | C4: SR26 full name | D4: SR25 equivalent (2025 master) | E4: Section / team | F4: Key contact | G4: Status / notes
B5: Faculty | C5: Faculty of Architecture, Building and Planning | D5: Faculties tab – ABP | E5: Associate Dean Sustainability / faculty sustainability lead | F5: TBC | G5: Pilot faculty
B6: Faculty | C6: Faculty of Arts | D6: Faculties tab – ARTS | E6: Associate Dean Sustainability / faculty sustainability lead | F6: TBC | G6: Pilot faculty
B7: Faculty | C7: Faculty of Business and Economics | D7: Faculties tab – FBE | E7: Associate Dean Sustainability / faculty sustainability lead | F7: TBC | G7: Pilot faculty
B8: Faculty | C8: Faculty of Science | D8: Faculties tab – SCI | E8: Associate Dean Sustainability / faculty sustainability lead | F8: TBC | G8: Pilot faculty
B9: CI&S | C9: Commercial, Infrastructure & Sustainability (CI&S) | D9: Corporate Development (CD Development & Estate Planning teams; CD Sustainability Strategy) | E9: CI&S – Estate Planning & Development (TBC: confirm with Gerard) | F9: TBC
B10: CI&S | C10: Commercial, Infrastructure & Sustainability (CI&S) | D10: Corporate Development (CD Development & Estate Planning teams; CD Sustainability Strategy) | E10: CI&S – Sustainability Strategy (incl. CLLAP) | F10: TBC
B11: CFOG | C11: Chief Finance Officer Group (CFOG) | D11: CFOG (Procurement; Accounting; Treasury & Investments; Enterprise Portfolio & Investments) | E11: CFOG – Procurement | F11: TBC
B12: CFOG | C12: Chief Finance Officer Group (CFOG) | D12: CFOG (Procurement; Accounting; Treasury & Investments; Enterprise Portfolio & Investments) | E12: CFOG – Treasury & Investments | F12: TBC
B13: ESG | C13: Enterprise Services Group (ESG) | D13: Business Services – Sustainability Delivery (nature & biodiversity, waste & circular economy, part of quant. climate leadership) | E13: ESG – Campus Operations & Sustainability Delivery | F13: TBC
B14: CIOG | C14: Chief Information Officer Group (CIOG) | D14: Business Services (AI – not requested in SR25) | E14: CIOG – Responsible AI & digital | F14: TBC
B15: MRE | C15: Melbourne Research and Enterprise (MRE) | D15: Chancellery Research and Enterprise | E15: MRE – Research (incl. MBI – TBC) | F15: TBC
B16: Chancellery | C16: Advancement, Communications & Marketing; Global, Culture & Engagement; Education (incl. SASS); Indigenous | D16: Chancellery tab | E16: — | F16: TBC | G16: No SR26 qualitative indicator currently names these units. SASS (Melbourne Plus) referenced for EE1(c). Confirm whether requests are needed.
B17: Legal & Risk | C17: Legal and Risk | D17: Legal and Risk tab | E17: — | F17: TBC | G17: No SR26 indicator currently assigned – may be relevant to climate resilience maturity (CL3(a)). TBC.
B18: TBC | C18: CGOP / CDEP / CDSS | D18: Not in SR25 master | E18: — | F18: TBC | G18: Structure changes TBC – confirm before requests are issued.
B20: RASCI – who receives a request for each indicator (R = Responsible to report; TBC = to confirm)
B21: Ref | C21: Priority area | D21: Indicator | E21: ABP | F21: ARTS | G21: FBE | H21: SCI | I21: CI&S | J21: CFOG | K21: ESG | L21: CIOG | M21: MRE
B22: EE1(a) | C22: Exceptional education | D22: Evidence of innovative approaches to sustainability teaching and learning | E22: R | F22: R | G22: R | H22: R | I22: R
B23: EE1(b) | C23: Exceptional education | D23: Pilots of possible approaches for understanding and developing students’ sustainability self-efficacy | E23: R | F23: R | G23: R | H23: R | I23: R
B24: EE1(c) | C24: Exceptional education | D24: Evidence of sustainability focused experiential and co curricular learning (eg Wattle Fellowship; Melbourne Plus) | E24: R | F24: R | G24: R | H24: R | I24: R
B25: EE1(d) | C25: Exceptional education | D25: Alumni profiles demonstrating how graduates contribute to sustainability through their careers or communities. | E25: R | F25: R | G25: R | H25: R | I25: R
B26: TR1(a) | C26: Transformational research | D26: Expert-reviewed evidence of researchers contributing to operational sustainability priorities through partnerships, advisory input, living labs, applied projects or decision-support | E26: R | F26: R | G26: R | H26: R | I26: R
B27: TR1(b) | C27: Transformational research | D27: Evidence of institutional pathways that enable ongoing collaboration between academic and professional staff | E27: R | F27: R | G27: R | H27: R
B28: TR1(c) | C28: Transformational research | D28: Expert assessment of the quality, relevance and continuity of these collaborations | E28: R | F28: R | G28: R | H28: R
B29: TR1(d) | C29: Transformational research | D29: Periodic feedback from participants on the effectiveness and mutual benefit of collaboration mechanisms. | E29: R | F29: R | G29: R | H29: R
B30: TR2(a) | C30: Transformational research | D30: Evidence of sustainability-related research impact across diverse pathways, could include policy, industry, community, practice, cultural and institutional outcomes | E30: R | F30: R | G30: R | H30: R
B31: TR2(b) | C31: Transformational research | D31: Documented progress of relevant strategic initiatives, including Impact Accelerators
B32: TR2(c) | C32: Transformational research | D32: Expert-reviewed summary of sustainability-related research outputs, outcomes and influence using available institutional evidence sources | M32: R
B33: TR2(d) | C33: Transformational research | D33: Case-based evidence demonstrating how research has contributed to meaningful sustainability outcomes. | E33: R | F33: R | G33: R | H33: R | I33: R
B34: TR3(a) | C34: Transformational research | D34: Evidence that sustainability considerations are integrated into relevant research systems, planning processes, guidance, training, induction or support services | E34: R | F34: R | G34: R | H34: R | I34: R
B35: TR3(b) | C35: Transformational research | D35: Demonstrated examples of more sustainable research practices in laboratories, fieldwork, procurement, travel or infrastructure use | E35: R | F35: R | G35: R | H35: R | I35: R | J35: R
B36: TR3(c) | C36: Transformational research | D36: Evidence of progress in sustainability-related research culture, capability and awareness, informed by periodic staff and graduate researcher surveys | E36: R | F36: R | G36: R | H36: R
B37: TR3(d) | C37: Transformational research | D37: Expert assessment of progress in embedding sustainable research practices across the institution. | E37: R | F37: R | G37: R | H37: R
B38: CL1(a) | C38: Climate leadership | D38: Annual Greenhouse Gas Inventory (including emissions scopes 1, 2 and 3) demonstrates carbon emission reductions, including maintaining procurement of 100% renewable electricity for all scope 2 sources[1]
B39: CL1(b) | C39: Climate leadership | D39: Development of Greenhouse Gas intensity metrics
B40: CL1(c) | C40: Climate leadership | D40: Review of Climate Leadership targets by 2030.[2] | I40: R
B41: CL2(a) | C41: Climate leadership | D41: By 2028, develop and document institutional mapping of research and education activities that are designed to contribute to global decarbonisation | E41: R | F41: R | G41: R | H41: R | I41: R
B42: CL2(b) | C42: Climate leadership | D42: Prioritised pipeline of decarbonisation focused research and education opportunities aligned with University emissions reduction priorities from 2028
B43: CL2(c) | C43: Climate leadership | D43: Ongoing communications that evidence the University’s climate action, research and learning to inform policy, sector and community decarbonisation efforts. | E43: R | F43: R | G43: R | H43: R
B44: CL3(a) | C44: Climate leadership | D44: Maturity assessment of the University’s preparedness for climate-related impacts and capability to respond, assessed across relevant organisational functions: o Governance and strategy o Health and safety o Business continuity o Emergency management and critical incidence management o Estate and buildings o Water management o Financial planning and reporting. | I44: R
B45: NB1(a) | C45: Nature and biodiversity | D45: Monitoring of biodiversity metrics from the Biodiversity Baseline Data Project
B46: NB1(b) | C46: Nature and biodiversity | D46: Size, health and diversity of remnant vegetation at the Dookie and Creswick campuses | K46: R
B47: NB1(c) | C47: Nature and biodiversity | D47: Defined quality measurement framework | K47: R
B48: NB1(d) | C48: Nature and biodiversity | D48: Defined and quantified campus connectivity | K48: R
B49: NB2(a) | C49: Nature and biodiversity | D49: Documented baseline nature footprint analysis | M49: R
B50: NB2(b) | C50: Nature and biodiversity | D50: Evidence of established framework to monitor and track supply-chain nature impacts over time | K50: R
B51: NB2(c) | C51: Nature and biodiversity | D51: Evidence of prioritised high risk procurement categories or suppliers for nature impact management | J51: R | K51: R
B52: AI1(a) | C52: Responsible AI | D52: Established measurement of estimated operational impacts and opportunities (eg operational impacts could include energy, water, emissions and intensity measures) | I52: R | L52: R
B53: AI1(b) | C53: Responsible AI | D53: Case studies of sustainability and AI-related education, research and collaboration activities. | I53: R | L53: R
B54: EI1(a) | C54: Estate and infrastructure | D54: Evidence of increased maturity of estate and infrastructure planning, development and operations to support the other priority areas in Sustainability 2030 | I54: R
B55: EI1(b) | C55: Estate and infrastructure | D55: Estimated sustainability impacts of the University’s estate and infrastructure capital plan to inform progress towards emissions reduction targets and other priority areas (to the extent enabled by available information) | I55: R
B56: EI1(c) | C56: Estate and infrastructure | D56: Reporting on relevant activities and impacts for the University’s major estate and infrastructure projects and programs aligned with the other priority areas in Sustainability 2030 | I56: R
B57: EI1(d) | C57: Estate and infrastructure | D57: Evidence of understanding and integration of Indigenous approaches to sustainability in estate planning and development programs and projects. | I57: R
B58: CE1(a) | C58: Circular economy | D58: Comparison of year-to-year tonnes of waste (absolute).
B59: CE2(a) | C59: Circular economy | D59: Comparison of year-to-year tonnes of recyclables (absolute).
B60: RP1(a) | C60: Responsible procurement | D60: Case studies of maturity improvement related to responsible procurement process and systems. | J60: R
B61: RP2(a) | C61: Responsible procurement | D61: Percentage of Indigenous spend of total addressable procurement spend
B62: RP2(b) | C62: Responsible procurement | D62: Percentage of social spend of total addressable procurement spend.
B63: MS1(a) | C63: Modern slavery and human rights | D63: Annual progress reporting via the Modern Slavery Statement | I63: R | J63: R
B64: RI1(a) | C64: Responsible investments | D64: Annual monitoring and reporting on the investment portfolio’s net zero transition progress, including tracking the percentage of assets under management (AUM) managed by investment managers aligned with (or committed to) net zero by 2050
B65: RI1(b) | C65: Responsible investments | D65: Continuous improvement of the reporting of the University’s sustainability-related investment profile metrics, could include investment in climate mitigation and transition solutions, and compliance with related obligations (eg UNPRI). | I65: R | J65: R
B66: EN1(a) | C66: Enablers | D66: Evidence of sustainability outcomes informed by Indigenous knowledges | E66: R | F66: R | G66: R | H66: R
B67: EN1(b) | C67: Enablers | D67: Living laboratories enabling applied learning, research and operational sustainability outcomes | E67: R | F67: R | G67: R | H67: R | I67: R
B68: EN1(c) | C68: Enablers | D68: Coordinated internal engagement and external partnerships contributing to delivery of sustainability outcomes across priority areas. | E68: R | F68: R | G68: R | H68: R | I68: R | J68: R | K68: R | L68: R
B69: EN1(d) | C69: Enablers | D69: Sustainability objectives integrated into governance and decision‑making processes, supported by transparent reporting. | E69: R | F69: R | G69: R | H69: R | I69: R | J69: R | K69: R | L69: R

Sheet 4. Request tracker
A1: ↑ | B1: End-2026 target status assessment and reporting
B2: 4. Request tracker
B4: Summary
C5: Not sent | E5: Sent | G5: Chased | I5: Support meeting | L5: Response rate | N5: Owner confirmed
C6: =COUNTIF($N$10:$N$20,"Not sent") | E6: =COUNTIF($N$10:$N$20,"Sent") | G6: =COUNTIF($N$10:$N$20,"Chased") | I6: =COUNTIF($N$10:$N$20,"Support meeting") | L6: =IFERROR((COUNTIF($N$10:$N$20,"Received")+COUNTIF($N$10:$N$20,"Under review")+COUNTIF($N$10:$N$20,"Complete"))/(COUNTA($N$10:$N$20)-COUNTIF($N$10:$N$20,"Not required")),0) | N6: =COUNTIF($M$10:$M$20,"Yes")&" / "&COUNTA($C$10:$C$20)
C7: Received | E7: Under review | G7: Complete | I7: Not required
C8: =COUNTIF($N$10:$N$20,"Received") | E8: =COUNTIF($N$10:$N$20,"Under review") | G8: =COUNTIF($N$10:$N$20,"Complete") | I8: =COUNTIF($N$10:$N$20,"Not required")
B9: # | C9: Group | D9: Unit / section | E9: Key contact | F9: No. of indicators requested | G9: Request workbook | H9: Date sent | I9: Due date | J9: Reminder date | K9: Support meeting offered/held | L9: Response received | M9: Owner confirmed | N9: Status | O9: Days overdue | P9: Notes / follow-up
B10: F1 | C10: Faculty | D10: ABP – Faculty of Architecture, Building and Planning | E10: TBC | F10: 20 | G10: ABP - end-2026 sustainability reporting request.xlsx | I10: 46402 | J10: =IF(I10="","",I10-7) | N10: Not sent | O10: =IF(OR(I10="",L10<>""),"",MAX(0,TODAY()-I10))
B11: F2 | C11: Faculty | D11: ARTS – Faculty of Arts | E11: TBC | F11: 20 | G11: ARTS - end-2026 sustainability reporting request.xlsx | I11: 46402 | J11: =IF(I11="","",I11-7) | N11: Not sent | O11: =IF(OR(I11="",L11<>""),"",MAX(0,TODAY()-I11))
B12: F3 | C12: Faculty | D12: FBE – Faculty of Business and Economics | E12: TBC | F12: 20 | G12: FBE - end-2026 sustainability reporting request.xlsx | I12: 46402 | J12: =IF(I12="","",I12-7) | N12: Not sent | O12: =IF(OR(I12="",L12<>""),"",MAX(0,TODAY()-I12))
B13: F4 | C13: Faculty | D13: SCI – Faculty of Science | E13: TBC | F13: 20 | G13: SCI - end-2026 sustainability reporting request.xlsx | I13: 46402 | J13: =IF(I13="","",I13-7) | N13: Not sent | O13: =IF(OR(I13="",L13<>""),"",MAX(0,TODAY()-I13))
B14: C1 | C14: Central | D14: CI&S – Estate Planning & Development (TBC: confirm with Gerard) | E14: TBC | F14: 5 | G14: CIandS - end-2026 sustainability reporting request.xlsx | I14: 46402 | J14: =IF(I14="","",I14-7) | N14: Not sent | O14: =IF(OR(I14="",L14<>""),"",MAX(0,TODAY()-I14))
B15: C2 | C15: Central | D15: CI&S – Sustainability Strategy (incl. CLLAP) | E15: TBC | F15: 17 | G15: CIandS - end-2026 sustainability reporting request.xlsx | I15: 46402 | J15: =IF(I15="","",I15-7) | N15: Not sent | O15: =IF(OR(I15="",L15<>""),"",MAX(0,TODAY()-I15))
B16: C3 | C16: Central | D16: CFOG – Procurement | E16: TBC | F16: 6 | G16: CFOG - end-2026 sustainability reporting request.xlsx | I16: 46402 | J16: =IF(I16="","",I16-7) | N16: Not sent | O16: =IF(OR(I16="",L16<>""),"",MAX(0,TODAY()-I16))
B17: C4 | C17: Central | D17: CFOG – Treasury & Investments | E17: TBC | F17: 1 | G17: CFOG - end-2026 sustainability reporting request.xlsx | I17: 46402 | J17: =IF(I17="","",I17-7) | N17: Not sent | O17: =IF(OR(I17="",L17<>""),"",MAX(0,TODAY()-I17))
B18: C5 | C18: Central | D18: ESG – Campus Operations & Sustainability Delivery | E18: TBC | F18: 7 | G18: ESG - end-2026 sustainability reporting request.xlsx | I18: 46402 | J18: =IF(I18="","",I18-7) | N18: Not sent | O18: =IF(OR(I18="",L18<>""),"",MAX(0,TODAY()-I18))
B19: C6 | C19: Central | D19: CIOG – Responsible AI & digital | E19: TBC | F19: 4 | G19: CIOG - end-2026 sustainability reporting request.xlsx | I19: 46402 | J19: =IF(I19="","",I19-7) | N19: Not sent | O19: =IF(OR(I19="",L19<>""),"",MAX(0,TODAY()-I19))
B20: C7 | C20: Central | D20: MRE – Research (incl. MBI – TBC) | E20: TBC | F20: 2 | G20: MRE - end-2026 sustainability reporting request.xlsx | I20: 46402 | J20: =IF(I20="","",I20-7) | N20: Not sent | O20: =IF(OR(I20="",L20<>""),"",MAX(0,TODAY()-I20))

Sheet Faculties
A1: ↑ | B1: End-2026 target status assessment and reporting
B2: Faculties
B3: Consolidated responses – paste from returned request workbooks (identical column layout). Click [+] above Columns H–K for end-2025 responses.
B5: 1.1 ABP – Faculty of Architecture, Building and Planning
C7: Sustainability 2030 target and indicator | H7: End-2025 reporting (for reference – click [+] above to expand) | L7: End-2026 reporting (PLEASE COMPLETE THIS SECTION)
B8: Ref | C8: Priority area | D8: Sustainability 2030 target | E8: Indicator | F8: 2026 Reporting request | G8: How SST will use this data | H8: Related SR25 ref | I8: End-2025 confirmed status | J8: End-2025 reporting response | K8: Links and supporting information | L8: Confirm end-2026 target status | M8: OPTION 1: Target-level reporting (Column D) | N8: OPTION 2: Indicator level reporting (Column E/F) | O8: Supporting information/comments | P8: Data source and limitations | Q8: Data owner confirms information is accurate | R8: Confirmed by (name, role, date)
L9: (Met or exceeded; partially met; not met; not yet started) | M9: Provide further evidence of target status assessment in the form of: A general update on activities in relation to the overarching target (Column D) | N9: Provide further evidence of target status assessment in the form of: Data and commentary in direct response to the reporting request (Column F) | O9: Provide any additional information to support the target status assessment (e.g. links, images, rationale for selection of target status) | P9: Where did this information come from (system, report, survey, person)? Note any gaps or limitations. | Q9: Select 'Yes' to confirm the information provided is accurate and can be used for reporting | R9: Name, role and date of the person confirming
B10: EE1(a) | C10: Exceptional education | D10: Provide our students with learning experiences that help them build the knowledge, skills and relationships to lead change for sustainable societies. | E10: Evidence of innovative approaches to sustainability teaching and learning | F10: In end-2025 reporting your faculty reported on the related SP2030 target 4a(ii) and rated it 'Partially met' (see Column J – click [+] above Columns H–K). Please build on this rather than repeating it, focusing on what is new in 2026. Please provide one or two examples from 2026 of innovative approaches your faculty has used to embed sustainability in teaching and learning (e.g. new or redesigned subjects, curriculum design, pedagogies, assessment approaches or learning resources). Include links to subject pages or resources where available. A full list of subjects is not required. | G10: We will collate examples of innovative sustainability teaching and learning across faculties to inform the Exceptional education section of the 2026 Sustainability Report, and select one or two for short case studies. | H10: 4a(ii) | I10: Partially met | J10: The Faculty has continued to make substantial and discipline-wide progress in embedding sustainability into the curriculum in ways that extend well beyond baseline requirements, ensuring that students critically engage with both the beneficial and harmful impacts of the built environment on environmental and human systems. A central mechanism for this work in 2025 has been the forward planning and strategic renewal of all Master’s programs across the Faculty, led by Professor Dan Hill under the Designing Futures strategy. This process goes beyond incremental subject updates and instead focuses on holistic program-level reform, explicitly positioning sustainability as a core organising principle rather than an add-on topic. In practice, this has involved structured, discipline-specific workshops bringing together all academic staff within each program to reflect on: - the current state of sustainability integration across subjects, - emerging societal, environmental and industry challenges, - the skills and capabilities graduates will require to respond responsibly and effectively, - how sustainability is communicated, scaffolded and reinforced across the program. A recent example is the Master of Construction Management, where a half-day, facilitated workshop brought together the full academic teaching team to collectively review the program’s direction. Guided by Professor Hill, the session examined course narratives, subject sequencing, learning outcomes and focus areas, with particular attention to how issues such as embodied carbon, circular construction, climate risk, systems thinking and ethical responsibility are integrated throughout the degree. The outcome of this process is a clearer, more coherent approach to sustainability that is embedded across core and specialist subjects, rather than confined to standalone units. Complementing this program-level work, the Faculty has continued the development of two new sustainability-focused subjects—one at undergraduate level and one at graduate level—both designed to foster interdisciplinary, applied engagement with climate and sustainability challenges. Ongoing curriculum mapping across programs further supports this effort by identifying sustainability-rich learning pathways and informing both subject development and student advising. Together, these initiatives demonstrate a deliberate and sustained commitment to embedding sustainability deeply and coherently across the curriculum, ensuring that graduates across all disciplines develop a critical understanding of the environmental and human systems they shape through professional practice.
B11: EE1(b) | C11: Exceptional education | D11: Provide our students with learning experiences that help them build the knowledge, skills and relationships to lead change for sustainable societies. | E11: Pilots of possible approaches for understanding and developing students’ sustainability self-efficacy | F11: Has your faculty piloted or trialled any approach in 2026 to understand or build students' confidence and capability to act on sustainability (sustainability self-efficacy)? If yes, briefly describe the approach, participating cohort, what was learned and next steps. If not, please respond 'none in 2026' – this is a new indicator and a nil response is useful. We are aware of the Sustainability Strengths Compass Living Lab project (CLLAP) and will collect it separately. | G11: This is a new indicator. We will use responses to establish a baseline of how (and whether) faculties are understanding student sustainability self-efficacy, and report on early pilots in the 2026 Sustainability Report. A nil response is useful to us. | H11: N/A – new indicator
B12: EE1(c) | C12: Exceptional education | D12: Provide our students with learning experiences that help them build the knowledge, skills and relationships to lead change for sustainable societies. | E12: Evidence of sustainability focused experiential and co curricular learning (eg Wattle Fellowship; Melbourne Plus) | F12: Please list any sustainability-focused experiential or co-curricular learning opportunities your faculty offered or supported in 2026 (e.g. industry or community projects, fieldwork, internships, student challenges), with approximate student participation where known and a one-line description of outcomes. We will collect Wattle Fellowship and Melbourne Plus information centrally – please only include these if your faculty ran a specific activity. | G12: We will combine faculty examples with central Wattle Fellowship and Melbourne Plus data to report on the range and reach of sustainability-focused experiential and co-curricular learning across the University. | H12: N/A – new indicator
B13: EE1(d) | C13: Exceptional education | D13: Provide our students with learning experiences that help them build the knowledge, skills and relationships to lead change for sustainable societies. | E13: Alumni profiles demonstrating how graduates contribute to sustainability through their careers or communities. | F13: In end-2025 reporting your faculty reported on the related SP2030 target 4b(i) and rated it 'Partially met' (see Column J – click [+] above Columns H–K). Please build on this rather than repeating it, focusing on what is new in 2026. Please nominate up to two alumni from your faculty whose careers or community work demonstrate how they apply sustainability knowledge and skills (name, course and graduating year, a short summary, a link to a profile if available, and whether consent to be featured is likely). If your faculty tracks sustainability-related graduate outcomes in any way, please briefly describe how. | G13: We will use nominated alumni to develop short graduate profiles for the 2026 Sustainability Report (subject to consent), and record any faculty approaches to tracking graduate outcomes to inform how this indicator is measured from 2027. | H13: 4b(i) | I13: Partially met | J13: The Faculty recognises the importance of understanding how graduates develop the capabilities required to shape, lead and succeed in sustainable societies. At present, however, there is no single quantitative metric that adequately captures graduate sustainability capability across the breadth and depth of the Faculty’s programs. While subject completions with sustainability-related content are sometimes used as a proxy indicator, the Faculty continues to view this as a limited and potentially misleading measure. Sustainability capability at ABP is increasingly developed through integrated curricula, studio-based learning, project work, and practice-oriented engagement, where sustainability is embedded in learning outcomes, assessment criteria, and decision-making processes rather than delivered as discrete content that can be easily counted. In 2025, the Faculty has focused on strengthening the conditions through which graduate sustainability capability is developed, rather than prematurely formalising narrow metrics. These conditions include: - Program-level curriculum renewal and forward planning, particularly across Master’s programs, where sustainability is being positioned as a core professional capability tied to leadership, systems thinking, ethical responsibility, and decision-making under uncertainty. - Authentic, practice-facing learning experiences, including studios, applied research projects, and design-make activities that require students to engage directly with issues such as embodied carbon, circular material flows, climate risk, and environmental performance. - Co-curricular and non-formal learning opportunities, such as sustainability-focused workshops delivered alongside major events (e.g. ASA2025), where students and early-career researchers build practical skills in environmental sensing, life cycle assessment, and data-informed sustainability decision-making. - Recognition and visibility of sustainability leadership, including student engagement within Sustainability Award–related initiatives and Living Lab projects, which model leadership pathways and professional norms around sustainability. The Faculty acknowledges that these outcomes are not yet systematically captured through a formal reporting framework. Over time, ABP intends to develop more meaningful indicators of graduate sustainability capability, potentially combining curriculum mapping, assessment alignment, graduate destination insights, and qualitative exemplars of student work. This will support more robust reporting in future Sustainability Plan refresh cycles, while ensuring that measurement aligns with the complexity and integrated nature of sustainability education within the built environment disciplines.
B14: TR1(a) | C14: Transformational research | D14: Utilise the expertise of the University’s researchers through mutually beneficial partnerships to help address the University’s operational sustainability challenges. | E14: Expert-reviewed evidence of researchers contributing to operational sustainability priorities through partnerships, advisory input, living labs, applied projects or decision-support | F14: In end-2025 reporting your faculty reported on the related SP2030 target 2a and rated it 'Met or exceeded' (see Column J – click [+] above Columns H–K). Please build on this rather than repeating it, focusing on what is new in 2026. Please provide up to two examples from 2026 of researchers in your faculty contributing to the University's own operational sustainability challenges (e.g. advising on campus energy, biodiversity, waste or buildings; applied projects; decision-support tools). For each, briefly describe the operational challenge, the researcher's contribution, the University team involved and the result. We will collect Campus Living Lab Accelerator Program (CLLAP) projects separately from CI&S – please include other examples only. | G14: We will report on examples of researchers helping solve the University's own operational sustainability challenges, alongside CLLAP projects reported by CI&S, and share them with operational teams to identify further collaboration. | H14: 2a | I14: Met or exceeded | J14: Across 2025, the Faculty of Architecture, Building and Planning has significantly strengthened and formalised its Living Labs approach, building on progress reported at mid-year and embedding sustainability experimentation as a core mode of practice across teaching, research, and operations. A major development in the second half of 2025 was the establishment of the ABP Sustainability Grant. This new internal funding scheme provides up to $10,000 annually to catalyse staff-led, cross-disciplinary sustainability initiatives that operate as Living Labs within the Faculty. The scheme supports projects that use real faculty contexts—spaces, systems, practices, and communities—as testbeds for sustainability innovation, with strong encouragement for student involvement, particularly graduate researchers. The Sustainability Grant marks a shift from ad hoc Living Lab activity toward a curated, faculty-wide framework that empowers staff to design, trial, and document practical sustainability interventions. The inaugural funding round attracted multiple applications from across disciplines and professional areas, and a formal selection process is currently underway, demonstrating strong engagement and appetite for Living Lab activity within ABP. In parallel, the Faculty has continued to develop and refine larger-scale Living Lab concepts at the precinct level. While the delivery of the Fishermans Bend campus project has been postponed, the Faculty remains committed to a Living Lab approach and has retained and further clarified the conceptual and methodological groundwork. This positions the Faculty to rapidly mobilise Living Lab activities once the project recommences, ensuring that sustainability, circularity, and environmental performance are embedded from the earliest stages of planning and development. Collectively, these initiatives demonstrate that ABP is not only contributing to the University’s Living Labs agenda, but actively curating, resourcing, and governing Living Labs as a sustained and scalable approach to sustainability action. A flagship example of the Faculty’s Living Labs approach in 2025 is the Interactive Campus Material and Carbon Atlas, which reached completion during the year. Funded through the Learning and Teaching Initiative (LTI), the project brought together academic staff, professional colleagues, and students to map and analyse the material stock and embodied carbon of selected University buildings. The Atlas has been developed as an interactive digital tool that enables users to explore building-level data, including construction materials, embodied carbon intensities, and potential opportunities for material reuse and circularity. Importantly, the project moves beyond retrospective analysis: the underlying framework enables forward projection of material requirements and carbon implications under different development and renewal scenarios. As such, the Atlas demonstrates the value of a Living Lab that directly integrates sustainability research with campus operations. It provides a practical decision-support tool with clear relevance for estate planning, capital works prioritisation, and long-term carbon reduction strategies. With the research and development phase now complete, the Faculty is committed to working with University stakeholders to present the tool to relevant professional teams and explore pathways for embedding it into institutional planning and sustainability processes. This next phase reflects the Faculty’s intent to ensure that Living Lab outputs translate into operational insight and long-term impact, rather than remaining standalone research artefacts. Together with the newly established ABP Sustainability Grant, the Interactive Campus Material and Carbon Atlas illustrates how the Faculty is operationalising Living Labs across scales—from grassroots initiatives to faculty-wide decision-support infrastructure.
B15: TR1(b) | C15: Transformational research | D15: Utilise the expertise of the University’s researchers through mutually beneficial partnerships to help address the University’s operational sustainability challenges. | E15: Evidence of institutional pathways that enable ongoing collaboration between academic and professional staff | F15: Does your faculty have any mechanism that supports ongoing collaboration between academic and professional staff on operational sustainability (e.g. a sustainability committee with mixed membership, seed funding, a coordination role or a regular forum)? If yes, briefly describe it and how often it operates. If not, please say so. | G15: We will map existing academic–professional collaboration mechanisms across faculties to establish a baseline for this new indicator and identify models other faculties could adopt. | H15: N/A – new indicator
B16: TR1(c) | C16: Transformational research | D16: Utilise the expertise of the University’s researchers through mutually beneficial partnerships to help address the University’s operational sustainability challenges. | E16: Expert assessment of the quality, relevance and continuity of these collaborations | F16: For the collaborations described in TR1(a)–(b), please give a short assessment (a paragraph is sufficient) of their quality, relevance and continuity: are they ongoing, useful to the University's operational priorities, and producing outcomes? | G16: We will use your assessment to describe the quality and continuity of research–operations collaboration in the 2026 report, and as baseline evidence for the interim target status assessment from 2027. | H16: N/A – new indicator
B17: TR1(d) | C17: Transformational research | D17: Utilise the expertise of the University’s researchers through mutually beneficial partnerships to help address the University’s operational sustainability challenges. | E17: Periodic feedback from participants on the effectiveness and mutual benefit of collaboration mechanisms. | F17: Has your faculty collected any feedback from participants (researchers or operational staff) on how well these collaboration mechanisms work and whether they are mutually beneficial? If yes, summarise key findings and any improvements identified; if not, please say so. | G17: We will use any feedback to understand whether collaboration mechanisms are working and to inform improvements. Where none has been collected, this helps us plan how to gather feedback from 2027. | H17: N/A – new indicator
B18: TR2(a) | C18: Transformational research | D18: Deliver high-quality research and partnerships that contribute to sustainability outcomes and demonstrable societal benefit. | E18: Evidence of sustainability-related research impact across diverse pathways, could include policy, industry, community, practice, cultural and institutional outcomes | F18: In end-2025 reporting your faculty reported on the related SP2030 target 5b(i) and rated it 'Met or exceeded' (see Column J – click [+] above Columns H–K). Please build on this rather than repeating it, focusing on what is new in 2026. Please provide one or two examples from 2026 of sustainability-related research from your faculty that has had impact beyond academia – on policy, industry, community, practice, cultural or institutional outcomes. For each, briefly describe the research, the partner or user, and the resulting change or influence, with links (e.g. Pursuit articles, policy submissions, reports). We will source University-wide research metrics (e.g. SDG-mapped publications via SciVal) from MRE – publication counts are not required. | G18: We will collate research impact examples across faculties to show the breadth of sustainability-related research impact in the Transformational research section of the 2026 Sustainability Report, complementing University-wide metrics from MRE. | H18: 5b(i) | I18: Met or exceeded | J18: The Faculty continues to be a national and international leader in sustainability research across the built environment, supported by a diverse ecosystem of specialist research hubs, laboratories, and collaborative initiatives. Together, these centres span disciplinary and interdisciplinary research, linking fundamental inquiry with applied outcomes that inform practice, policy, and industry transformation. Sustainability-, climate-, and environment-focused research institutes and hubs within the Faculty include: - Melbourne Centre for Cities – urban governance, policy innovation, and climate-responsive city-making - InfUr – Informal Urbanism Research Hub – environmental justice, resilience, and community-led urbanism - Transport, Health and Urban Design (THUD) – healthy and sustainable cities through mobility and planning research - Urban Ecology and Design Lab (UED Lab) – ecological design strategies, biodiversity, and nature-based solutions - Sustainable and Healthy Environments (SHE) Lab – materials, thermal comfort, indoor environmental quality, and health–environment linkages - The Retrofit Lab – decarbonisation of existing building stock, circular design, and retrofit decision-making - Advanced Digital Design + Fabrication – sustainable construction, digital materials, and low-carbon manufacturing These research hubs collectively contribute to advancing knowledge across design, planning, construction, and policy, while also creating pathways for translation into real-world impact. A flagship example of the Faculty’s research impact in 2025 is Beyond EPiC, a research-led spin-off emerging from long-standing work within the Faculty on life cycle assessment (LCA), embodied carbon, and environmental performance of the built environment. Beyond EPiC provides a clear example of how the Faculty’s sustainability research translates into action and impact at scale. Emerging directly from decades of peer-reviewed research at the University of Melbourne, Beyond EPiC develops environmental data, digital tools, and applied insights that help architects, engineers, planners, developers, and policymakers make evidence-based decisions across the built environment. Grounded in internationally recognised hybrid life cycle assessment (LCA) methodologies, Beyond EPiC transforms complex environmental research into clear, consistent, and actionable intelligence—maintaining scientific rigour while enabling real-world application. This approach exemplifies the Faculty’s ethos of where science meets the design of buildings and cities. A key research impact in 2025 has been direct policy influence. Beyond EPiC’s embodied carbon data underpins the BASIX Materials Index used by the New South Wales Government for residential development applications. Every project lodged under BASIX must report embodied emissions using these coefficients, making Beyond EPiC’s research a core component of the state’s environmental compliance framework. Since this integration, tens of thousands of homes have been designed and certified using Beyond EPiC data, driving lower-impact material choices and design optimisation at scale. This represents a significant shift from sustainability research as advisory input to sustainability research as embedded policy infrastructure, shaping decisions across an entire construction sector. Beyond EPiC’s impact extends beyond regulation. Its tools and datasets support industry training, consulting, and early-stage design decision-making, enabling practitioners to compare materials, optimise assemblies, and understand embodied carbon trade-offs in ways that were previously inaccessible. This creates a continuous feedback loop between research, teaching, practice, and policy—ensuring that academic inquiry remains responsive to real-world constraints while raising the baseline of environmental accountability. As such, Beyond EPiC exemplifies the Faculty’s model of sustainability research impact: scientifically rigorous, trusted by government, used at scale, and capable of shaping policy, professional practice, and environmental outcomes simultaneously. | K18: www.beyondepic.io
B19: TR2(d) | C19: Transformational research | D19: Deliver high-quality research and partnerships that contribute to sustainability outcomes and demonstrable societal benefit. | E19: Case-based evidence demonstrating how research has contributed to meaningful sustainability outcomes. | F19: In end-2025 reporting your faculty reported on the related SP2030 target 5b(i) and rated it 'Met or exceeded' (see Column J – click [+] above Columns H–K). Please build on this rather than repeating it, focusing on what is new in 2026. Please provide one case study (up to 300 words) of a research project from your faculty that has contributed to a meaningful sustainability outcome: the research, stakeholders involved, pathway to impact and evidence of the outcome. This can be one of the examples from TR2(a), developed in more detail. We are also seeking examples from Melbourne Climate Futures, the Melbourne Biodiversity Institute and Strategic Communications. | G19: We will select the strongest examples to develop as full research case studies for the 2026 Sustainability Report (we may contact you for more detail and images). | H19: 5b(i) | I19: Met or exceeded | J19: The Faculty continues to be a national and international leader in sustainability research across the built environment, supported by a diverse ecosystem of specialist research hubs, laboratories, and collaborative initiatives. Together, these centres span disciplinary and interdisciplinary research, linking fundamental inquiry with applied outcomes that inform practice, policy, and industry transformation. Sustainability-, climate-, and environment-focused research institutes and hubs within the Faculty include: - Melbourne Centre for Cities – urban governance, policy innovation, and climate-responsive city-making - InfUr – Informal Urbanism Research Hub – environmental justice, resilience, and community-led urbanism - Transport, Health and Urban Design (THUD) – healthy and sustainable cities through mobility and planning research - Urban Ecology and Design Lab (UED Lab) – ecological design strategies, biodiversity, and nature-based solutions - Sustainable and Healthy Environments (SHE) Lab – materials, thermal comfort, indoor environmental quality, and health–environment linkages - The Retrofit Lab – decarbonisation of existing building stock, circular design, and retrofit decision-making - Advanced Digital Design + Fabrication – sustainable construction, digital materials, and low-carbon manufacturing These research hubs collectively contribute to advancing knowledge across design, planning, construction, and policy, while also creating pathways for translation into real-world impact. A flagship example of the Faculty’s research impact in 2025 is Beyond EPiC, a research-led spin-off emerging from long-standing work within the Faculty on life cycle assessment (LCA), embodied carbon, and environmental performance of the built environment. Beyond EPiC provides a clear example of how the Faculty’s sustainability research translates into action and impact at scale. Emerging directly from decades of peer-reviewed research at the University of Melbourne, Beyond EPiC develops environmental data, digital tools, and applied insights that help architects, engineers, planners, developers, and policymakers make evidence-based decisions across the built environment. Grounded in internationally recognised hybrid life cycle assessment (LCA) methodologies, Beyond EPiC transforms complex environmental research into clear, consistent, and actionable intelligence—maintaining scientific rigour while enabling real-world application. This approach exemplifies the Faculty’s ethos of where science meets the design of buildings and cities. A key research impact in 2025 has been direct policy influence. Beyond EPiC’s embodied carbon data underpins the BASIX Materials Index used by the New South Wales Government for residential development applications. Every project lodged under BASIX must report embodied emissions using these coefficients, making Beyond EPiC’s research a core component of the state’s environmental compliance framework. Since this integration, tens of thousands of homes have been designed and certified using Beyond EPiC data, driving lower-impact material choices and design optimisation at scale. This represents a significant shift from sustainability research as advisory input to sustainability research as embedded policy infrastructure, shaping decisions across an entire construction sector. Beyond EPiC’s impact extends beyond regulation. Its tools and datasets support industry training, consulting, and early-stage design decision-making, enabling practitioners to compare materials, optimise assemblies, and understand embodied carbon trade-offs in ways that were previously inaccessible. This creates a continuous feedback loop between research, teaching, practice, and policy—ensuring that academic inquiry remains responsive to real-world constraints while raising the baseline of environmental accountability. As such, Beyond EPiC exemplifies the Faculty’s model of sustainability research impact: scientifically rigorous, trusted by government, used at scale, and capable of shaping policy, professional practice, and environmental outcomes simultaneously. | K19: www.beyondepic.io
B20: TR3(a) | C20: Transformational research | D20: Embed sustainability within research systems, processes, capability and culture, so research is conducted responsibly, efficiently and with reduced environmental impact. | E20: Evidence that sustainability considerations are integrated into relevant research systems, planning processes, guidance, training, induction or support services | F20: In end-2025 reporting your faculty reported on the related SP2030 target 5c(ii) and rated it 'Partially met' (see Column J – click [+] above Columns H–K). Please build on this rather than repeating it, focusing on what is new in 2026. Please describe how sustainability considerations are built into your faculty's research systems or support – e.g. research planning or approval processes, guidance, graduate researcher induction or training, grant development support. Please highlight any new or improved process introduced in 2026. | G20: We will report on how sustainability is being built into research systems and support across the University, and use responses to establish a baseline for this new target. | H20: 5c(ii) | I20: Partially met | J20: The Faculty has taken deliberate and strategic steps in 2025 to strengthen how sustainability considerations shape research practices and activities. This has focused on making sustainability explicit, visible, and rewarded within the Faculty’s research culture, while building the foundations for longer-term embedding across disciplines. A major development has been the introduction of formal recognition and incentive mechanisms that foreground sustainability in research excellence. The ABP Sustainability Award, embedded within the Faculty’s Engagement, Culture, Innovation, and Impact awards program, recognises academic and professional staff who demonstrate leadership in integrating sustainability into research practices. By celebrating approaches such as life cycle thinking, low-carbon methodologies, resource efficiency, and collaborative research models, the award signals that sustainability is a core dimension of research quality and impact within ABP. This cultural shift is reinforced through the ABP Sustainability Grants Program, which supports staff-led projects that actively trial new ways of embedding sustainability into research, teaching, and operational contexts. Grant criteria encourage interdisciplinary collaboration and require applicants to engage directly with the environmental implications of their activities—supporting experimentation, documentation, and knowledge-sharing around more sustainable research practices. In parallel, Faculty researchers continue to advance methodological leadership that enables more sustainable decision-making in research and practice. Work on hybrid life cycle assessment (LCA), embodied carbon accounting, and environmental benchmarking—particularly through collaborations with Beyond EPiC—has expanded the tools available to researchers, industry, and government to measure and reduce environmental impacts. These methods increasingly inform how research questions are framed, evaluated, and translated into policy and practice. Together, these initiatives reflect a maturing research culture in which sustainability is increasingly normalised, recognised, and actively shaped through incentives, methods, and shared expectations. While this work will continue to evolve and scale, 2025 represents a clear step change in positioning sustainability as a defining feature of responsible research practice within the Faculty.
B21: TR3(b) | C21: Transformational research | D21: Embed sustainability within research systems, processes, capability and culture, so research is conducted responsibly, efficiently and with reduced environmental impact. | E21: Demonstrated examples of more sustainable research practices in laboratories, fieldwork, procurement, travel or infrastructure use | F21: In end-2025 reporting your faculty reported on the related SP2030 target 5c(ii) and rated it 'Partially met' (see Column J – click [+] above Columns H–K). Please build on this rather than repeating it, focusing on what is new in 2026. Are there any efforts within the faculty to make research practices more sustainable (e.g. green lab certification, equipment sharing, reduced research travel, sustainable fieldwork, sustainable procurement of research consumables)? If so, please describe up to two examples and any evidence of uptake, resource savings or emissions reductions. | G21: We will report on ways the University is making research practices more sustainable in the 2026 Sustainability Report, and share practical examples (e.g. green labs) across faculties. | H21: 5c(ii) | I21: Partially met | J21: The Faculty has taken deliberate and strategic steps in 2025 to strengthen how sustainability considerations shape research practices and activities. This has focused on making sustainability explicit, visible, and rewarded within the Faculty’s research culture, while building the foundations for longer-term embedding across disciplines. A major development has been the introduction of formal recognition and incentive mechanisms that foreground sustainability in research excellence. The ABP Sustainability Award, embedded within the Faculty’s Engagement, Culture, Innovation, and Impact awards program, recognises academic and professional staff who demonstrate leadership in integrating sustainability into research practices. By celebrating approaches such as life cycle thinking, low-carbon methodologies, resource efficiency, and collaborative research models, the award signals that sustainability is a core dimension of research quality and impact within ABP. This cultural shift is reinforced through the ABP Sustainability Grants Program, which supports staff-led projects that actively trial new ways of embedding sustainability into research, teaching, and operational contexts. Grant criteria encourage interdisciplinary collaboration and require applicants to engage directly with the environmental implications of their activities—supporting experimentation, documentation, and knowledge-sharing around more sustainable research practices. In parallel, Faculty researchers continue to advance methodological leadership that enables more sustainable decision-making in research and practice. Work on hybrid life cycle assessment (LCA), embodied carbon accounting, and environmental benchmarking—particularly through collaborations with Beyond EPiC—has expanded the tools available to researchers, industry, and government to measure and reduce environmental impacts. These methods increasingly inform how research questions are framed, evaluated, and translated into policy and practice. Together, these initiatives reflect a maturing research culture in which sustainability is increasingly normalised, recognised, and actively shaped through incentives, methods, and shared expectations. While this work will continue to evolve and scale, 2025 represents a clear step change in positioning sustainability as a defining feature of responsible research practice within the Faculty.
B22: TR3(c) | C22: Transformational research | D22: Embed sustainability within research systems, processes, capability and culture, so research is conducted responsibly, efficiently and with reduced environmental impact. | E22: Evidence of progress in sustainability-related research culture, capability and awareness, informed by periodic staff and graduate researcher surveys | F22: Does your faculty have any evidence of change in sustainability-related research culture, capability or awareness – e.g. results from staff or graduate researcher surveys, or participation in capability-building events or training? Please provide a brief summary and the source. If no evidence is available, please say so. | G22: We will use any survey or capability data to describe changes in sustainability-related research culture. Where no evidence exists, this helps us plan University-wide measurement (e.g. staff and graduate researcher surveys) from 2027. | H22: N/A – new indicator
B23: TR3(d) | C23: Transformational research | D23: Embed sustainability within research systems, processes, capability and culture, so research is conducted responsibly, efficiently and with reduced environmental impact. | E23: Expert assessment of progress in embedding sustainable research practices across the institution. | F23: Drawing on your responses to TR3(a)–(c), please provide a short overall assessment (2–3 sentences) of your faculty's progress in embedding sustainable research practices: where progress is strongest, the main gaps, and priority actions for 2027. | G23: We will use faculty self-assessments to identify strengths, gaps and priority actions in embedding sustainable research practices, to inform internal management reporting and the Transformational research working group. | H23: N/A – new indicator
B24: CL2(a) | C24: Climate leadership | D24: Develop understanding of our research and education programs that contribute to accelerating global decarbonisation and our own climate transition. | E24: By 2028, develop and document institutional mapping of research and education activities that are designed to contribute to global decarbonisation | F24: Please list up to three examples of 2026 communications from your faculty that showcase climate action, research or learning and aim to inform policy, sector or community decarbonisation (e.g. policy submissions, public events, media, reports). Include links, the intended audience and any reach data you have. This will also contribute to the University's mapping of decarbonisation-related research and education (due by 2028). | G24: We will use these examples to show how the University communicates climate research and learning to external audiences, and as an input to the institutional decarbonisation research and education mapping due by 2028. | H24: N/A – new indicator
B25: CL2(c) | C25: Climate leadership | D25: Develop understanding of our research and education programs that contribute to accelerating global decarbonisation and our own climate transition. | E25: Ongoing communications that evidence the University’s climate action, research and learning to inform policy, sector and community decarbonisation efforts. | F25: If not already covered in CL2(a), please list any ongoing channels or programs (e.g. event series, newsletters, podcasts, policy engagement) through which your faculty regularly communicates climate research and learning to policy, sector or community audiences. You may respond 'see CL2(a)' if already covered. We will also engage Melbourne Climate Futures and the Melbourne Energy Institute. | G25: We will report on the University's ongoing climate communications in the Climate leadership section of the 2026 Sustainability Report, alongside contributions from Melbourne Climate Futures and the Melbourne Energy Institute. | H25: N/A – new indicator
B26: EN1(a) | C26: Enablers | D26: Enablers | E26: Evidence of sustainability outcomes informed by Indigenous knowledges | F26: In end-2025 reporting your faculty reported on the related SP2030 target 6a and rated it 'Met or exceeded' (see Column J – click [+] above Columns H–K). Please build on this rather than repeating it, focusing on what is new in 2026. Please provide one case study of an activity in your faculty (education, research, engagement or operations) where Indigenous knowledges informed a sustainability outcome. Describe the activity, how Indigenous knowledges were incorporated or co-created and with whom, and the result. Please confirm that appropriate permissions are in place for sharing. | G26: We will report on the ways Indigenous knowledges inform sustainability activities across the University, and develop selected examples into case studies with appropriate permissions. | H26: 6a | I26: Met or exceeded | J26: In 2025, the Faculty has continued to deepen its engagement with sustainability through Indigenous-led and co-created learning, research, and partnerships, strengthening understanding of sustainability as a Country-centred, relational, and long-term responsibility rather than a purely technical or extractive concept. A major development is the award of an ARC Linkage Project: Co-designing Housing for First Nations Prosperity, which will commence in 2026. This project represents a significant example of sustainability research grounded in First Nations leadership, knowledge, and lived experience, operating at the intersection of architecture, housing policy, economics, and Indigenous wellbeing. Led by Associate Professor Rory Hyde and a multidisciplinary team across architecture, public health, policy and design, the project is being co-developed with First Nations organisations and partners in Shepparton, Victoria, including the Kaiela Institute, Beyond Housing, and VACCHO, alongside industry and government partners. The research places First Nations knowledge, lore, and priorities at the centre of housing design and delivery, challenging conventional Western models that have historically failed to meet cultural, social, and environmental needs. Sustainability in this project is understood holistically: as cultural continuity, social connection, climate resilience, economic viability, and care for Country. Through participatory co-design and strategic design methods, the project will produce a design catalogue and investment model that enables the delivery of housing that is affordable, culturally appropriate, climate-responsive, and socially sustaining. These outcomes directly address the Closing the Gap agenda while also offering transferable insights for broader housing challenges nationally. Complementing this work, the Faculty continues to support longstanding Indigenous-led collaborations such as Professor Alex Felson’s project on the Great Birrarung Parklands, developed in partnership with the Wurundjeri Woi Wurrung Cultural Heritage Aboriginal Corporation, the Birrarung Council, and other stakeholders. This project brings Indigenous knowledge and climate science together to explore future scenarios for the Yarra River corridor, modelling two-way learning that informs long-term ecological stewardship, governance, and design. Indigenous perspectives on sustainability are also embedded across teaching and learning in the Faculty, particularly within architecture, landscape architecture, and urban planning studios. These studios engage students with questions of Country, custodianship, and cultural practice, often in dialogue with Indigenous collaborators, reinforcing sustainability as a relational and ethical practice rather than a purely technical one. Collectively, these initiatives demonstrate that the Faculty’s approach to sustainability is increasingly shaped through Indigenous-led knowledge systems, reciprocal learning, and co-creation, contributing to more just, culturally grounded, and enduring sustainability outcomes across education, research, and practice.
B27: EN1(b) | C27: Enablers | D27: Enablers | E27: Living laboratories enabling applied learning, research and operational sustainability outcomes | F27: In end-2025 reporting your faculty reported on the related SP2030 target 2a and rated it 'Met or exceeded' (see Column J – click [+] above Columns H–K). Please build on this rather than repeating it, focusing on what is new in 2026. Please provide a case study of a living lab which operates within your faculty, including a description of its activities, who is involved (students, researchers, operational staff) and its outputs, outcomes or impact in 2026. Please note we will approach living labs funded through the Campus Living Lab Accelerator Program (CLLAP) separately. | G27: We will share examples of living labs from across the University in the 2026 Sustainability Report, alongside CLLAP projects reported by CI&S. | H27: 2a | I27: Met or exceeded | J27: Across 2025, the Faculty of Architecture, Building and Planning has significantly strengthened and formalised its Living Labs approach, building on progress reported at mid-year and embedding sustainability experimentation as a core mode of practice across teaching, research, and operations. A major development in the second half of 2025 was the establishment of the ABP Sustainability Grant. This new internal funding scheme provides up to $10,000 annually to catalyse staff-led, cross-disciplinary sustainability initiatives that operate as Living Labs within the Faculty. The scheme supports projects that use real faculty contexts—spaces, systems, practices, and communities—as testbeds for sustainability innovation, with strong encouragement for student involvement, particularly graduate researchers. The Sustainability Grant marks a shift from ad hoc Living Lab activity toward a curated, faculty-wide framework that empowers staff to design, trial, and document practical sustainability interventions. The inaugural funding round attracted multiple applications from across disciplines and professional areas, and a formal selection process is currently underway, demonstrating strong engagement and appetite for Living Lab activity within ABP. In parallel, the Faculty has continued to develop and refine larger-scale Living Lab concepts at the precinct level. While the delivery of the Fishermans Bend campus project has been postponed, the Faculty remains committed to a Living Lab approach and has retained and further clarified the conceptual and methodological groundwork. This positions the Faculty to rapidly mobilise Living Lab activities once the project recommences, ensuring that sustainability, circularity, and environmental performance are embedded from the earliest stages of planning and development. Collectively, these initiatives demonstrate that ABP is not only contributing to the University’s Living Labs agenda, but actively curating, resourcing, and governing Living Labs as a sustained and scalable approach to sustainability action. A flagship example of the Faculty’s Living Labs approach in 2025 is the Interactive Campus Material and Carbon Atlas, which reached completion during the year. Funded through the Learning and Teaching Initiative (LTI), the project brought together academic staff, professional colleagues, and students to map and analyse the material stock and embodied carbon of selected University buildings. The Atlas has been developed as an interactive digital tool that enables users to explore building-level data, including construction materials, embodied carbon intensities, and potential opportunities for material reuse and circularity. Importantly, the project moves beyond retrospective analysis: the underlying framework enables forward projection of material requirements and carbon implications under different development and renewal scenarios. As such, the Atlas demonstrates the value of a Living Lab that directly integrates sustainability research with campus operations. It provides a practical decision-support tool with clear relevance for estate planning, capital works prioritisation, and long-term carbon reduction strategies. With the research and development phase now complete, the Faculty is committed to working with University stakeholders to present the tool to relevant professional teams and explore pathways for embedding it into institutional planning and sustainability processes. This next phase reflects the Faculty’s intent to ensure that Living Lab outputs translate into operational insight and long-term impact, rather than remaining standalone research artefacts. Together with the newly established ABP Sustainability Grant, the Interactive Campus Material and Carbon Atlas illustrates how the Faculty is operationalising Living Labs across scales—from grassroots initiatives to faculty-wide decision-support infrastructure.
B28: EN1(c) | C28: Enablers | D28: Enablers | E28: Coordinated internal engagement and external partnerships contributing to delivery of sustainability outcomes across priority areas. | F28: In end-2025 reporting your faculty reported on the related SP2030 target 3a(ii) and rated it 'Met or exceeded' (see Column J – click [+] above Columns H–K). Please build on this rather than repeating it, focusing on what is new in 2026. Please list the key sustainability-focused communities of practice, internal networks or external partnerships active in your faculty in 2026 (name, partners, priority area), and provide a short description of one that has contributed to a Sustainability 2030 outcome. | G28: We will report on internal engagement and partnerships contributing to Sustainability 2030 outcomes, and update our record of sustainability-focused communities of practice and contacts across the University. | H28: 3a(ii) | I28: Met or exceeded | J28: In 2025, ABP continued to support sustainability-focused communities of practice that enable staff to learn from one another and embed sustainability across formal, non-formal, and informal learning contexts. These communities operate through a combination of structured forums, shared initiatives, and recognition mechanisms that make sustainability practice visible, valued, and transferable across the Faculty. Core to this ecosystem is the Faculty’s Climate Action Group, which continues to provide a cross-disciplinary forum for peer learning, curriculum coordination, and shared reflection on sustainability pedagogy and practice. The Group has supported sustained collaboration across academic and professional staff and has played a key role in aligning Faculty initiatives with University sustainability priorities. In 2025, the Faculty also played a leading role in hosting the Architectural Science Association (ASA) Conference, which focused strongly on sustainability, environmental performance, and design-led research. The conference was the largest attended in the 60-year history of the organisation, bringing together academics, practitioners, and industry partners from across Australia and the region. It provided a major platform for knowledge exchange on sustainability-focused teaching, research, and practice, and significantly strengthened both intra- and inter-institutional communities of practice. Complementing these collaborative forums, the Faculty introduced the ABP Sustainability Award as a mechanism for amplifying and connecting sustainability practice across teaching, research, operations, and Faculty culture. Together, these initiatives demonstrate a mature and multi-layered approach to building sustainability-focused communities of practice—combining regular peer engagement, high-impact knowledge exchange, and recognition of exemplary work to support ongoing learning and leadership in sustainability. Introduced in 2025, the ABP Sustainability Award functions as a Faculty-wide community-of-practice mechanism by recognising, showcasing, and disseminating exemplary sustainability initiatives led by academic and professional staff. Rather than operating solely as an individual award, the scheme is designed to surface transferable practices and create shared reference points for sustainability leadership across ABP. The Award recognises excellence across a broad set of criteria, including innovation and leadership, collaboration and engagement, measurable environmental outcomes, integration of sustainability into teaching and learning, influence on policy and professional practice, and contributions to a culture of sustainability within the Faculty. Eligible initiatives span teaching, research, operations, and cultural change, reflecting the diverse ways sustainability is embedded across ABP. By highlighting concrete examples of effective practice—such as projects that reduce environmental footprints, embed circularity into learning environments, or foster cross-disciplinary collaboration—the Award enables staff to learn from peers and adapt successful approaches within their own contexts. The selection process, chaired by the Assistant Dean (Sustainability) and involving senior Faculty leadership and staff representatives, further reinforces shared standards and collective ownership of sustainability goals. In this way, the Sustainability Award complements more formal communities of practice by creating a visible, Faculty-wide platform for knowledge sharing, inspiration, and peer learning. It supports sustainability not only as a technical or curricular concern, but as a shared professional and cultural endeavour.
B29: EN1(d) | C29: Enablers | D29: Enablers | E29: Sustainability objectives integrated into governance and decision‑making processes, supported by transparent reporting. | F29: Please describe how sustainability is built into your faculty's governance and decision-making – e.g. a sustainability committee or Associate Dean (Sustainability) role, a faculty sustainability action plan, sustainability criteria in planning or approvals, and how progress is reported (e.g. to the Faculty Executive). Please link the action plan if one exists. | G29: We will report on how sustainability is integrated into governance and decision-making across faculties and portfolios, and use responses as a baseline for the governance enabler from 2027. | H29: N/A – new indicator
B32: 1.2 ARTS – Faculty of Arts
C34: Sustainability 2030 target and indicator | H34: End-2025 reporting (for reference – click [+] above to expand) | L34: End-2026 reporting (PLEASE COMPLETE THIS SECTION)
B35: Ref | C35: Priority area | D35: Sustainability 2030 target | E35: Indicator | F35: 2026 Reporting request | G35: How SST will use this data | H35: Related SR25 ref | I35: End-2025 confirmed status | J35: End-2025 reporting response | K35: Links and supporting information | L35: Confirm end-2026 target status | M35: OPTION 1: Target-level reporting (Column D) | N35: OPTION 2: Indicator level reporting (Column E/F) | O35: Supporting information/comments | P35: Data source and limitations | Q35: Data owner confirms information is accurate | R35: Confirmed by (name, role, date)
L36: (Met or exceeded; partially met; not met; not yet started) | M36: Provide further evidence of target status assessment in the form of: A general update on activities in relation to the overarching target (Column D) | N36: Provide further evidence of target status assessment in the form of: Data and commentary in direct response to the reporting request (Column F) | O36: Provide any additional information to support the target status assessment (e.g. links, images, rationale for selection of target status) | P36: Where did this information come from (system, report, survey, person)? Note any gaps or limitations. | Q36: Select 'Yes' to confirm the information provided is accurate and can be used for reporting | R36: Name, role and date of the person confirming
B37: EE1(a) | C37: Exceptional education | D37: Provide our students with learning experiences that help them build the knowledge, skills and relationships to lead change for sustainable societies. | E37: Evidence of innovative approaches to sustainability teaching and learning | F37: In end-2025 reporting your faculty reported on the related SP2030 target 4a(ii) and rated it 'Partially met' (see Column J – click [+] above Columns H–K). Please build on this rather than repeating it, focusing on what is new in 2026. Please provide one or two examples from 2026 of innovative approaches your faculty has used to embed sustainability in teaching and learning (e.g. new or redesigned subjects, curriculum design, pedagogies, assessment approaches or learning resources). Include links to subject pages or resources where available. A full list of subjects is not required. | G37: We will collate examples of innovative sustainability teaching and learning across faculties to inform the Exceptional education section of the 2026 Sustainability Report, and select one or two for short case studies. | H37: 4a(ii) | I37: Partially met | J37: This target poses some specific challenges for the Faculty of Arts because we are a large and diverse entity overwhelmingly teaching academic-focused degrees—the BA, MAs and PhDs (in addition to other smaller initiatives)—across many domains in the Humanities and Social Sciences. As such, it's important to acknowledge and respect that it would not be appropriate for 'sustainability' to be integrated equally into all components in such a varied curriculum. For example, while the SSPS Capstone intensively focused on sustainability through rich and complex case-studies, this cannot be said and should not be expected of a 2nd-year subject in French. However, we have begun discussions with colleagues about putting in place a minor within the BA which we believe would be the best way of meeting this target, amongst other things. In 2026, that discussion will be further elaborated and, we hope, concretised.
B38: EE1(b) | C38: Exceptional education | D38: Provide our students with learning experiences that help them build the knowledge, skills and relationships to lead change for sustainable societies. | E38: Pilots of possible approaches for understanding and developing students’ sustainability self-efficacy | F38: Has your faculty piloted or trialled any approach in 2026 to understand or build students' confidence and capability to act on sustainability (sustainability self-efficacy)? If yes, briefly describe the approach, participating cohort, what was learned and next steps. If not, please respond 'none in 2026' – this is a new indicator and a nil response is useful. We are aware of the Sustainability Strengths Compass Living Lab project (CLLAP) and will collect it separately. | G38: This is a new indicator. We will use responses to establish a baseline of how (and whether) faculties are understanding student sustainability self-efficacy, and report on early pilots in the 2026 Sustainability Report. A nil response is useful to us. | H38: N/A – new indicator
B39: EE1(c) | C39: Exceptional education | D39: Provide our students with learning experiences that help them build the knowledge, skills and relationships to lead change for sustainable societies. | E39: Evidence of sustainability focused experiential and co curricular learning (eg Wattle Fellowship; Melbourne Plus) | F39: Please list any sustainability-focused experiential or co-curricular learning opportunities your faculty offered or supported in 2026 (e.g. industry or community projects, fieldwork, internships, student challenges), with approximate student participation where known and a one-line description of outcomes. We will collect Wattle Fellowship and Melbourne Plus information centrally – please only include these if your faculty ran a specific activity. | G39: We will combine faculty examples with central Wattle Fellowship and Melbourne Plus data to report on the range and reach of sustainability-focused experiential and co-curricular learning across the University. | H39: N/A – new indicator
B40: EE1(d) | C40: Exceptional education | D40: Provide our students with learning experiences that help them build the knowledge, skills and relationships to lead change for sustainable societies. | E40: Alumni profiles demonstrating how graduates contribute to sustainability through their careers or communities. | F40: In end-2025 reporting your faculty reported on the related SP2030 target 4b(i) and rated it 'Partially met' (see Column J – click [+] above Columns H–K). Please build on this rather than repeating it, focusing on what is new in 2026. Please nominate up to two alumni from your faculty whose careers or community work demonstrate how they apply sustainability knowledge and skills (name, course and graduating year, a short summary, a link to a profile if available, and whether consent to be featured is likely). If your faculty tracks sustainability-related graduate outcomes in any way, please briefly describe how. | G40: We will use nominated alumni to develop short graduate profiles for the 2026 Sustainability Report (subject to consent), and record any faculty approaches to tracking graduate outcomes to inform how this indicator is measured from 2027. | H40: 4b(i) | I40: Partially met | J40: See previous response. (copied below) While the Faculty is certainly producing such graduates, because we are a very early stage of curriculum mapping, we're unable to provide the relevant empirical data.
B41: TR1(a) | C41: Transformational research | D41: Utilise the expertise of the University’s researchers through mutually beneficial partnerships to help address the University’s operational sustainability challenges. | E41: Expert-reviewed evidence of researchers contributing to operational sustainability priorities through partnerships, advisory input, living labs, applied projects or decision-support | F41: In end-2025 reporting your faculty reported on the related SP2030 target 2a and rated it 'Met or exceeded' (see Column J – click [+] above Columns H–K). Please build on this rather than repeating it, focusing on what is new in 2026. Please provide up to two examples from 2026 of researchers in your faculty contributing to the University's own operational sustainability challenges (e.g. advising on campus energy, biodiversity, waste or buildings; applied projects; decision-support tools). For each, briefly describe the operational challenge, the researcher's contribution, the University team involved and the result. We will collect Campus Living Lab Accelerator Program (CLLAP) projects separately from CI&S – please include other examples only. | G41: We will report on examples of researchers helping solve the University's own operational sustainability challenges, alongside CLLAP projects reported by CI&S, and share them with operational teams to identify further collaboration. | H41: 2a | I41: Met or exceeded | J41: See attached report. (RH note: Saved in responses folder) | K41: Draft report on the Living Lab project is here: Report John Medley Living Lab Project FINAL.docx
B42: TR1(b) | C42: Transformational research | D42: Utilise the expertise of the University’s researchers through mutually beneficial partnerships to help address the University’s operational sustainability challenges. | E42: Evidence of institutional pathways that enable ongoing collaboration between academic and professional staff | F42: Does your faculty have any mechanism that supports ongoing collaboration between academic and professional staff on operational sustainability (e.g. a sustainability committee with mixed membership, seed funding, a coordination role or a regular forum)? If yes, briefly describe it and how often it operates. If not, please say so. | G42: We will map existing academic–professional collaboration mechanisms across faculties to establish a baseline for this new indicator and identify models other faculties could adopt. | H42: N/A – new indicator
B43: TR1(c) | C43: Transformational research | D43: Utilise the expertise of the University’s researchers through mutually beneficial partnerships to help address the University’s operational sustainability challenges. | E43: Expert assessment of the quality, relevance and continuity of these collaborations | F43: For the collaborations described in TR1(a)–(b), please give a short assessment (a paragraph is sufficient) of their quality, relevance and continuity: are they ongoing, useful to the University's operational priorities, and producing outcomes? | G43: We will use your assessment to describe the quality and continuity of research–operations collaboration in the 2026 report, and as baseline evidence for the interim target status assessment from 2027. | H43: N/A – new indicator
B44: TR1(d) | C44: Transformational research | D44: Utilise the expertise of the University’s researchers through mutually beneficial partnerships to help address the University’s operational sustainability challenges. | E44: Periodic feedback from participants on the effectiveness and mutual benefit of collaboration mechanisms. | F44: Has your faculty collected any feedback from participants (researchers or operational staff) on how well these collaboration mechanisms work and whether they are mutually beneficial? If yes, summarise key findings and any improvements identified; if not, please say so. | G44: We will use any feedback to understand whether collaboration mechanisms are working and to inform improvements. Where none has been collected, this helps us plan how to gather feedback from 2027. | H44: N/A – new indicator
B45: TR2(a) | C45: Transformational research | D45: Deliver high-quality research and partnerships that contribute to sustainability outcomes and demonstrable societal benefit. | E45: Evidence of sustainability-related research impact across diverse pathways, could include policy, industry, community, practice, cultural and institutional outcomes | F45: In end-2025 reporting your faculty reported on the related SP2030 target 5b(i) and rated it 'Met or exceeded' (see Column J – click [+] above Columns H–K). Please build on this rather than repeating it, focusing on what is new in 2026. Please provide one or two examples from 2026 of sustainability-related research from your faculty that has had impact beyond academia – on policy, industry, community, practice, cultural or institutional outcomes. For each, briefly describe the research, the partner or user, and the resulting change or influence, with links (e.g. Pursuit articles, policy submissions, reports). We will source University-wide research metrics (e.g. SDG-mapped publications via SciVal) from MRE – publication counts are not required. | G45: We will collate research impact examples across faculties to show the breadth of sustainability-related research impact in the Transformational research section of the 2026 Sustainability Report, complementing University-wide metrics from MRE. | H45: 5b(i) | I45: Met or exceeded | J45: In addition to the matters listed at mid-2025, the Ass Dean joined the Board of MBI and hosted a major showcase of MBI activities to Arts Faculty researchers which boosted involvement in the BDI's researech clusters
B46: TR2(d) | C46: Transformational research | D46: Deliver high-quality research and partnerships that contribute to sustainability outcomes and demonstrable societal benefit. | E46: Case-based evidence demonstrating how research has contributed to meaningful sustainability outcomes. | F46: In end-2025 reporting your faculty reported on the related SP2030 target 5b(i) and rated it 'Met or exceeded' (see Column J – click [+] above Columns H–K). Please build on this rather than repeating it, focusing on what is new in 2026. Please provide one case study (up to 300 words) of a research project from your faculty that has contributed to a meaningful sustainability outcome: the research, stakeholders involved, pathway to impact and evidence of the outcome. This can be one of the examples from TR2(a), developed in more detail. We are also seeking examples from Melbourne Climate Futures, the Melbourne Biodiversity Institute and Strategic Communications. | G46: We will select the strongest examples to develop as full research case studies for the 2026 Sustainability Report (we may contact you for more detail and images). | H46: 5b(i) | I46: Met or exceeded | J46: In addition to the matters listed at mid-2025, the Ass Dean joined the Board of MBI and hosted a major showcase of MBI activities to Arts Faculty researchers which boosted involvement in the BDI's researech clusters
B47: TR3(a) | C47: Transformational research | D47: Embed sustainability within research systems, processes, capability and culture, so research is conducted responsibly, efficiently and with reduced environmental impact. | E47: Evidence that sustainability considerations are integrated into relevant research systems, planning processes, guidance, training, induction or support services | F47: In end-2025 reporting your faculty reported on the related SP2030 target 5c(ii) and rated it 'Not met' (see Column J – click [+] above Columns H–K). Please build on this rather than repeating it, focusing on what is new in 2026. Please describe how sustainability considerations are built into your faculty's research systems or support – e.g. research planning or approval processes, guidance, graduate researcher induction or training, grant development support. Please highlight any new or improved process introduced in 2026. | G47: We will report on how sustainability is being built into research systems and support across the University, and use responses to establish a baseline for this new target. | H47: 5c(ii) | I47: Not met | J47: This needs more specific attention In general terms, the Faculty has focused on reducing air travel, the major environmental impact of our research activity.
B48: TR3(b) | C48: Transformational research | D48: Embed sustainability within research systems, processes, capability and culture, so research is conducted responsibly, efficiently and with reduced environmental impact. | E48: Demonstrated examples of more sustainable research practices in laboratories, fieldwork, procurement, travel or infrastructure use | F48: In end-2025 reporting your faculty reported on the related SP2030 target 5c(ii) and rated it 'Not met' (see Column J – click [+] above Columns H–K). Please build on this rather than repeating it, focusing on what is new in 2026. Are there any efforts within the faculty to make research practices more sustainable (e.g. green lab certification, equipment sharing, reduced research travel, sustainable fieldwork, sustainable procurement of research consumables)? If so, please describe up to two examples and any evidence of uptake, resource savings or emissions reductions. | G48: We will report on ways the University is making research practices more sustainable in the 2026 Sustainability Report, and share practical examples (e.g. green labs) across faculties. | H48: 5c(ii) | I48: Not met | J48: This needs more specific attention In general terms, the Faculty has focused on reducing air travel, the major environmental impact of our research activity.
B49: TR3(c) | C49: Transformational research | D49: Embed sustainability within research systems, processes, capability and culture, so research is conducted responsibly, efficiently and with reduced environmental impact. | E49: Evidence of progress in sustainability-related research culture, capability and awareness, informed by periodic staff and graduate researcher surveys | F49: Does your faculty have any evidence of change in sustainability-related research culture, capability or awareness – e.g. results from staff or graduate researcher surveys, or participation in capability-building events or training? Please provide a brief summary and the source. If no evidence is available, please say so. | G49: We will use any survey or capability data to describe changes in sustainability-related research culture. Where no evidence exists, this helps us plan University-wide measurement (e.g. staff and graduate researcher surveys) from 2027. | H49: N/A – new indicator
B50: TR3(d) | C50: Transformational research | D50: Embed sustainability within research systems, processes, capability and culture, so research is conducted responsibly, efficiently and with reduced environmental impact. | E50: Expert assessment of progress in embedding sustainable research practices across the institution. | F50: Drawing on your responses to TR3(a)–(c), please provide a short overall assessment (2–3 sentences) of your faculty's progress in embedding sustainable research practices: where progress is strongest, the main gaps, and priority actions for 2027. | G50: We will use faculty self-assessments to identify strengths, gaps and priority actions in embedding sustainable research practices, to inform internal management reporting and the Transformational research working group. | H50: N/A – new indicator
B51: CL2(a) | C51: Climate leadership | D51: Develop understanding of our research and education programs that contribute to accelerating global decarbonisation and our own climate transition. | E51: By 2028, develop and document institutional mapping of research and education activities that are designed to contribute to global decarbonisation | F51: Please list up to three examples of 2026 communications from your faculty that showcase climate action, research or learning and aim to inform policy, sector or community decarbonisation (e.g. policy submissions, public events, media, reports). Include links, the intended audience and any reach data you have. This will also contribute to the University's mapping of decarbonisation-related research and education (due by 2028). | G51: We will use these examples to show how the University communicates climate research and learning to external audiences, and as an input to the institutional decarbonisation research and education mapping due by 2028. | H51: N/A – new indicator
B52: CL2(c) | C52: Climate leadership | D52: Develop understanding of our research and education programs that contribute to accelerating global decarbonisation and our own climate transition. | E52: Ongoing communications that evidence the University’s climate action, research and learning to inform policy, sector and community decarbonisation efforts. | F52: If not already covered in CL2(a), please list any ongoing channels or programs (e.g. event series, newsletters, podcasts, policy engagement) through which your faculty regularly communicates climate research and learning to policy, sector or community audiences. You may respond 'see CL2(a)' if already covered. We will also engage Melbourne Climate Futures and the Melbourne Energy Institute. | G52: We will report on the University's ongoing climate communications in the Climate leadership section of the 2026 Sustainability Report, alongside contributions from Melbourne Climate Futures and the Melbourne Energy Institute. | H52: N/A – new indicator
B53: EN1(a) | C53: Enablers | D53: Enablers | E53: Evidence of sustainability outcomes informed by Indigenous knowledges | F53: In end-2025 reporting your faculty reported on the related SP2030 target 6a and rated it 'Partially met' (see Column J – click [+] above Columns H–K). Please build on this rather than repeating it, focusing on what is new in 2026. Please provide one case study of an activity in your faculty (education, research, engagement or operations) where Indigenous knowledges informed a sustainability outcome. Describe the activity, how Indigenous knowledges were incorporated or co-created and with whom, and the result. Please confirm that appropriate permissions are in place for sharing. | G53: We will report on the ways Indigenous knowledges inform sustainability activities across the University, and develop selected examples into case studies with appropriate permissions. | H53: 6a | I53: Partially met | J53: See previous response. (copied below) In addition to housing the Indigenous Studies Program, academic staff have contributed to University-wide Indigenous-led initiatives with important sustainability consequences, and more broadly, champsion such values in their scholarly work.
B54: EN1(b) | C54: Enablers | D54: Enablers | E54: Living laboratories enabling applied learning, research and operational sustainability outcomes | F54: In end-2025 reporting your faculty reported on the related SP2030 target 2a and rated it 'Met or exceeded' (see Column J – click [+] above Columns H–K). Please build on this rather than repeating it, focusing on what is new in 2026. Please provide a case study of a living lab which operates within your faculty, including a description of its activities, who is involved (students, researchers, operational staff) and its outputs, outcomes or impact in 2026. Please note we will approach living labs funded through the Campus Living Lab Accelerator Program (CLLAP) separately. | G54: We will share examples of living labs from across the University in the 2026 Sustainability Report, alongside CLLAP projects reported by CI&S. | H54: 2a | I54: Met or exceeded | J54: See attached report. (RH note: Saved in responses folder) | K54: Draft report on the Living Lab project is here: Report John Medley Living Lab Project FINAL.docx
B55: EN1(c) | C55: Enablers | D55: Enablers | E55: Coordinated internal engagement and external partnerships contributing to delivery of sustainability outcomes across priority areas. | F55: In end-2025 reporting your faculty reported on the related SP2030 target 3a(ii) and rated it 'Partially met' (see Column J – click [+] above Columns H–K). Please build on this rather than repeating it, focusing on what is new in 2026. Please list the key sustainability-focused communities of practice, internal networks or external partnerships active in your faculty in 2026 (name, partners, priority area), and provide a short description of one that has contributed to a Sustainability 2030 outcome. | G55: We will report on internal engagement and partnerships contributing to Sustainability 2030 outcomes, and update our record of sustainability-focused communities of practice and contacts across the University. | H55: 3a(ii) | I55: Partially met | J55: Academics in the Faculty have supported and learned from each other in new ways through the Living Lab and through using the sustainability networks in the Faculty and beyond to showcase and develop T&L initiatives. This is, of course, an ongoing process.
B56: EN1(d) | C56: Enablers | D56: Enablers | E56: Sustainability objectives integrated into governance and decision‑making processes, supported by transparent reporting. | F56: Please describe how sustainability is built into your faculty's governance and decision-making – e.g. a sustainability committee or Associate Dean (Sustainability) role, a faculty sustainability action plan, sustainability criteria in planning or approvals, and how progress is reported (e.g. to the Faculty Executive). Please link the action plan if one exists. | G56: We will report on how sustainability is integrated into governance and decision-making across faculties and portfolios, and use responses as a baseline for the governance enabler from 2027. | H56: N/A – new indicator
B59: 1.3 FBE – Faculty of Business and Economics
C61: Sustainability 2030 target and indicator | H61: End-2025 reporting (for reference – click [+] above to expand) | L61: End-2026 reporting (PLEASE COMPLETE THIS SECTION)
B62: Ref | C62: Priority area | D62: Sustainability 2030 target | E62: Indicator | F62: 2026 Reporting request | G62: How SST will use this data | H62: Related SR25 ref | I62: End-2025 confirmed status | J62: End-2025 reporting response | K62: Links and supporting information | L62: Confirm end-2026 target status | M62: OPTION 1: Target-level reporting (Column D) | N62: OPTION 2: Indicator level reporting (Column E/F) | O62: Supporting information/comments | P62: Data source and limitations | Q62: Data owner confirms information is accurate | R62: Confirmed by (name, role, date)
L63: (Met or exceeded; partially met; not met; not yet started) | M63: Provide further evidence of target status assessment in the form of: A general update on activities in relation to the overarching target (Column D) | N63: Provide further evidence of target status assessment in the form of: Data and commentary in direct response to the reporting request (Column F) | O63: Provide any additional information to support the target status assessment (e.g. links, images, rationale for selection of target status) | P63: Where did this information come from (system, report, survey, person)? Note any gaps or limitations. | Q63: Select 'Yes' to confirm the information provided is accurate and can be used for reporting | R63: Name, role and date of the person confirming
B64: EE1(a) | C64: Exceptional education | D64: Provide our students with learning experiences that help them build the knowledge, skills and relationships to lead change for sustainable societies. | E64: Evidence of innovative approaches to sustainability teaching and learning | F64: In end-2025 reporting your faculty reported on the related SP2030 target 4a(ii) and rated it 'Partially met' (see Column J – click [+] above Columns H–K). Please build on this rather than repeating it, focusing on what is new in 2026. Please provide one or two examples from 2026 of innovative approaches your faculty has used to embed sustainability in teaching and learning (e.g. new or redesigned subjects, curriculum design, pedagogies, assessment approaches or learning resources). Include links to subject pages or resources where available. A full list of subjects is not required. | G64: We will collate examples of innovative sustainability teaching and learning across faculties to inform the Exceptional education section of the 2026 Sustainability Report, and select one or two for short case studies. | H64: 4a(ii) | I64: Partially met | J64: The refresh of the Bachelor of Commerce BCOM refresh included explicitly embedding sustainability in course level learning outcomes, major level learning outcomes, and is now a specialisation (Ethics and Sustainability) available to students across all majors. See also Sust teaching case study p2
B65: EE1(b) | C65: Exceptional education | D65: Provide our students with learning experiences that help them build the knowledge, skills and relationships to lead change for sustainable societies. | E65: Pilots of possible approaches for understanding and developing students’ sustainability self-efficacy | F65: Has your faculty piloted or trialled any approach in 2026 to understand or build students' confidence and capability to act on sustainability (sustainability self-efficacy)? If yes, briefly describe the approach, participating cohort, what was learned and next steps. If not, please respond 'none in 2026' – this is a new indicator and a nil response is useful. We are aware of the Sustainability Strengths Compass Living Lab project (CLLAP) and will collect it separately. | G65: This is a new indicator. We will use responses to establish a baseline of how (and whether) faculties are understanding student sustainability self-efficacy, and report on early pilots in the 2026 Sustainability Report. A nil response is useful to us. | H65: N/A – new indicator
B66: EE1(c) | C66: Exceptional education | D66: Provide our students with learning experiences that help them build the knowledge, skills and relationships to lead change for sustainable societies. | E66: Evidence of sustainability focused experiential and co curricular learning (eg Wattle Fellowship; Melbourne Plus) | F66: Please list any sustainability-focused experiential or co-curricular learning opportunities your faculty offered or supported in 2026 (e.g. industry or community projects, fieldwork, internships, student challenges), with approximate student participation where known and a one-line description of outcomes. We will collect Wattle Fellowship and Melbourne Plus information centrally – please only include these if your faculty ran a specific activity. | G66: We will combine faculty examples with central Wattle Fellowship and Melbourne Plus data to report on the range and reach of sustainability-focused experiential and co-curricular learning across the University. | H66: N/A – new indicator
B67: EE1(d) | C67: Exceptional education | D67: Provide our students with learning experiences that help them build the knowledge, skills and relationships to lead change for sustainable societies. | E67: Alumni profiles demonstrating how graduates contribute to sustainability through their careers or communities. | F67: In end-2025 reporting your faculty reported on the related SP2030 target 4b(i) and rated it 'Met or exceeded' (see Column J – click [+] above Columns H–K). Please build on this rather than repeating it, focusing on what is new in 2026. Please nominate up to two alumni from your faculty whose careers or community work demonstrate how they apply sustainability knowledge and skills (name, course and graduating year, a short summary, a link to a profile if available, and whether consent to be featured is likely). If your faculty tracks sustainability-related graduate outcomes in any way, please briefly describe how. | G67: We will use nominated alumni to develop short graduate profiles for the 2026 Sustainability Report (subject to consent), and record any faculty approaches to tracking graduate outcomes to inform how this indicator is measured from 2027. | H67: 4b(i) | I67: Met or exceeded | J67: A new 'specialisation' (similar to a Major) in Ethics and Sustainability has been approved for the Bachelor of Commerce and available in 2026. The previous Discovery subject Sustainable Commerce has been discontinued. In Work-Integrated-Learning subjects, such as WorkHUB, Business Practicum and Management Consulting, have pivoted to ensure sustainability related projects are offered in all semesters. Case comps, and other co-curricular activities explicitly focus on sustainability related themes. aSSERT, a sustainability competency self-assessment co-developed with FEIT and SCI faculty, was piloted in third year undergraduate sustainability elective subject (MGMT30008), students reportedly were able to develop competencies related to "embracing complexity" and "envisioning sustainable futures" See also Sust teaching case study p2
B68: TR1(a) | C68: Transformational research | D68: Utilise the expertise of the University’s researchers through mutually beneficial partnerships to help address the University’s operational sustainability challenges. | E68: Expert-reviewed evidence of researchers contributing to operational sustainability priorities through partnerships, advisory input, living labs, applied projects or decision-support | F68: In end-2025 reporting your faculty reported on the related SP2030 target 2a and rated it 'Partially met' (see Column J – click [+] above Columns H–K). Please build on this rather than repeating it, focusing on what is new in 2026. Please provide up to two examples from 2026 of researchers in your faculty contributing to the University's own operational sustainability challenges (e.g. advising on campus energy, biodiversity, waste or buildings; applied projects; decision-support tools). For each, briefly describe the operational challenge, the researcher's contribution, the University team involved and the result. We will collect Campus Living Lab Accelerator Program (CLLAP) projects separately from CI&S – please include other examples only. | G68: We will report on examples of researchers helping solve the University's own operational sustainability challenges, alongside CLLAP projects reported by CI&S, and share them with operational teams to identify further collaboration. | H68: 2a | I68: Partially met | J68: CLLAP report on University Investor Stewardship provided separately
B69: TR1(b) | C69: Transformational research | D69: Utilise the expertise of the University’s researchers through mutually beneficial partnerships to help address the University’s operational sustainability challenges. | E69: Evidence of institutional pathways that enable ongoing collaboration between academic and professional staff | F69: Does your faculty have any mechanism that supports ongoing collaboration between academic and professional staff on operational sustainability (e.g. a sustainability committee with mixed membership, seed funding, a coordination role or a regular forum)? If yes, briefly describe it and how often it operates. If not, please say so. | G69: We will map existing academic–professional collaboration mechanisms across faculties to establish a baseline for this new indicator and identify models other faculties could adopt. | H69: N/A – new indicator
B70: TR1(c) | C70: Transformational research | D70: Utilise the expertise of the University’s researchers through mutually beneficial partnerships to help address the University’s operational sustainability challenges. | E70: Expert assessment of the quality, relevance and continuity of these collaborations | F70: For the collaborations described in TR1(a)–(b), please give a short assessment (a paragraph is sufficient) of their quality, relevance and continuity: are they ongoing, useful to the University's operational priorities, and producing outcomes? | G70: We will use your assessment to describe the quality and continuity of research–operations collaboration in the 2026 report, and as baseline evidence for the interim target status assessment from 2027. | H70: N/A – new indicator
B71: TR1(d) | C71: Transformational research | D71: Utilise the expertise of the University’s researchers through mutually beneficial partnerships to help address the University’s operational sustainability challenges. | E71: Periodic feedback from participants on the effectiveness and mutual benefit of collaboration mechanisms. | F71: Has your faculty collected any feedback from participants (researchers or operational staff) on how well these collaboration mechanisms work and whether they are mutually beneficial? If yes, summarise key findings and any improvements identified; if not, please say so. | G71: We will use any feedback to understand whether collaboration mechanisms are working and to inform improvements. Where none has been collected, this helps us plan how to gather feedback from 2027. | H71: N/A – new indicator
B72: TR2(a) | C72: Transformational research | D72: Deliver high-quality research and partnerships that contribute to sustainability outcomes and demonstrable societal benefit. | E72: Evidence of sustainability-related research impact across diverse pathways, could include policy, industry, community, practice, cultural and institutional outcomes | F72: In end-2025 reporting your faculty reported on the related SP2030 target 5b(i) and rated it 'Partially met' (see Column J – click [+] above Columns H–K). Please build on this rather than repeating it, focusing on what is new in 2026. Please provide one or two examples from 2026 of sustainability-related research from your faculty that has had impact beyond academia – on policy, industry, community, practice, cultural or institutional outcomes. For each, briefly describe the research, the partner or user, and the resulting change or influence, with links (e.g. Pursuit articles, policy submissions, reports). We will source University-wide research metrics (e.g. SDG-mapped publications via SciVal) from MRE – publication counts are not required. | G72: We will collate research impact examples across faculties to show the breadth of sustainability-related research impact in the Transformational research section of the 2026 Sustainability Report, complementing University-wide metrics from MRE. | H72: 5b(i) | I72: Partially met | J72: Several departments have completed high quality sustainability-focused research, which includes papers published in peer reviwed research journals and a range of commissioned research for diverse industry partners including the national accounting standard setting body, which focus on a range of sustainability-related topics. See M&M Sust Research Hub case study p2 | K72: https://fbe.unimelb.edu.au/research/our-research-at-a-glance
B73: TR2(d) | C73: Transformational research | D73: Deliver high-quality research and partnerships that contribute to sustainability outcomes and demonstrable societal benefit. | E73: Case-based evidence demonstrating how research has contributed to meaningful sustainability outcomes. | F73: In end-2025 reporting your faculty reported on the related SP2030 target 5b(i) and rated it 'Partially met' (see Column J – click [+] above Columns H–K). Please build on this rather than repeating it, focusing on what is new in 2026. Please provide one case study (up to 300 words) of a research project from your faculty that has contributed to a meaningful sustainability outcome: the research, stakeholders involved, pathway to impact and evidence of the outcome. This can be one of the examples from TR2(a), developed in more detail. We are also seeking examples from Melbourne Climate Futures, the Melbourne Biodiversity Institute and Strategic Communications. | G73: We will select the strongest examples to develop as full research case studies for the 2026 Sustainability Report (we may contact you for more detail and images). | H73: 5b(i) | I73: Partially met | J73: Several departments have completed high quality sustainability-focused research, which includes papers published in peer reviwed research journals and a range of commissioned research for diverse industry partners including the national accounting standard setting body, which focus on a range of sustainability-related topics. See M&M Sust Research Hub case study p2 | K73: https://fbe.unimelb.edu.au/research/our-research-at-a-glance
B74: TR3(a) | C74: Transformational research | D74: Embed sustainability within research systems, processes, capability and culture, so research is conducted responsibly, efficiently and with reduced environmental impact. | E74: Evidence that sustainability considerations are integrated into relevant research systems, planning processes, guidance, training, induction or support services | F74: In end-2025 reporting your faculty reported on the related SP2030 target 5c(ii) and rated it 'Partially met' (see Column J – click [+] above Columns H–K). Please build on this rather than repeating it, focusing on what is new in 2026. Please describe how sustainability considerations are built into your faculty's research systems or support – e.g. research planning or approval processes, guidance, graduate researcher induction or training, grant development support. Please highlight any new or improved process introduced in 2026. | G74: We will report on how sustainability is being built into research systems and support across the University, and use responses to establish a baseline for this new target. | H74: 5c(ii) | I74: Partially met | J74: The Department of Management & Marketing Sustainable Research Hub is leading on 'Graduate Researcher Training for Sustainability-Related Research'. Equipping the next generation of researchers with the interdisciplinary and transdisciplinary knowledge and skills, and systems thinking competencies that enables them to recognize and pursue complex sustainability problems in their research, and to recognize the potential impact of their research on sustainability concerns. Development of these capabilities includes curriculum design, experiential learning opportunities, research ethics protocols, and institutional support needed to foster impactful sustainability research. (Also see case study p2) | K74: https://fbe.unimelb.edu.au/managementmarketing/research/the-sustainability-hub
B75: TR3(b) | C75: Transformational research | D75: Embed sustainability within research systems, processes, capability and culture, so research is conducted responsibly, efficiently and with reduced environmental impact. | E75: Demonstrated examples of more sustainable research practices in laboratories, fieldwork, procurement, travel or infrastructure use | F75: In end-2025 reporting your faculty reported on the related SP2030 target 5c(ii) and rated it 'Partially met' (see Column J – click [+] above Columns H–K). Please build on this rather than repeating it, focusing on what is new in 2026. Are there any efforts within the faculty to make research practices more sustainable (e.g. green lab certification, equipment sharing, reduced research travel, sustainable fieldwork, sustainable procurement of research consumables)? If so, please describe up to two examples and any evidence of uptake, resource savings or emissions reductions. | G75: We will report on ways the University is making research practices more sustainable in the 2026 Sustainability Report, and share practical examples (e.g. green labs) across faculties. | H75: 5c(ii) | I75: Partially met | J75: The Department of Management & Marketing Sustainable Research Hub is leading on 'Graduate Researcher Training for Sustainability-Related Research'. Equipping the next generation of researchers with the interdisciplinary and transdisciplinary knowledge and skills, and systems thinking competencies that enables them to recognize and pursue complex sustainability problems in their research, and to recognize the potential impact of their research on sustainability concerns. Development of these capabilities includes curriculum design, experiential learning opportunities, research ethics protocols, and institutional support needed to foster impactful sustainability research. (Also see case study p2) | K75: https://fbe.unimelb.edu.au/managementmarketing/research/the-sustainability-hub
B76: TR3(c) | C76: Transformational research | D76: Embed sustainability within research systems, processes, capability and culture, so research is conducted responsibly, efficiently and with reduced environmental impact. | E76: Evidence of progress in sustainability-related research culture, capability and awareness, informed by periodic staff and graduate researcher surveys | F76: Does your faculty have any evidence of change in sustainability-related research culture, capability or awareness – e.g. results from staff or graduate researcher surveys, or participation in capability-building events or training? Please provide a brief summary and the source. If no evidence is available, please say so. | G76: We will use any survey or capability data to describe changes in sustainability-related research culture. Where no evidence exists, this helps us plan University-wide measurement (e.g. staff and graduate researcher surveys) from 2027. | H76: N/A – new indicator
B77: TR3(d) | C77: Transformational research | D77: Embed sustainability within research systems, processes, capability and culture, so research is conducted responsibly, efficiently and with reduced environmental impact. | E77: Expert assessment of progress in embedding sustainable research practices across the institution. | F77: Drawing on your responses to TR3(a)–(c), please provide a short overall assessment (2–3 sentences) of your faculty's progress in embedding sustainable research practices: where progress is strongest, the main gaps, and priority actions for 2027. | G77: We will use faculty self-assessments to identify strengths, gaps and priority actions in embedding sustainable research practices, to inform internal management reporting and the Transformational research working group. | H77: N/A – new indicator
B78: CL2(a) | C78: Climate leadership | D78: Develop understanding of our research and education programs that contribute to accelerating global decarbonisation and our own climate transition. | E78: By 2028, develop and document institutional mapping of research and education activities that are designed to contribute to global decarbonisation | F78: Please list up to three examples of 2026 communications from your faculty that showcase climate action, research or learning and aim to inform policy, sector or community decarbonisation (e.g. policy submissions, public events, media, reports). Include links, the intended audience and any reach data you have. This will also contribute to the University's mapping of decarbonisation-related research and education (due by 2028). | G78: We will use these examples to show how the University communicates climate research and learning to external audiences, and as an input to the institutional decarbonisation research and education mapping due by 2028. | H78: N/A – new indicator
B79: CL2(c) | C79: Climate leadership | D79: Develop understanding of our research and education programs that contribute to accelerating global decarbonisation and our own climate transition. | E79: Ongoing communications that evidence the University’s climate action, research and learning to inform policy, sector and community decarbonisation efforts. | F79: If not already covered in CL2(a), please list any ongoing channels or programs (e.g. event series, newsletters, podcasts, policy engagement) through which your faculty regularly communicates climate research and learning to policy, sector or community audiences. You may respond 'see CL2(a)' if already covered. We will also engage Melbourne Climate Futures and the Melbourne Energy Institute. | G79: We will report on the University's ongoing climate communications in the Climate leadership section of the 2026 Sustainability Report, alongside contributions from Melbourne Climate Futures and the Melbourne Energy Institute. | H79: N/A – new indicator
B80: EN1(a) | C80: Enablers | D80: Enablers | E80: Evidence of sustainability outcomes informed by Indigenous knowledges | F80: In end-2025 reporting your faculty reported on the related SP2030 target 6a and rated it 'Partially met' (see Column J – click [+] above Columns H–K). Please build on this rather than repeating it, focusing on what is new in 2026. Please provide one case study of an activity in your faculty (education, research, engagement or operations) where Indigenous knowledges informed a sustainability outcome. Describe the activity, how Indigenous knowledges were incorporated or co-created and with whom, and the result. Please confirm that appropriate permissions are in place for sharing. | G80: We will report on the ways Indigenous knowledges inform sustainability activities across the University, and develop selected examples into case studies with appropriate permissions. | H80: 6a | I80: Partially met | J80: The Dilin Duwa Centre for Indigenous Business Leadership is developing research, teaching and engagement programs to enhance the economic skill base of Indigenous Australians, including through entrepreneurship, jobs and procurement. The Mabo Centre works to support Traditional Owners achieve successful Native Title outcomes for their communities through research, training, excahange and acceleration. PhD student Caleb Adams' cross disciplinary thesis topic is 'Understanding and Unlocking Financial Capital: Empowering First Nations Leadership in and for a Green Economy' | K80: https://dilinduwa.com.au/ https://mabocentre.com/
B81: EN1(b) | C81: Enablers | D81: Enablers | E81: Living laboratories enabling applied learning, research and operational sustainability outcomes | F81: In end-2025 reporting your faculty reported on the related SP2030 target 2a and rated it 'Partially met' (see Column J – click [+] above Columns H–K). Please build on this rather than repeating it, focusing on what is new in 2026. Please provide a case study of a living lab which operates within your faculty, including a description of its activities, who is involved (students, researchers, operational staff) and its outputs, outcomes or impact in 2026. Please note we will approach living labs funded through the Campus Living Lab Accelerator Program (CLLAP) separately. | G81: We will share examples of living labs from across the University in the 2026 Sustainability Report, alongside CLLAP projects reported by CI&S. | H81: 2a | I81: Partially met | J81: CLLAP report on University Investor Stewardship provided separately
B82: EN1(c) | C82: Enablers | D82: Enablers | E82: Coordinated internal engagement and external partnerships contributing to delivery of sustainability outcomes across priority areas. | F82: In end-2025 reporting your faculty reported on the related SP2030 target 3a(ii) and rated it 'Partially met' (see Column J – click [+] above Columns H–K). Please build on this rather than repeating it, focusing on what is new in 2026. Please list the key sustainability-focused communities of practice, internal networks or external partnerships active in your faculty in 2026 (name, partners, priority area), and provide a short description of one that has contributed to a Sustainability 2030 outcome. | G82: We will report on internal engagement and partnerships contributing to Sustainability 2030 outcomes, and update our record of sustainability-focused communities of practice and contacts across the University. | H82: 3a(ii) | I82: Partially met | J82: The Faculty leads many cross department events and workshops to further sustainability knowledge and integration. For example, FBE faciliating the Shared Value Project exec ed for the 3rd time in 2025 as well as the SVP summit in 2025 at Melbourne Connect. FBE is deepening its relationship with SVP - which will provide a key highly visable and impactful pathway to embedding sustsinability and shared value into teaching as well offering myriad research opportunities. The Faculty led a University research engagement event - the Sustainable Finance Futures Forum - on September 17 within Sustainability Week. The event was attended by approximately 80 people from industry and the University community. It featured a keynote by Director of the University's Sustainable Finance Hub, Simon O'Connor, followed by an industry panel and then workshop session on climate scenario analyses led by A/Prof Ben Neville
B83: EN1(d) | C83: Enablers | D83: Enablers | E83: Sustainability objectives integrated into governance and decision‑making processes, supported by transparent reporting. | F83: Please describe how sustainability is built into your faculty's governance and decision-making – e.g. a sustainability committee or Associate Dean (Sustainability) role, a faculty sustainability action plan, sustainability criteria in planning or approvals, and how progress is reported (e.g. to the Faculty Executive). Please link the action plan if one exists. | G83: We will report on how sustainability is integrated into governance and decision-making across faculties and portfolios, and use responses as a baseline for the governance enabler from 2027. | H83: N/A – new indicator
B86: 1.4 SCI – Faculty of Science
C88: Sustainability 2030 target and indicator | H88: End-2025 reporting (for reference – click [+] above to expand) | L88: End-2026 reporting (PLEASE COMPLETE THIS SECTION)
B89: Ref | C89: Priority area | D89: Sustainability 2030 target | E89: Indicator | F89: 2026 Reporting request | G89: How SST will use this data | H89: Related SR25 ref | I89: End-2025 confirmed status | J89: End-2025 reporting response | K89: Links and supporting information | L89: Confirm end-2026 target status | M89: OPTION 1: Target-level reporting (Column D) | N89: OPTION 2: Indicator level reporting (Column E/F) | O89: Supporting information/comments | P89: Data source and limitations | Q89: Data owner confirms information is accurate | R89: Confirmed by (name, role, date)
L90: (Met or exceeded; partially met; not met; not yet started) | M90: Provide further evidence of target status assessment in the form of: A general update on activities in relation to the overarching target (Column D) | N90: Provide further evidence of target status assessment in the form of: Data and commentary in direct response to the reporting request (Column F) | O90: Provide any additional information to support the target status assessment (e.g. links, images, rationale for selection of target status) | P90: Where did this information come from (system, report, survey, person)? Note any gaps or limitations. | Q90: Select 'Yes' to confirm the information provided is accurate and can be used for reporting | R90: Name, role and date of the person confirming
B91: EE1(a) | C91: Exceptional education | D91: Provide our students with learning experiences that help them build the knowledge, skills and relationships to lead change for sustainable societies. | E91: Evidence of innovative approaches to sustainability teaching and learning | F91: In end-2025 reporting your faculty reported on the related SP2030 target 4a(ii) and rated it 'Met or exceeded' (see Column J – click [+] above Columns H–K). Please build on this rather than repeating it, focusing on what is new in 2026. Please provide one or two examples from 2026 of innovative approaches your faculty has used to embed sustainability in teaching and learning (e.g. new or redesigned subjects, curriculum design, pedagogies, assessment approaches or learning resources). Include links to subject pages or resources where available. A full list of subjects is not required. | G91: We will collate examples of innovative sustainability teaching and learning across faculties to inform the Exceptional education section of the 2026 Sustainability Report, and select one or two for short case studies. | H91: 4a(ii) | I91: Met or exceeded | J91: Sustainability, conservation, biodiversity are elements of most courses and majors within the FoS. Several additional courses are being considered at PG level in 2026 The FoS education strategy https://staff.unimelb.edu.au/science/learning-and-teaching-support/education-strategy has been developed with the following targets related to sustainability: Under Innovate: "Maintain a focus on embedding the principles of sustainability in our teaching and learning practices, including ‘green’ and sustainable laboratory initiatives"; Future ready graduates: "Our programs will embed the concepts of sustainability set out in the University’s Sustainability Plan 2030 so that our graduates are fluent in contemporary concepts of human, social, economic and environmental sustainability. " With the 12 month implementation plan noting that: "Understanding our students’ carbon footprint is the first step towards incorporating sustainability in teaching and learning."
B92: EE1(b) | C92: Exceptional education | D92: Provide our students with learning experiences that help them build the knowledge, skills and relationships to lead change for sustainable societies. | E92: Pilots of possible approaches for understanding and developing students’ sustainability self-efficacy | F92: Has your faculty piloted or trialled any approach in 2026 to understand or build students' confidence and capability to act on sustainability (sustainability self-efficacy)? If yes, briefly describe the approach, participating cohort, what was learned and next steps. If not, please respond 'none in 2026' – this is a new indicator and a nil response is useful. We are aware of the Sustainability Strengths Compass Living Lab project (CLLAP) and will collect it separately. | G92: This is a new indicator. We will use responses to establish a baseline of how (and whether) faculties are understanding student sustainability self-efficacy, and report on early pilots in the 2026 Sustainability Report. A nil response is useful to us. | H92: N/A – new indicator
B93: EE1(c) | C93: Exceptional education | D93: Provide our students with learning experiences that help them build the knowledge, skills and relationships to lead change for sustainable societies. | E93: Evidence of sustainability focused experiential and co curricular learning (eg Wattle Fellowship; Melbourne Plus) | F93: Please list any sustainability-focused experiential or co-curricular learning opportunities your faculty offered or supported in 2026 (e.g. industry or community projects, fieldwork, internships, student challenges), with approximate student participation where known and a one-line description of outcomes. We will collect Wattle Fellowship and Melbourne Plus information centrally – please only include these if your faculty ran a specific activity. | G93: We will combine faculty examples with central Wattle Fellowship and Melbourne Plus data to report on the range and reach of sustainability-focused experiential and co-curricular learning across the University. | H93: N/A – new indicator
B94: EE1(d) | C94: Exceptional education | D94: Provide our students with learning experiences that help them build the knowledge, skills and relationships to lead change for sustainable societies. | E94: Alumni profiles demonstrating how graduates contribute to sustainability through their careers or communities. | F94: In end-2025 reporting your faculty reported on the related SP2030 target 4b(i) and rated it 'Met or exceeded' (see Column J – click [+] above Columns H–K). Please build on this rather than repeating it, focusing on what is new in 2026. Please nominate up to two alumni from your faculty whose careers or community work demonstrate how they apply sustainability knowledge and skills (name, course and graduating year, a short summary, a link to a profile if available, and whether consent to be featured is likely). If your faculty tracks sustainability-related graduate outcomes in any way, please briefly describe how. | G94: We will use nominated alumni to develop short graduate profiles for the 2026 Sustainability Report (subject to consent), and record any faculty approaches to tracking graduate outcomes to inform how this indicator is measured from 2027. | H94: 4b(i) | I94: Met or exceeded | J94: As above. FoS is the custodial faculty for the Office of Environmental Programs The BSc had 208 graduates across the following environmental/sustainability focussed majors: Zoology 40 Marine Biology 19 Plant Science 6 Geology 16 Geography 19 Environmental Science 26 Ecosystem Science 6 Ecology & Evolutionary Biology 24 Climate and Weather 9 The Office of Environmental programs had 198 postgraduate graduates in 2025: 5 Graduate Certificate in Bushfire Planning and Management 2 Graduate Certificate in Environment 7 Graduate Diploma in Urban Horticulture 5 Master of Climate Science 10 Master of Ecosystem Management and Conservation 105 Master of Environment 40 Master of Environmental Science 24 Master of Urban Horticulture
B95: TR1(a) | C95: Transformational research | D95: Utilise the expertise of the University’s researchers through mutually beneficial partnerships to help address the University’s operational sustainability challenges. | E95: Expert-reviewed evidence of researchers contributing to operational sustainability priorities through partnerships, advisory input, living labs, applied projects or decision-support | F95: In end-2025 reporting your faculty reported on the related SP2030 target 2a and rated it 'Partially met' (see Column J – click [+] above Columns H–K). Please build on this rather than repeating it, focusing on what is new in 2026. Please provide up to two examples from 2026 of researchers in your faculty contributing to the University's own operational sustainability challenges (e.g. advising on campus energy, biodiversity, waste or buildings; applied projects; decision-support tools). For each, briefly describe the operational challenge, the researcher's contribution, the University team involved and the result. We will collect Campus Living Lab Accelerator Program (CLLAP) projects separately from CI&S – please include other examples only. | G95: We will report on examples of researchers helping solve the University's own operational sustainability challenges, alongside CLLAP projects reported by CI&S, and share them with operational teams to identify further collaboration. | H95: 2a | I95: Partially met | J95: The faculty has many projects that can be considered living labs. A centralised approach is required to document them. 2025 examples include how the undergraduate chemistry teaching laboratories redesigned their practicals to use less reagents and safer chemicals to achieve the same learning outcomes. Physics have redesigned the X-band radiation lab electricity usage resulting in the saving of a very significant percentage of electricity costs. Biosciences and vet school both conducted -80oC freezer sample clean out and efficiency awareness work. This is part of green laboratory certification. SAFES have worked on Indigenous food gardens and have an Indigenous food guide and there are examples of urban and woodland greening that serve as best practice examples across Australia | K95: https://www.unimelb.edu.au/newsroom/news/2024/october/native-harvest-cookbook-aims-to-put-indigenous-food-in-every-aussie-kitchen https://theconversation.com/we-planted-two-woody-meadows-a-decade-ago-to-see-what-would-thrive-now-the-concept-is-popular-across-australia-269611
B96: TR1(b) | C96: Transformational research | D96: Utilise the expertise of the University’s researchers through mutually beneficial partnerships to help address the University’s operational sustainability challenges. | E96: Evidence of institutional pathways that enable ongoing collaboration between academic and professional staff | F96: Does your faculty have any mechanism that supports ongoing collaboration between academic and professional staff on operational sustainability (e.g. a sustainability committee with mixed membership, seed funding, a coordination role or a regular forum)? If yes, briefly describe it and how often it operates. If not, please say so. | G96: We will map existing academic–professional collaboration mechanisms across faculties to establish a baseline for this new indicator and identify models other faculties could adopt. | H96: N/A – new indicator
B97: TR1(c) | C97: Transformational research | D97: Utilise the expertise of the University’s researchers through mutually beneficial partnerships to help address the University’s operational sustainability challenges. | E97: Expert assessment of the quality, relevance and continuity of these collaborations | F97: For the collaborations described in TR1(a)–(b), please give a short assessment (a paragraph is sufficient) of their quality, relevance and continuity: are they ongoing, useful to the University's operational priorities, and producing outcomes? | G97: We will use your assessment to describe the quality and continuity of research–operations collaboration in the 2026 report, and as baseline evidence for the interim target status assessment from 2027. | H97: N/A – new indicator
B98: TR1(d) | C98: Transformational research | D98: Utilise the expertise of the University’s researchers through mutually beneficial partnerships to help address the University’s operational sustainability challenges. | E98: Periodic feedback from participants on the effectiveness and mutual benefit of collaboration mechanisms. | F98: Has your faculty collected any feedback from participants (researchers or operational staff) on how well these collaboration mechanisms work and whether they are mutually beneficial? If yes, summarise key findings and any improvements identified; if not, please say so. | G98: We will use any feedback to understand whether collaboration mechanisms are working and to inform improvements. Where none has been collected, this helps us plan how to gather feedback from 2027. | H98: N/A – new indicator
B99: TR2(a) | C99: Transformational research | D99: Deliver high-quality research and partnerships that contribute to sustainability outcomes and demonstrable societal benefit. | E99: Evidence of sustainability-related research impact across diverse pathways, could include policy, industry, community, practice, cultural and institutional outcomes | F99: In end-2025 reporting your faculty reported on the related SP2030 target 5b(i) and rated it 'Met or exceeded' (see Column J – click [+] above Columns H–K). Please build on this rather than repeating it, focusing on what is new in 2026. Please provide one or two examples from 2026 of sustainability-related research from your faculty that has had impact beyond academia – on policy, industry, community, practice, cultural or institutional outcomes. For each, briefly describe the research, the partner or user, and the resulting change or influence, with links (e.g. Pursuit articles, policy submissions, reports). We will source University-wide research metrics (e.g. SDG-mapped publications via SciVal) from MRE – publication counts are not required. | G99: We will collate research impact examples across faculties to show the breadth of sustainability-related research impact in the Transformational research section of the 2026 Sustainability Report, complementing University-wide metrics from MRE. | H99: 5b(i) | I99: Met or exceeded | J99: QS rankings, SDG research outputs all attest to our strength in environmental and sustainable research. We have a research strategy which has clear deliverables for sustainability, including a focus on several "Big Research Challenges" which directly relate to Sustainability https://staff.unimelb.edu.au/science/research/research-governance/research-strategy-2023-2030/FOS-Research-strategy-_INTRANET-LINKS-FIXED.pdf We had a Science at Melbourne Public lecture on environmental pollution: https://science.unimelb.edu.au/about/news/dont-drink-the-water-or-breathe-the-air-pollution-and-solutions and the climate crisis: https://science.unimelb.edu.au/about/news/australia-and-the-pacific-islands-solidarity-in-a-time-of-climate-crisis/_nocache
B100: TR2(d) | C100: Transformational research | D100: Deliver high-quality research and partnerships that contribute to sustainability outcomes and demonstrable societal benefit. | E100: Case-based evidence demonstrating how research has contributed to meaningful sustainability outcomes. | F100: In end-2025 reporting your faculty reported on the related SP2030 target 5b(i) and rated it 'Met or exceeded' (see Column J – click [+] above Columns H–K). Please build on this rather than repeating it, focusing on what is new in 2026. Please provide one case study (up to 300 words) of a research project from your faculty that has contributed to a meaningful sustainability outcome: the research, stakeholders involved, pathway to impact and evidence of the outcome. This can be one of the examples from TR2(a), developed in more detail. We are also seeking examples from Melbourne Climate Futures, the Melbourne Biodiversity Institute and Strategic Communications. | G100: We will select the strongest examples to develop as full research case studies for the 2026 Sustainability Report (we may contact you for more detail and images). | H100: 5b(i) | I100: Met or exceeded | J100: QS rankings, SDG research outputs all attest to our strength in environmental and sustainable research. We have a research strategy which has clear deliverables for sustainability, including a focus on several "Big Research Challenges" which directly relate to Sustainability https://staff.unimelb.edu.au/science/research/research-governance/research-strategy-2023-2030/FOS-Research-strategy-_INTRANET-LINKS-FIXED.pdf We had a Science at Melbourne Public lecture on environmental pollution: https://science.unimelb.edu.au/about/news/dont-drink-the-water-or-breathe-the-air-pollution-and-solutions and the climate crisis: https://science.unimelb.edu.au/about/news/australia-and-the-pacific-islands-solidarity-in-a-time-of-climate-crisis/_nocache
B101: TR3(a) | C101: Transformational research | D101: Embed sustainability within research systems, processes, capability and culture, so research is conducted responsibly, efficiently and with reduced environmental impact. | E101: Evidence that sustainability considerations are integrated into relevant research systems, planning processes, guidance, training, induction or support services | F101: In end-2025 reporting your faculty reported on the related SP2030 target 5c(ii) and rated it 'Partially met' (see Column J – click [+] above Columns H–K). Please build on this rather than repeating it, focusing on what is new in 2026. Please describe how sustainability considerations are built into your faculty's research systems or support – e.g. research planning or approval processes, guidance, graduate researcher induction or training, grant development support. Please highlight any new or improved process introduced in 2026. | G101: We will report on how sustainability is being built into research systems and support across the University, and use responses to establish a baseline for this new target. | H101: 5c(ii) | I101: Partially met | J101: We have a research strategy and implimentation plan which has clear deliverables for sustainability; Link for Research strategy: https://staff.unimelb.edu.au/science/research/research-governance/research-strategy-2023-2030 Link for Implimentation Plan: https://staff.unimelb.edu.au/science/research/research-governance/research-strategy-2023-2030/Research-Strategy-Implementation-Plan_FINAL_12Dec24.pdf which for example includes "Action 10. Improve sustainability of our core business practices"
B102: TR3(b) | C102: Transformational research | D102: Embed sustainability within research systems, processes, capability and culture, so research is conducted responsibly, efficiently and with reduced environmental impact. | E102: Demonstrated examples of more sustainable research practices in laboratories, fieldwork, procurement, travel or infrastructure use | F102: In end-2025 reporting your faculty reported on the related SP2030 target 5c(ii) and rated it 'Partially met' (see Column J – click [+] above Columns H–K). Please build on this rather than repeating it, focusing on what is new in 2026. Are there any efforts within the faculty to make research practices more sustainable (e.g. green lab certification, equipment sharing, reduced research travel, sustainable fieldwork, sustainable procurement of research consumables)? If so, please describe up to two examples and any evidence of uptake, resource savings or emissions reductions. | G102: We will report on ways the University is making research practices more sustainable in the 2026 Sustainability Report, and share practical examples (e.g. green labs) across faculties. | H102: 5c(ii) | I102: Partially met | J102: We have a research strategy and implimentation plan which has clear deliverables for sustainability; Link for Research strategy: https://staff.unimelb.edu.au/science/research/research-governance/research-strategy-2023-2030 Link for Implimentation Plan: https://staff.unimelb.edu.au/science/research/research-governance/research-strategy-2023-2030/Research-Strategy-Implementation-Plan_FINAL_12Dec24.pdf which for example includes "Action 10. Improve sustainability of our core business practices"
B103: TR3(c) | C103: Transformational research | D103: Embed sustainability within research systems, processes, capability and culture, so research is conducted responsibly, efficiently and with reduced environmental impact. | E103: Evidence of progress in sustainability-related research culture, capability and awareness, informed by periodic staff and graduate researcher surveys | F103: Does your faculty have any evidence of change in sustainability-related research culture, capability or awareness – e.g. results from staff or graduate researcher surveys, or participation in capability-building events or training? Please provide a brief summary and the source. If no evidence is available, please say so. | G103: We will use any survey or capability data to describe changes in sustainability-related research culture. Where no evidence exists, this helps us plan University-wide measurement (e.g. staff and graduate researcher surveys) from 2027. | H103: N/A – new indicator
B104: TR3(d) | C104: Transformational research | D104: Embed sustainability within research systems, processes, capability and culture, so research is conducted responsibly, efficiently and with reduced environmental impact. | E104: Expert assessment of progress in embedding sustainable research practices across the institution. | F104: Drawing on your responses to TR3(a)–(c), please provide a short overall assessment (2–3 sentences) of your faculty's progress in embedding sustainable research practices: where progress is strongest, the main gaps, and priority actions for 2027. | G104: We will use faculty self-assessments to identify strengths, gaps and priority actions in embedding sustainable research practices, to inform internal management reporting and the Transformational research working group. | H104: N/A – new indicator
B105: CL2(a) | C105: Climate leadership | D105: Develop understanding of our research and education programs that contribute to accelerating global decarbonisation and our own climate transition. | E105: By 2028, develop and document institutional mapping of research and education activities that are designed to contribute to global decarbonisation | F105: Please list up to three examples of 2026 communications from your faculty that showcase climate action, research or learning and aim to inform policy, sector or community decarbonisation (e.g. policy submissions, public events, media, reports). Include links, the intended audience and any reach data you have. This will also contribute to the University's mapping of decarbonisation-related research and education (due by 2028). | G105: We will use these examples to show how the University communicates climate research and learning to external audiences, and as an input to the institutional decarbonisation research and education mapping due by 2028. | H105: N/A – new indicator
B106: CL2(c) | C106: Climate leadership | D106: Develop understanding of our research and education programs that contribute to accelerating global decarbonisation and our own climate transition. | E106: Ongoing communications that evidence the University’s climate action, research and learning to inform policy, sector and community decarbonisation efforts. | F106: If not already covered in CL2(a), please list any ongoing channels or programs (e.g. event series, newsletters, podcasts, policy engagement) through which your faculty regularly communicates climate research and learning to policy, sector or community audiences. You may respond 'see CL2(a)' if already covered. We will also engage Melbourne Climate Futures and the Melbourne Energy Institute. | G106: We will report on the University's ongoing climate communications in the Climate leadership section of the 2026 Sustainability Report, alongside contributions from Melbourne Climate Futures and the Melbourne Energy Institute. | H106: N/A – new indicator
