Workbook

Sheet 0. Read me
A1: ↑ | B1: SR26 data collection master spreadsheet
B2: 2026 Sustainability Report – data collection master
B4: Purpose | C4: Central record of SR26 data requirements, owners, reporting requests, responses and evidence. Adapted from the 2025 end-year reporting master spreadsheet (V0.2) and the Sustainability 2030 updated targets (Qual and Quan worksheets).
B5: Status | C5: DRAFT v0.9 – pilot with 4 faculties (ABP, ARTS, FBE, SCI) and 11 central units (CI&S, CFOG, ESG, CIOG, MRE, AC&M, GCE, Education, SaSS, Indigenous, L&R).
B6: Reporting approach | C6: Transition year: cover all of CY2026, distinguishing former Sustainability Plan 2030 activity from foundations and early actions after the Sustainability 2030 launch (~20 Oct 2026). Databook is the authoritative quantitative source. Target status (Met/Partially met/Not met) retained for now for internal management reporting – rating framework under review.
B7: Key dates (TBC) | C7: Early engagement (existing meetings): w/c 26 Oct 2026 | Requests issued: W1 Nov (from 2 Nov) | Collection period incl. optional 1:1 meetings: 2 Nov – 15 Dec (6 weeks) | Responses and highlighted stories due: Tuesday 15 December 2026 | First review: W3 Dec | Targeted follow-up: W3–W4 Dec | Consolidated master: W4 Dec | Sustainability Reporting Review Group: ~15 Feb 2027 | VCAG: 16 Feb & ~2 Mar 2027
B8: Tabs | C8: 1. Requirements matrix – every S2030 qualitative indicator, owner and request 2. Quant coverage – every quantitative indicator checked against the Databook draft, owner and action 2b. Databook register – every Databook data point with columns to confirm definition, source, owner 3. Stakeholder map – SR25 → SR26 unit mapping 3b. RASCI matrix – A/R/S/C/I roles per indicator and area (SR25 RASCI format), with counts 3c. RASCI triangulation – SR26 roles cross-checked against the SR25 RASCI, gaps flagged 4. Request tracker – sent/chased/received/confirmed status and response rate Faculties / CI&S / CFOG / ESG / CIOG / MRE / L&R – consolidated responses (copy in from returned request workbooks; same layout) Highlighted stories – consolidated optional stories and case-study shortlist A1. Data scoring – auto-pulls every unit's responses per indicator and scores target status (SR25 method) 0.5 Target Check – which units were asked about each indicator T1. Manual target review – every indicator with responses from the units asked, side by side, plus reviewer notes T2. Single target review – pick an indicator and see all units' responses and the scored status Request wording log – original S2030 wording vs tailored faculty request wording Evidence register – source, evidence, limitations and owner confirmation for every material claim Issues log – open questions, TBCs and decisions Project management tabs (overview, plan, timeline, comms/web to-do, content checklist, page index) are in the separate 'SR26 project management' workbook
B9: Refs | C9: Refs are new SR26 codes: priority-area code + target number + indicator letter (e.g. EE1(a) = Exceptional education, target 1, indicator a). 'Related SR25 ref' links to the closest SP2030 (2025) target where one exists.
B10: Regenerating | C10: Workbooks are generated by build.py in the repository. Edit the settings at the top (due dates, pilot faculties, unit mapping) and re-run to produce request workbooks for additional faculties/units.
B11: Version history | C11: v0.1: First draft: requirements matrix, pilot faculty and central-unit requests, tracker, evidence register. v0.2: SR25-style faculty wording and 'How SST will use'; scoring/T1/T2 formulas; Legal & Risk; project tabs; linked SR25 responses tab. v0.3: Quantitative indicators separated: removed from requirements matrix; '2. Quant coverage' and '2b. Databook register' against the Databook draft; '4. Quantitative data' tab in central-unit requests. v0.4: RASCI rebuilt to the SR25 standard ('3b. RASCI matrix'): indicator hierarchy, consolidated portfolios, SST contacts, A/R/S/C/I codes, summary counts. v0.5: '3c. RASCI triangulation': each SR26 indicator compared with the SR25 RASCI (equivalent targets, translated areas), gaps and suggested actions. v0.6: Chancellery units added following SR25 (ACM, CGCE, Chancellery Education, SASS, Chancellery Indigenous) with linked SR25 responses; cross-tab consistency check (check.py); Impact column added to Issues log (as SR25). v0.7: Team review: Chancellery units as separate tabs (AC&M, MRE, GCE, Education, SaSS, Indigenous); faculty requests cut down (ABP walkthrough) – EE1(a)+(c) merged, 'any examples' wording, alumni to SaSS, CL2(a)/(c) to AC&M, TR3(a)/(c)/(d) to MRE; simpler evidence register; highlighted stories compiled per unit with SST priority-area columns; project tabs moved to a separate project workbook. v0.8: TR1(b)–(d) to MRE only; EN1(d) removed from faculties (9 faculty questions); note on EE1(c) in T1/T2 that faculty answers sit under EE1(a). v0.9: Team timeline applied: early engagement w/c 26 Oct; requests W1 Nov; due 15 Dec 2026 (responses and stories); first review W3 Dec; follow-up W3–W4 Dec; consolidation W4 Dec; CDSS as contact; optional 1:1 meetings; tracker statuses and project timeline updated.
B12: Request wording | C12: Faculty requests are rewritten in the SR25 style and point to each faculty's end-2025 response (see Request wording log). Central-unit requests use the S2030 'Qual' worksheet wording as-is.
B13: Formulas | C13: Responses must be pasted into the Faculties/central-unit tabs keeping the same rows – A1, 0.5 and T2 look them up by Ref. Do not insert rows inside a block; add new units by re-running build.py.

Sheet 1. Requirements matrix
A1: ↑ | B1: End-2026 target status assessment and reporting
B2: 1. Requirements matrix (qualitative)
B5: Ref | C5: Domain | D5: Priority area | E5: Target | F5: Indicator | G5: Reporting requirement (S2030 Qual sheet) | H5: Key stakeholders (S2030 sheet) | I5: SR26 request issued to | J5: Specific projects we are aware of (area & person) | K5: Internal vs External | L5: Flag for continuous improvement | M5: Notes | N5: Related SR25 ref | O5: Channel | P5: Quantitative component | Q5: Owner confirmed?
B6: EE1(a) | C6: Education and research | D6: Exceptional education | E6: Provide our students with learning experiences that help them build the knowledge, skills and relationships to lead change for sustainable societies. | F6: Evidence of innovative approaches to sustainability teaching and learning | G6: Please describe any innovative approaches used within your Faculty/Portfolio to embed sustainability in teaching and learning. This could include examples of subjects, curriculum design, pedagogies, assessment approaches or learning resources. Please provide links or supporting evidence where available. | H6: Faculties, CI&S | I6: Faculties (pilot), CI&S, Education | K6: Both | L6: No | N6: 4a(ii) | O6: Tailored request
B7: EE1(b) | C7: Education and research | D7: Exceptional education | E7: Provide our students with learning experiences that help them build the knowledge, skills and relationships to lead change for sustainable societies. | F7: Pilots of possible approaches for understanding and developing students’ sustainability self-efficacy | G7: Please describe any pilots or trials undertaken within your Faculty/Portfolio to understand or strengthen students’ sustainability self-efficacy. This could include the approach used, participating cohorts, what was assessed or learned, and any planned next steps. | H7: Faculties, CI&S | I7: Faculties (pilot), CI&S, Education | J7: * Living Lab project (case study): Personalising Sustainability Pathways for students - Sustainability Strengths Compass. Project lead: Dianne Vella Brodrick. Funded partly by the Campus Living Lab Accelerator Program (CLLAP) (SST) | K7: Both | L7: No | O7: Tailored request
B8: EE1(c) | C8: Education and research | D8: Exceptional education | E8: Provide our students with learning experiences that help them build the knowledge, skills and relationships to lead change for sustainable societies. | F8: Evidence of sustainability focused experiential and co curricular learning (eg Wattle Fellowship; Melbourne Plus) | G8: Please provide examples of sustainability-focused experiential or co-curricular learning offered or supported by your Faculty/Portfolio (e.g. Wattle Fellowship, Melbourne Plus or similar), could include participation where available and a brief description of the learning experience and outcomes. | H8: Faculties, CI&S | I8: CI&S, SaSS | J8: * Wattle Fellowship (Linh Do); Wattle Fellowship could provide case studies and have an annual report. * Student and Scholarly Services (SASS - Melbourne Plus - Jess Trevitt) - how would we frame the ask differently for these data owners since we already know they offer experiential/co-curriculuar learning? SASS and Melbourne Plus can provide number of completions of students in the Sustainability Advocacy stream, and case studies. | K8: Both | L8: No | O8: Tailored request | P8: Yes – Yes – data held (2023–2025); see 2. Quant coverage
B9: EE1(d) | C9: Education and research | D9: Exceptional education | E9: Provide our students with learning experiences that help them build the knowledge, skills and relationships to lead change for sustainable societies. | F9: Alumni profiles demonstrating how graduates contribute to sustainability through their careers or communities. | G9: Please provide examples or profiles of graduates or alumni from your Faculty who demonstrate how they apply sustainability knowledge, skills or capabilities through their careers, communities or other activities. Where available, include any evidence used by the Faculty to understand graduate outcomes related to sustainability. | H9: Faculties, CI&S | I9: SaSS | K9: Both | L9: No | N9: 4b(i) | O9: Tailored request | P9: Yes – Yes – metrics defined, no data yet; see 2. Quant coverage
B10: TR1(a) | C10: Education and research | D10: Transformational research | E10: Utilise the expertise of the University’s researchers through mutually beneficial partnerships to help address the University’s operational sustainability challenges. | F10: Expert-reviewed evidence of researchers contributing to operational sustainability priorities through partnerships, advisory input, living labs, applied projects or decision-support | G10: Please provide examples of researchers within your Faculty/Portfolio contributing to University operational sustainability priorities through partnerships, advisory input, living labs, applied projects or decision-support. Briefly describe the operational challenge, researcher contribution and resulting or expected outcome. | H10: Faculties, CI&S | I10: Faculties (pilot), CI&S | J10: MRE Campus Living Lab Accelerator Program (CLLAP) case studies (CI&S). Also Enterprise Services Group - Campus Operations and Delivery (COD) might have collaborations we're not aware of (e.g. Rachael Miller) | K10: Both | L10: No | N10: 2a | O10: Tailored request
B11: TR1(b) | C11: Education and research | D11: Transformational research | E11: Utilise the expertise of the University’s researchers through mutually beneficial partnerships to help address the University’s operational sustainability challenges. | F11: Evidence of institutional pathways that enable ongoing collaboration between academic and professional staff | G11: Please describe any pathways, mechanisms or processes within your Faculty/Portfolio that enable ongoing collaboration between academic and professional staff on operational sustainability challenges, could include formal programs, governance arrangements, funding mechanisms or coordination channels. | H11: Faculties | I11: MRE | J11: MRE | K11: Both | L11: No | O11: Tailored request
B12: TR1(c) | C12: Education and research | D12: Transformational research | E12: Utilise the expertise of the University’s researchers through mutually beneficial partnerships to help address the University’s operational sustainability challenges. | F12: Expert assessment of the quality, relevance and continuity of these collaborations | G12: Please provide an assessment of the quality, relevance and continuity of sustainability-related collaborations involving your Faculty/Portfolio, could include evidence of whether collaborations are sustained, useful to operational priorities and producing relevant outcomes. | H12: Faculties | I12: MRE | J12: MRE | K12: Both | L12: No | O12: Tailored request
B13: TR1(d) | C13: Education and research | D13: Transformational research | E13: Utilise the expertise of the University’s researchers through mutually beneficial partnerships to help address the University’s operational sustainability challenges. | F13: Periodic feedback from participants on the effectiveness and mutual benefit of collaboration mechanisms. | G13: Please provide any participant feedback or other evidence from your Faculty/Portfolio on the effectiveness and mutual benefit of collaboration mechanisms between researchers and operational teams, could include key findings and any improvements identified. | H13: Faculties | I13: MRE | J13: MRE | K13: Both | L13: No | O13: Tailored request
B14: TR2(a) | C14: Education and research | D14: Transformational research | E14: Deliver high-quality research and partnerships that contribute to sustainability outcomes and demonstrable societal benefit. | F14: Evidence of sustainability-related research impact across diverse pathways, could include policy, industry, community, practice, cultural and institutional outcomes | G14: Please provide examples of sustainability-related research impact from your Faculty/Portfolio across policy, industry, community, practice, cultural or institutional pathways. For key examples, briefly describe the research contribution, partner/user and resulting outcome or influence. | H14: Faculties | I14: Faculties (pilot), AC&M | J14: Melbourne Research and Enterprise (Nishi Raja-Stranger and Ivan Marusic) Strategic Communications - Research lead will be able to identify examples of impactful sustainability-related research; also Pursuit (may be via Strat Comms too) Melbourne Climate Futures (Ben Neville, Beth Barber, Belle Workman) - MCF produce an annual impact report we could refer to. Melbourne Biodiversity Insitute (Brendan Wintle, Alanta Colley, Rachel Morgain) Possibly Melbourne Energy Institute. MDHS Climate CATCH Lab and other specific research centres could be approached and asked about their impact, or we could flag specific research centres in faculty requests. | K14: Both | L14: No | N14: 5b(i) | O14: Tailored request
B15: TR2(c) | C15: Education and research | D15: Transformational research | E15: Deliver high-quality research and partnerships that contribute to sustainability outcomes and demonstrable societal benefit. | F15: Expert-reviewed summary of sustainability-related research outputs, outcomes and influence using available institutional evidence sources | G15: currently mapped to the SDGs using SciVal | H15: MRE | I15: MRE | K15: Both | L15: No | O15: Tailored request | P15: Yes – Yes – data held (2025); see 2. Quant coverage
B16: TR2(d) | C16: Education and research | D16: Transformational research | E16: Deliver high-quality research and partnerships that contribute to sustainability outcomes and demonstrable societal benefit. | F16: Case-based evidence demonstrating how research has contributed to meaningful sustainability outcomes. | G16: Please provide case studies from your Faculty/Portfolio demonstrating how research has contributed to meaningful sustainability outcomes. Briefly describe the research, stakeholders involved, pathway to impact and evidence of the resulting sustainability outcome. | H16: Faculties, CI&S | I16: Faculties (pilot), CI&S | J16: Strategic Communications - Research lead will be able to identify examples of impactful sustainability-related research; also Pursuit (may be via Strat Comms too) Melbourne Climate Futures (Ben Neville, Beth Barber, Belle Workman) Melbourne Biodiversity Insitute (Brendan Wintle, Alanta Colley, Rachel Morgain) Possibly Melbourne Energy Institute. | K16: Both | L16: No | N16: 5b(i) | O16: Tailored request
B17: TR3(a) | C17: Education and research | D17: Transformational research | E17: Embed sustainability within research systems, processes, capability and culture, so research is conducted responsibly, efficiently and with reduced environmental impact. | F17: Evidence that sustainability considerations are integrated into relevant research systems, planning processes, guidance, training, induction or support services | G17: Please describe how sustainability considerations are integrated into research systems, planning processes, guidance, training, induction or support services within your Faculty/Portfolio, could include examples of any new or improved processes. | H17: Faculties, CI&S | I17: MRE | K17: Both | L17: No | N17: 5c(ii) | O17: Tailored request
B18: TR3(b) | C18: Education and research | D18: Transformational research | E18: Embed sustainability within research systems, processes, capability and culture, so research is conducted responsibly, efficiently and with reduced environmental impact. | F18: Demonstrated examples of more sustainable research practices in laboratories, fieldwork, procurement, travel or infrastructure use | G18: Please describe any efforts within your Faculty/Portfolio to make research practices more sustainable, could include examples from laboratories, fieldwork, procurement, research travel or infrastructure use. Where available, provide evidence of uptake, resource savings, emissions reductions or other outcomes. | H18: Faculties, CI&S, CFOG | I18: Faculties (pilot), CI&S, CFOG | K18: Both | L18: No | N18: 5c(ii) | O18: Tailored request | P18: Yes – Yes – metrics defined, no data yet; see 2. Quant coverage
B19: TR3(c) | C19: Education and research | D19: Transformational research | E19: Embed sustainability within research systems, processes, capability and culture, so research is conducted responsibly, efficiently and with reduced environmental impact. | F19: Evidence of progress in sustainability-related research culture, capability and awareness, informed by periodic staff and graduate researcher surveys | G19: Please provide evidence of progress in sustainability-related research culture, capability and awareness within your Faculty/Portfolio. This could include relevant staff and/or graduate researcher survey findings, participation in capability-building activities, or other indicators of change over time. | H19: Faculties | I19: MRE | J19: Melbourne Research and Enterprise (Nishi Raja-Stranger; Ivan Marusic) - MRE will be a key reporter for all research targets. | K19: Both | L19: No | O19: Tailored request
B20: TR3(d) | C20: Education and research | D20: Transformational research | E20: Embed sustainability within research systems, processes, capability and culture, so research is conducted responsibly, efficiently and with reduced environmental impact. | F20: Expert assessment of progress in embedding sustainable research practices across the institution. | G20: Faculty/Portfolio’s assessment of progress in embedding sustainable research practices, highlighting areas of strong progress, remaining gaps and priority actions for further improvement. | H20: Faculties | I20: MRE | K20: Both | L20: No | O20: Tailored request
B21: CL1(c) | C21: Sustainability leadership | D21: Climate leadership | E21: Achieve net zero emissions by 2050: Interim target Reduce emissions by 20% across all emissions scopes by CY2030 on the CY2023 re-baseline including: • Scopes 1 and 2: 66% reduction • Scope 3: 12% reduction. Long-term target Reduce emissions by 90% across all emissions scopes by CY2050 on the CY2023 re-baseline and invest in carbon removal credits for residual emissions from hard-to-abate sources (up to 10%). | F21: Review of Climate Leadership targets by 2030.[2] | H21: CI&S | I21: CI&S | K21: Both | L21: Yes | M21: Need to review again on 2030. The climate target itself is still two months old | O21: Tailored request | P21: Yes – No; see 2. Quant coverage
B22: CL2(a) | C22: Sustainability leadership | D22: Climate leadership | E22: Develop understanding of our research and education programs that contribute to accelerating global decarbonisation and our own climate transition. | F22: By 2028, develop and document institutional mapping of research and education activities that are designed to contribute to global decarbonisation | G22: Please list and describe examples of communications from your Faculty/Portfolio that demonstrate climate action, research and learning and aim to inform policy, sector or community decarbonisation efforts. Could include links, intended audiences and any available evidence of reach or influence. | H22: Faculties, CI&S | I22: AC&M | K22: Both | L22: No | O22: Tailored request | P22: Yes – Yes – metrics defined, no data yet; see 2. Quant coverage
B23: CL2(c) | C23: Sustainability leadership | D23: Climate leadership | E23: Develop understanding of our research and education programs that contribute to accelerating global decarbonisation and our own climate transition. | F23: Ongoing communications that evidence the University’s climate action, research and learning to inform policy, sector and community decarbonisation efforts. | G23: List and describe communications from the faculty in terms of climate action, research and learning to inform policy, sector and community decarbonisation efforts | H23: Faculties, | I23: AC&M | K23: Both | L23: No | O23: Tailored request | P23: Yes – Yes – metrics defined, no data yet; see 2. Quant coverage
B24: CL3(a) | C24: Sustainability leadership | D24: Climate leadership | E24: Reach and maintain high levels of climate-change resilience maturity | F24: Maturity assessment of the University’s preparedness for climate-related impacts and capability to respond, assessed across relevant organisational functions: o Governance and strategy o Health and safety o Business continuity o Emergency management and critical incidence management o Estate and buildings o Water management o Financial planning and reporting. | G24: Provide update of University maturity assesment. Include maturity ratings, key gaps and priority improvement actions.when available | H24: CI&S | I24: CI&S, L&R | K24: Both | L24: No | M24: Could check with Gerard. Gerard is the one who manage this indicator | O24: Tailored request | P24: Yes – Yes – metrics defined, no data yet; see 2. Quant coverage
B25: NB1(b) | C25: Sustainability leadership | D25: Nature and biodiversity | E25: Achieve an increase of biodiversity relative to defined baseline years for each campus. | F25: Size, health and diversity of remnant vegetation at the Dookie and Creswick campuses | H25: Rachel | I25: ESG | K25: Internal | L25: No | M25: Havent been previously disclose publicly | O25: Tailored request | P25: Yes – No; see 2. Quant coverage
B26: NB1(c) | C26: Sustainability leadership | D26: Nature and biodiversity | E26: Achieve an increase of biodiversity relative to defined baseline years for each campus. | F26: Defined quality measurement framework | H26: ESG | I26: ESG | K26: Both | L26: No | M26: Follow up with Rachel | O26: Tailored request | P26: Yes – No; see 2. Quant coverage
B27: NB1(d) | C27: Sustainability leadership | D27: Nature and biodiversity | E27: Achieve an increase of biodiversity relative to defined baseline years for each campus. | F27: Defined and quantified campus connectivity | G27: Please provide the current definition and quantified assessment of campus ecological connectivity, could include the methodology used, campuses covered, baseline or benchmark values, and any material change over the reporting period. | H27: ESG | I27: ESG | K27: Both | L27: No | O27: Tailored request | P27: Yes – No; see 2. Quant coverage
B28: NB2(a) | C28: Sustainability leadership | D28: Nature and biodiversity | E28: Improve our understanding of our supply chain impacts on nature. | F28: Documented baseline nature footprint analysis | G28: Impact Encore Measurement | H28: MBI | I28: MRE | K28: Both | L28: No | O28: Tailored request | P28: Yes – Yes – metrics defined, no data yet; see 2. Quant coverage
B29: NB2(b) | C29: Sustainability leadership | D29: Nature and biodiversity | E29: Improve our understanding of our supply chain impacts on nature. | F29: Evidence of established framework to monitor and track supply-chain nature impacts over time | G29: Please describe the framework established to monitor and track supply-chain impacts on nature over time, could include metrics, data sources, governance/ownership, reporting frequency and current implementation status. | H29: ESG | I29: ESG | J29: Melbourne Biodiversity Institute (MBI) - Brendan Wintle and August Wylynko | K29: Both | L29: No | O29: Tailored request
B30: NB2(c) | C30: Sustainability leadership | D30: Nature and biodiversity | E30: Improve our understanding of our supply chain impacts on nature. | F30: Evidence of prioritised high risk procurement categories or suppliers for nature impact management | G30: Please provide the prioritised high-risk procurement categories and/or suppliers identified for nature-impact management, could include the basis for prioritisation and any risk-management, engagement or mitigation actions undertaken or planned. | H30: ESG, CFOG | I30: CFOG, ESG | J30: MBI | K30: Both | L30: No | O30: Tailored request
B31: AI1(a) | C31: Sustainability leadership | D31: Responsible AI | E31: Improve understanding of our sustainability-related risks and opportunities of AI technologies by 2028. | F31: Established measurement of estimated operational impacts and opportunities (eg operational impacts could include energy, water, emissions and intensity measures) | H31: CI&S, CIOG | I31: CI&S, CIOG | K31: Both | L31: Yes | M31: Rose & Sally currently actively managing this target and indicator. High level overview on 2026, will work on the detailed measurement next year | O31: Tailored request | P31: Yes – No; see 2. Quant coverage
B32: AI1(b) | C32: Sustainability leadership | D32: Responsible AI | E32: Improve understanding of our sustainability-related risks and opportunities of AI technologies by 2028. | F32: Case studies of sustainability and AI-related education, research and collaboration activities. | G32: Please provide case studies from your Faculty/Portfolio of sustainability and AI-related education, research or collaboration activities, describing the activity, participants or partners, sustainability issue addressed and key outcomes or lessons. | H32: CI&S, CIOG | I32: CI&S, CIOG | J32: AI Steering Committee - developing AI roadmap, which includes responsible AI as a key pillar. | K32: Both | L32: No | O32: Tailored request
B33: EI1(a) | C33: Resilient University | D33: Estate and infrastructure | E33: Integrate environmental sustainability in the way that the University achieves strategic and operational objectives for our estate and infrastructure. | F33: Evidence of increased maturity of estate and infrastructure planning, development and operations to support the other priority areas in Sustainability 2030 | G33: Case study evidence of increased sustainability maturity in estate and infrastructure planning, development and operations, could include examples of changes to standards, processes, governance, decision-making or project requirements that support Sustainability 2030 priority areas. | H33: CI&S | I33: CI&S | J33: CI&S - Estate Planning and Development teams | K33: Both | L33: No | M33: Facilitated by Gerard | O33: Tailored request | P33: Yes – No; see 2. Quant coverage
B34: EI1(b) | C34: Resilient University | D34: Estate and infrastructure | E34: Integrate environmental sustainability in the way that the University achieves strategic and operational objectives for our estate and infrastructure. | F34: Estimated sustainability impacts of the University’s estate and infrastructure capital plan to inform progress towards emissions reduction targets and other priority areas (to the extent enabled by available information) | G34: Please provide any available information on sustainability impacts associated with estate and infrastructure projects or capital works relevant to your Faculty/Portfolio. This could include impacts related to emissions and other Sustainability 2030 priority areas. | H34: CI&S | I34: CI&S | J34: CI&S - Estate Planning and Development teams | K34: Both | L34: No | O34: Tailored request | P34: Yes – No; see 2. Quant coverage
B35: EI1(c) | C35: Resilient University | D35: Estate and infrastructure | E35: Integrate environmental sustainability in the way that the University achieves strategic and operational objectives for our estate and infrastructure. | F35: Reporting on relevant activities and impacts for the University’s major estate and infrastructure projects and programs aligned with the other priority areas in Sustainability 2030 | G35: Please provide an update on sustainability-related activities and impacts for major estate and infrastructure projects or programs relevant to your Faculty/Portfolio. This could include key initiatives, relevant performance measures and alignment with Sustainability 2030 priority areas. | H35: CI&S | I35: CI&S | J35: CI&S - Estate Planning and Development teams | K35: Both | L35: No | O35: Tailored request | P35: Yes – No; see 2. Quant coverage
B36: EI1(d) | C36: Resilient University | D36: Estate and infrastructure | E36: Integrate environmental sustainability in the way that the University achieves strategic and operational objectives for our estate and infrastructure. | F36: Evidence of understanding and integration of Indigenous approaches to sustainability in estate planning and development programs and projects. | G36: Please provide examples showing how Indigenous approaches, knowledges or perspectives on sustainability have informed estate planning, development programs or projects relevant to your Faculty/Portfolio. This could include how Indigenous stakeholders were engaged and what changed as a result. | H36: CI&S | I36: CI&S | J36: CI&S - Estate Planning and Development teams | K36: Both | L36: No | O36: Tailored request
B37: RP1(a) | C37: Resilient University | D37: Responsible procurement | E37: Strengthen our ethical and sustainable procurement approach. | F37: Case studies of maturity improvement related to responsible procurement process and systems. | G37: Maturity score if framework established; % procurement staff trained | I37: CFOG | K37: Both | L37: No | M37: Quantitative metrics could support qualitative case studies to demonstrate system/process improvements | O37: Tailored request | P37: Yes – No; see 2. Quant coverage
B38: MS1(a) | C38: Resilient University | D38: Modern slavery and human rights | E38: Manage our approach to modern slavery and human rights-related risks and opportunities. | F38: Annual progress reporting via the Modern Slavery Statement | G38: Annual Modern Slavery Statement, with case studies | H38: CFOG, CI&S | I38: CI&S, CFOG | J38: CFOG - Procurement; Modern Slavery Working Group (existing). | K38: External | L38: No | O38: Tailored request
B39: RI1(b) | C39: Resilient University | D39: Responsible investments | E39: Achieve net zero financed emissions for the University’s investment portfolio by 2050. | F39: Continuous improvement of the reporting of the University’s sustainability-related investment profile metrics, could include investment in climate mitigation and transition solutions, and compliance with related obligations (eg UNPRI). | G39: Report on relevant sustainability-related investment portfolio metrics and report on how the University has complied with its related obligations | H39: CFOG, CI&S | I39: CI&S, CFOG | K39: Both | L39: No | O39: Tailored request | P39: Yes – Yes – data held (2023–2025); see 2. Quant coverage
B40: EN1(a) | C40: Enablers | D40: Enablers | E40: Enablers | F40: Evidence of sustainability outcomes informed by Indigenous knowledges | G40: Please provide examples or case studies from your Faculty/Portfolio of sustainability outcomes informed by Indigenous knowledges. Describe the activity or decision, how Indigenous knowledges were incorporated or co-created, who was involved, and the resulting sustainability outcome. | H40: Faculties | I40: Faculties (pilot), GCE, Indigenous | J40: For discussion - it would be good to chat about the nuances of this one | K40: Both | L40: No | N40: 6a | O40: Tailored request
B41: EN1(b) | C41: Enablers | D41: Enablers | E41: Enablers | F41: Living laboratories enabling applied learning, research and operational sustainability outcomes | G41: Comment on living labs in the Faculty - outputs, outcomes, and impact | H41: Faculties, CI&S | I41: Faculties (pilot), CI&S | J41: SST is a key data owner: Can report on projects and outcomes from the Campus Living Lab Accelerator Program. Also will gather case studies from individual projects (4) | K41: Both | L41: No | N41: 2a | O41: Tailored request | P41: Yes – Yes – metrics defined, no data yet; see 2. Quant coverage
B42: EN1(c) | C42: Enablers | D42: Enablers | E42: Enablers | F42: Coordinated internal engagement and external partnerships contributing to delivery of sustainability outcomes across priority areas. | G42: Please provide examples of internal engagement or external partnerships involving your Faculty/Portfolio that contributed to Sustainability 2030 outcomes, could include the priority area addressed, participating groups/partners, nature of the collaboration and key outcomes. | H42: Faculties, CIOG, CFOG, CI&S, ESG | I42: Faculties (pilot), CI&S, CFOG, ESG, CIOG, AC&M, GCE, Education | J42: Noting a gap - we used to collect data from Advancement on the number of sustainability-focused events and attendees. We don't have an indicator that captures that now but it would fit under Engagement and Partnerships. For discussion: Should we collect this data and find a place to report it? (Data owners: Advancement, Karl Brown) The Global, Culture and Engagement team also provided us with case studies where sustainability is embedded in partnerships, or where students are engaging with sustainability in learning opportunities. They will have a case study this year about the winter school they ran which was focused on the SDGs. Main data owners/contacts: Charmaine Monteiro (Global); Padmini Sebastian (Engagement); also - we haven't engaged the 'Culture' part of GCE - should we engage them this year for case studies? | K42: Both | L42: No | N42: 3a(ii) | O42: Tailored request
B43: EN1(d) | C43: Enablers | D43: Enablers | E43: Enablers | F43: Sustainability objectives integrated into governance and decision‑making processes, supported by transparent reporting. | G43: Please provide evidence of how sustainability objectives are integrated into governance and decision-making within your Faculty/Portfolio, could include relevant committees, policies, planning or approval processes, accountability mechanisms and examples of transparent reporting. | H43: Faculties, CIOG, CFOG, CI&S, ESG | I43: CI&S, CFOG, ESG, CIOG | J43: Reporting working group set up - talking about potential alignment with ASRS in future. Collaboration of SST, FBE (Accounting) and the Finance team in CFOG. Sally is the key contact for more info. | K43: Both | L43: No | O43: Tailored request

Sheet 2. Quant coverage
A1: ↑ | B1: End-2026 target status assessment and reporting
B2: 2. Quantitative indicators – Databook coverage
B3: The Sustainability Databook is the authoritative quantitative source (SR26 approach). Each quantitative indicator is checked against the Databook draft: figures held are confirmed by the owner; gaps are requested in Tab 4 of that owner's request. Faculties are not asked for quantitative data. Data points are listed in '2b. Databook register'.
B5: Ref | C5: Priority area | D5: Indicator | E5: Type | F5: Quant? (Y/M) | G5: Suggested metric (Quan sheet) | H5: In Databook draft? | I5: No. of data points | J5: Suggested data owner | K5: Action | L5: Requested in | M5: Status | N5: Notes
B6: EE1(c) | C6: Exceptional education | D6: Evidence of sustainability focused experiential and co curricular learning (eg Wattle Fellowship; Melbourne Plus) | E6: Mixed – narrative in requirements matrix; metric here | F6: M | G6: Number of experiential learning projects; number of participating students | H6: Yes – data held (2023–2025) | I6: 3 | J6: SaSS | K6: Owner confirms existing figures and provides CY2026 (provisional by 15 Dec, final Jan–Feb) – Tab 4 of owner's request | L6: SaSS request – Tab 4 | M6: Not started
B7: EE1(d) | C7: Exceptional education | D7: Alumni profiles demonstrating how graduates contribute to sustainability through their careers or communities. | E7: Mixed – narrative in requirements matrix; metric here | F7: M | G7: Number of alumni that contribute to sustainability; % profiles demonstrating sustainability contribution; insights form different industries that influenced by alumni | H7: Yes – metrics defined, no data yet | I7: 2 | J7: SaSS | K7: Owner provides CY2026 (and earlier years if available) and confirms metric definition – Tab 4 of owner's request | L7: SaSS request – Tab 4 | M7: Not started
B8: TR2(b) | C8: Transformational research | D8: Documented progress of relevant strategic initiatives, including Impact Accelerators | E8: Quantitative only – removed from requirements matrix | F8: Y | G8: Percentage of milestone completion rate to the set annual target of strategic initiatives; number of initiatives on track; number of initiatives delivered | H8: Yes – metrics defined, no data yet | I8: 5 | J8: MRE | K8: Owner provides CY2026 (and earlier years if available) and confirms metric definition – Tab 4 of owner's request | L8: MRE request – Tab 4 | M8: Not started
B9: TR2(c) | C9: Transformational research | D9: Expert-reviewed summary of sustainability-related research outputs, outcomes and influence using available institutional evidence sources | E9: Mixed – narrative in requirements matrix; metric here | F9: Y | G9: currently mapped to the SDGs using SciVal, old metrics explorer (publication mapped to SDG whether they mentioned in mews, media, policy,etc), | H9: Yes – data held (2025) | I9: 86 | J9: MRE | K9: Owner confirms existing figures and provides CY2026 (provisional by 15 Dec, final Jan–Feb) – Tab 4 of owner's request | L9: MRE request – Tab 4 | M9: Not started
B10: TR3(b) | C10: Transformational research | D10: Demonstrated examples of more sustainable research practices in laboratories, fieldwork, procurement, travel or infrastructure use | E10: Mixed – narrative in requirements matrix; metric here | F10: M | G10: Number of laboratories achieving green lab certification; number of new sustainable activity; number of sustainability fieldwork | H10: Yes – metrics defined, no data yet | I10: 3 | J10: MRE | K10: Owner provides CY2026 (and earlier years if available) and confirms metric definition – Tab 4 of owner's request | L10: MRE request – Tab 4 | M10: Not started
B11: CL1(a) | C11: Climate leadership | D11: Annual Greenhouse Gas Inventory (including emissions scopes 1, 2 and 3) demonstrates carbon emission reductions, including maintaining procurement of 100% renewable electricity for all scope 2 sources[1] | E11: Quantitative only – removed from requirements matrix | F11: Y | G11: Total scope 1,2 and 3 emissions (tCO2-e); emissions by scope; % reduction from previous baseline; % renewable electircity produced | H11: Yes – data held (2023–2025) | I11: 78 | J11: ESG | K11: Owner confirms existing figures and provides CY2026 (provisional by 15 Dec, final Jan–Feb) – Tab 4 of owner's request | L11: ESG request – Tab 4 | M11: Not started
B12: CL1(b) | C12: Climate leadership | D12: Development of Greenhouse Gas intensity metrics | E12: Quantitative only – removed from requirements matrix | F12: Y | G12: Greenhouse gas emissions by FTE, EFTSL, and Gross floor area (https://www.unimelb.edu.au/sustainabilityreport/2025/data-tables#GHGe-scope) | H12: Yes – data held (2023–2025) | I12: 8 | J12: ESG | K12: Owner confirms existing figures and provides CY2026 (provisional by 15 Dec, final Jan–Feb) – Tab 4 of owner's request | L12: ESG request – Tab 4 | M12: Not started
B13: CL1(c) | C13: Climate leadership | D13: Review of Climate Leadership targets by 2030.[2] | E13: Mixed – narrative in requirements matrix; metric here | F13: M | H13: No | I13: 0 | J13: ESG | K13: Not in Databook – decide: add metric to Databook, or report this indicator qualitatively only | M13: Not started
B14: CL2(a) | C14: Climate leadership | D14: By 2028, develop and document institutional mapping of research and education activities that are designed to contribute to global decarbonisation | E14: Mixed – narrative in requirements matrix; metric here | F14: M | G14: Number of relevant research projects/programs mapped; number of relevant subjects mapped | H14: Yes – metrics defined, no data yet | I14: 2 | J14: SST | K14: SST – compiled from faculty and CI&S responses | M14: Not started
B15: CL2(b) | C15: Climate leadership | D15: Prioritised pipeline of decarbonisation focused research and education opportunities aligned with University emissions reduction priorities from 2028 | E15: Quantitative only – removed from requirements matrix | F15: Y | G15: Number of pipelined projects or research transitioned from opportunity to active per year | H15: Yes – metrics defined, no data yet | I15: 1 | J15: SST | K15: SST – compiled from faculty and CI&S responses | M15: Not started
B16: CL2(c) | C16: Climate leadership | D16: Ongoing communications that evidence the University’s climate action, research and learning to inform policy, sector and community decarbonisation efforts. | E16: Mixed – narrative in requirements matrix; metric here | F16: M | G16: Annual count of published documents, policy briefs, or public engagement events; number of policy/sector engagement; # views of communication material | H16: Yes – metrics defined, no data yet | I16: 2 | J16: SST | K16: SST – compiled from faculty and CI&S responses | M16: Not started
B17: CL3(a) | C17: Climate leadership | D17: Maturity assessment of the University’s preparedness for climate-related impacts and capability to respond, assessed across relevant organisational functions: o Governance and strategy o Health and safety o Business continuity o Emergency management and critical incidence management o Estate and buildings o Water management o Financial planning and reporting. | E17: Mixed – narrative in requirements matrix; metric here | F17: M | G17: Maturity score by function; overall/average maturity score; % functions raching target maturity level | H17: Yes – metrics defined, no data yet | I17: 7 | J17: CI&S | K17: Owner provides CY2026 (and earlier years if available) and confirms metric definition – Tab 4 of owner's request | L17: CI&S request – Tab 4 | M17: Not started
B18: NB1(a) | C18: Nature and biodiversity | D18: Monitoring of biodiversity metrics from the Biodiversity Baseline Data Project | E18: Quantitative only – removed from requirements matrix | F18: Y | G18: 7 diversity metrics from https://sustainablecampus.unimelb.edu.au/biodiversity/biodiversity-baseline-data-project#main-content | H18: Yes – data held (2025) | I18: 63 | J18: ESG | K18: Owner confirms existing figures and provides CY2026 (provisional by 15 Dec, final Jan–Feb) – Tab 4 of owner's request | L18: ESG request – Tab 4 | M18: Not started
B19: NB1(b) | C19: Nature and biodiversity | D19: Size, health and diversity of remnant vegetation at the Dookie and Creswick campuses | E19: Mixed – narrative in requirements matrix; metric here | F19: Y | H19: No | I19: 0 | J19: ESG | K19: Not in Databook – decide: add metric to Databook, or report this indicator qualitatively only | M19: Not started
B20: NB1(c) | C20: Nature and biodiversity | D20: Defined quality measurement framework | E20: Mixed – narrative in requirements matrix; metric here | F20: M | H20: No | I20: 0 | J20: ESG | K20: Not in Databook – decide: add metric to Databook, or report this indicator qualitatively only | M20: Not started
B21: NB1(d) | C21: Nature and biodiversity | D21: Defined and quantified campus connectivity | E21: Mixed – narrative in requirements matrix; metric here | F21: M | G21: Please provide the current definition and quantified assessment of campus ecological connectivity, could include the methodology used, campuses covered, baseline or benchmark values, and any material change over the reporting period. | H21: No | I21: 0 | J21: ESG | K21: Not in Databook – decide: add metric to Databook, or report this indicator qualitatively only | M21: Not started
B22: NB2(a) | C22: Nature and biodiversity | D22: Documented baseline nature footprint analysis | E22: Mixed – narrative in requirements matrix; metric here | F22: Y | G22: Impact Encore Measurement | H22: Yes – metrics defined, no data yet | I22: 7 | J22: MRE | K22: Owner provides CY2026 (and earlier years if available) and confirms metric definition – Tab 4 of owner's request | L22: MRE request – Tab 4 | M22: Not started
B23: AI1(a) | C23: Responsible AI | D23: Established measurement of estimated operational impacts and opportunities (eg operational impacts could include energy, water, emissions and intensity measures) | E23: Mixed – narrative in requirements matrix; metric here | F23: M | G23: Pending denominator | H23: No | I23: 0 | J23: CIOG | K23: Not in Databook – decide: add metric to Databook, or report this indicator qualitatively only | M23: Not started
B24: EI1(a) | C24: Estate and infrastructure | D24: Evidence of increased maturity of estate and infrastructure planning, development and operations to support the other priority areas in Sustainability 2030 | E24: Mixed – narrative in requirements matrix; metric here | F24: M | G24: qual, climate resilience?, | H24: No | I24: 0 | J24: CI&S | K24: Not in Databook – decide: add metric to Databook, or report this indicator qualitatively only | M24: Not started
B25: EI1(b) | C25: Estate and infrastructure | D25: Estimated sustainability impacts of the University’s estate and infrastructure capital plan to inform progress towards emissions reduction targets and other priority areas (to the extent enabled by available information) | E25: Mixed – narrative in requirements matrix; metric here | F25: M | G25: Forecast operational emission (tCO2-e); expected energy consumptions/savings; expected water impact; expected waste material impact; potential biodiversity impact | H25: No | I25: 0 | J25: CI&S | K25: Not in Databook – decide: add metric to Databook, or report this indicator qualitatively only | M25: Not started
B26: EI1(c) | C26: Estate and infrastructure | D26: Reporting on relevant activities and impacts for the University’s major estate and infrastructure projects and programs aligned with the other priority areas in Sustainability 2030 | E26: Mixed – narrative in requirements matrix; metric here | F26: M | G26: case by case | H26: No | I26: 0 | J26: CI&S | K26: Not in Databook – decide: add metric to Databook, or report this indicator qualitatively only | M26: Not started
B27: CE1(a) | C27: Circular economy | D27: Comparison of year-to-year tonnes of waste (absolute). | E27: Quantitative only – removed from requirements matrix | F27: Y | G27: tonnes of waste; % change against previous baseline | H27: Yes – data held (2023–2025) | I27: 3 | J27: ESG | K27: Owner confirms existing figures and provides CY2026 (provisional by 15 Dec, final Jan–Feb) – Tab 4 of owner's request | L27: ESG request – Tab 4 | M27: Not started
B28: CE2(a) | C28: Circular economy | D28: Comparison of year-to-year tonnes of recyclables (absolute). | E28: Quantitative only – removed from requirements matrix | F28: Y | G28: waste diversion rate; tonnes diverted from landfill; % change against previous baseline | H28: Yes – data held (2023–2025) | I28: 3 | J28: ESG | K28: Owner confirms existing figures and provides CY2026 (provisional by 15 Dec, final Jan–Feb) – Tab 4 of owner's request | L28: ESG request – Tab 4 | M28: Not started
B29: RP1(a) | C29: Responsible procurement | D29: Case studies of maturity improvement related to responsible procurement process and systems. | E29: Mixed – narrative in requirements matrix; metric here | F29: Y | G29: Maturity score if framework established; % procurement staff trained | H29: No | I29: 0 | J29: CFOG | K29: Not in Databook – decide: add metric to Databook, or report this indicator qualitatively only | M29: Not started
B30: RP2(a) | C30: Responsible procurement | D30: Percentage of Indigenous spend of total addressable procurement spend | E30: Quantitative only – removed from requirements matrix | F30: Y | G30: Percentage of Indigenous spend of total addressable procurement spend | H30: Yes – metrics defined, no data yet | I30: 3 | J30: CFOG | K30: Owner provides CY2026 (and earlier years if available) and confirms metric definition – Tab 4 of owner's request | L30: CFOG request – Tab 4 | M30: Not started
B31: RP2(b) | C31: Responsible procurement | D31: Percentage of social spend of total addressable procurement spend. | E31: Quantitative only – removed from requirements matrix | F31: Y | G31: Percentage of social spend of total addressable procurement spend. | H31: Yes – metrics defined, no data yet | I31: 3 | J31: CFOG | K31: Owner provides CY2026 (and earlier years if available) and confirms metric definition – Tab 4 of owner's request | L31: CFOG request – Tab 4 | M31: Not started
B32: RI1(a) | C32: Responsible investments | D32: Annual monitoring and reporting on the investment portfolio’s net zero transition progress, including tracking the percentage of assets under management (AUM) managed by investment managers aligned with (or committed to) net zero by 2050 | E32: Quantitative only – removed from requirements matrix | F32: Y | G32: Percentage of AUM managed by investment managers aligned with net zero by 2050 | H32: Yes – metrics defined, no data yet | I32: 3 | J32: CFOG | K32: Owner provides CY2026 (and earlier years if available) and confirms metric definition – Tab 4 of owner's request | L32: CFOG request – Tab 4 | M32: Not started
B33: RI1(b) | C33: Responsible investments | D33: Continuous improvement of the reporting of the University’s sustainability-related investment profile metrics, could include investment in climate mitigation and transition solutions, and compliance with related obligations (eg UNPRI). | E33: Mixed – narrative in requirements matrix; metric here | F33: M | G33: $ and % AUM invested in climate/transition solution | H33: Yes – data held (2023–2025) | I33: 23 | J33: CFOG | K33: Owner confirms existing figures and provides CY2026 (provisional by 15 Dec, final Jan–Feb) – Tab 4 of owner's request | L33: CFOG request – Tab 4 | M33: Not started
B34: EN1(b) | C34: Enablers | D34: Living laboratories enabling applied learning, research and operational sustainability outcomes | E34: Mixed – narrative in requirements matrix; metric here | F34: M | G34: Number of projects funded; $ project funding | H34: Yes – metrics defined, no data yet | I34: 2 | J34: CI&S | K34: Owner provides CY2026 (and earlier years if available) and confirms metric definition – Tab 4 of owner's request | L34: CI&S request – Tab 4 | M34: Not started

Sheet 2b. Databook register
A1: ↑ | B1: End-2026 target status assessment and reporting
B2: 2b. Databook register (data points)
B3: Every data point in the Databook draft. Baseline–CY2025 are copied from the draft for context. Complete the yellow columns as owners confirm figures (SR26 approach: definition, boundary, period, source, owner, quality note and confirmation for each figure).
B5: Ref | C5: Priority area | D5: Indicator | E5: Metric | F5: Unit | G5: Baseline | H5: CY2023 | I5: CY2024 | J5: CY2025 | K5: CY2026 | L5: Data status | M5: Data owner | N5: Definition | O5: Reporting boundary | P5: Source system | Q5: Quality note / limitations | R5: Owner confirmed? | S5: Confirmation date
B6: EE1(c) | C6: Exceptional Education | D6: Evidence of sustainability focused experiential and cocurricular learning | E6: Number of Co-curricular Learning | F6: # | H6: 14 | I6: 22 | J6: 10 | L6: Data held | M6: SaSS
B7: EE1(c) | E7: Number of Experiential Learning Projects | F7: # | L7: No data yet | M7: SaSS
B8: EE1(c) | E8: Number of Participating Students | F8: # | L8: No data yet | M8: SaSS
B9: EE1(d) | C9: Exceptional Education | D9: Alumni profiles demonstrating how graduates contribute to sustainability through their careers or communities | E9: Alumni that contribute to sustainability | F9: # | L9: No data yet | M9: SaSS
B10: EE1(d) | E10: Alumni profiles demonstrating sustainability contribution | F10: % | L10: No data yet | M10: SaSS
B11: TR2(b) | C11: Transformational Research | D11: Documented progress of relevant strategic initiatives, including Impact Accelerators | E11: Completion rate to the set annual target of strategic initiatives
B12: TR2(b) | E12: Impact Accelerators | F12: % | L12: No data yet | M12: MRE
B13: TR2(b) | E13: Strategic Initiatives 2 | F13: % | L13: No data yet | M13: MRE
B14: TR2(b) | E14: Strategic Initiatives 3 | F14: % | L14: No data yet | M14: MRE
B15: TR2(b) | E15: Strategic Initiatives on track | F15: # | L15: No data yet | M15: MRE
B16: TR2(b) | E16: Strategic Initiatives delivered | F16: # | L16: No data yet | M16: MRE
B17: TR2(c) | C17: Transformational Research | D17: Expert-reviewed summary of sustainability-related research outputs, outcomes and influence using available institutional evidence sources | E17: SDG-related research outputs in the top 10% of citations
B18: TR2(c) | E18: SDG 1 - No Poverty | F18: # | J18: 424 | L18: Data held | M18: MRE
B19: TR2(c) | E19: SDG 2 - Zero Hunger | F19: # | J19: 781 | L19: Data held | M19: MRE
B20: TR2(c) | E20: SDG 3 - Good health and well-being | F20: # | J20: 15195 | L20: Data held | M20: MRE
B21: TR2(c) | E21: SDG 4 - Quality Education | F21: # | J21: 1292 | L21: Data held | M21: MRE
B22: TR2(c) | E22: SDG 5 - Gender Equality | F22: # | J22: 1275 | L22: Data held | M22: MRE
B23: TR2(c) | E23: SDG 6 - Clean water and sanitation | F23: # | J23: 661 | L23: Data held | M23: MRE
B24: TR2(c) | E24: SDG 7 - Affordable and clean energy | F24: # | J24: 997 | L24: Data held | M24: MRE
B25: TR2(c) | E25: SDG 8 - Decent work and economic growth | F25: # | J25: 995 | L25: Data held | M25: MRE
B26: TR2(c) | E26: SDG 9 - Industry, innovation and infrastructure | F26: # | J26: 1457 | L26: Data held | M26: MRE
B27: TR2(c) | E27: SDG 10 - Reduced inequality | F27: # | J27: 1617 | L27: Data held | M27: MRE
B28: TR2(c) | E28: SDG 11 - Sustainable cities and communities | F28: # | J28: 1436 | L28: Data held | M28: MRE
B29: TR2(c) | E29: SDG 12 - Responsible consumption and production | F29: # | J29: 838 | L29: Data held | M29: MRE
... B33: TR2(c) | E33: SDG 16 - Peace, justice and strong institutions | F33: # | J33: 1681 | L33: Data held | M33: MRE
B34: TR2(c) | E34: SDG-related research outputs in the top 10% of citations (Field-weighted)
B35: TR2(c) | E35: SDG 1 - No Poverty | F35: % | J35: 20 | L35: Data held | M35: MRE
B36: TR2(c) | E36: SDG 2 - Zero Hunger | F36: % | J36: 19 | L36: Data held | M36: MRE
B37: TR2(c) | E37: SDG 3 - Good health and well-being | F37: % | J37: 20 | L37: Data held | M37: MRE
B38: TR2(c) | E38: SDG 4 - Quality Education | F38: % | J38: 19 | L38: Data held | M38: MRE
B39: TR2(c) | E39: SDG 5 - Gender Equality | F39: % | J39: 18 | L39: Data held | M39: MRE
B40: TR2(c) | E40: SDG 6 - Clean water and sanitation | F40: % | J40: 17 | L40: Data held | M40: MRE
B41: TR2(c) | E41: SDG 7 - Affordable and clean energy | F41: % | J41: 22 | L41: Data held | M41: MRE
B42: TR2(c) | E42: SDG 8 - Decent work and economic growth | F42: % | J42: 22 | L42: Data held | M42: MRE
B43: TR2(c) | E43: SDG 9 - Industry, innovation and infrastructure | F43: % | J43: 23 | L43: Data held | M43: MRE
B44: TR2(c) | E44: SDG 10 - Reduced inequality | F44: % | J44: 20 | L44: Data held | M44: MRE
B45: TR2(c) | E45: SDG 11 - Sustainable cities and communities | F45: % | J45: 20 | L45: Data held | M45: MRE
B46: TR2(c) | E46: SDG 12 - Responsible consumption and production | F46: % | J46: 20 | L46: Data held | M46: MRE
... B104: TR2(c) | E104: SDG 17 - Partnerships | F104: # | J104: 0 | L104: Data held | M104: MRE
B105: TR3(b) | C105: Transformational Research | D105: Demonstrated examples of more sustainable research practices in laboratories, fieldwork, procurement, travel or infrastructure use | E105: Laboratories achieveng Green Lab Ceritifcation | F105: # | L105: No data yet | M105: MRE
B106: TR3(b) | E106: New Sustainable Activities | F106: # | L106: No data yet | M106: MRE
B107: TR3(b) | E107: Sustainable Fieldworks | F107: # | L107: No data yet | M107: MRE
B108: CL1(a) | C108: Climate Leadership | D108: Annual GHG Inventory demonstrateds carbon emission reductions, including maintaining procurement of 100% renewable electricities for all scope 2 sources | E108: Gross Total Greenhouse Gas Emissions | F108: tCO2e | H108: 241128 | I108: 220239 | J108: 170705 | L108: Data held | M108: ESG
B109: CL1(a) | E109: Direct Scope 1 emissions | F109: tCO2e | H109: 16665 | I109: 15567 | J109: 16484.01 | L109: Data held | M109: ESG
B110: CL1(a) | E110: Stationary energy (gaseous fuels) | F110: tCO2e | H110: 14192 | I110: 13662 | J110: 13800 | L110: Data held | M110: ESG
B111: CL1(a) | E111: Refrigerants | F111: tCO2e | H111: 1928 | I111: 1531 | J111: 2244 | L111: Data held | M111: ESG
B112: CL1(a) | E112: Transport (land and sea) | F112: tCO2e | H112: 390 | I112: 344 | J112: 432 | L112: Data held | M112: ESG
B113: CL1(a) | E113: Stationary energy (LPG) | F113: tCO2e | H113: 156 | I113: 30 | J113: 0.01 | L113: Data held | M113: ESG
B114: CL1(a) | E114: Electricity (Market-Based) | F114: tCO2e | H114: 0 | I114: 0 | J114: 0 | L114: Data held | M114: ESG
B115: CL1(a) | E115: Professional services | F115: tCO2e | H115: 0 | I115: 0 | J115: 0 | L115: Data held | M115: ESG
B116: CL1(a) | E116: Construction materials and services | F116: tCO2e | H116: 0 | I116: 0 | J116: 0 | L116: Data held | M116: ESG
B117: CL1(a) | E117: Transport (air travel) | F117: tCO2e | H117: 0 | I117: 0 | J117: 8 | L117: Data held | M117: ESG
B118: CL1(a) | E118: ICT services and equipment | F118: tCO2e | H118: 0 | I118: 0 | J118: 0 | L118: Data held | M118: ESG
B119: CL1(a) | E119: Products | F119: tCO2e | H119: 0 | I119: 0 | J119: 0 | L119: Data held | M119: ESG
B120: CL1(a) | E120: Food | F120: tCO2e | H120: 0 | I120: 0 | J120: 0 | L120: Data held | M120: ESG
... B156: CL1(a) | E156: Stationary energy (gaseous fuels) | F156: tCO2e | H156: 1102 | I156: 1061 | J156: 2315 | L156: Data held | M156: ESG
B157: CL1(a) | E157: Refrigerants | F157: tCO2e | J157: 80 | L157: Data held | M157: ESG
B158: CL1(a) | E158: Transport (land and sea) | F158: tCO2e | H158: 7394 | I158: 5564 | J158: 5461 | L158: Data held | M158: ESG
B159: CL1(a) | E159: Stationary energy (LPG) | F159: tCO2e | H159: 52 | I159: 10 | J159: 0 | L159: Data held | M159: ESG
B160: CL1(a) | E160: Electricity (Market-Based) | F160: tCO2e | H160: 3878 | I160: 3592 | J160: 4644 | L160: Data held | M160: ESG
B161: CL1(a) | E161: Professional services | F161: tCO2e | H161: 58053 | I161: 69377 | J161: 69347 | L161: Data held | M161: ESG
B162: CL1(a) | E162: Construction materials and services | F162: tCO2e | H162: 27169 | I162: 20601 | J162: 15830 | L162: Data held | M162: ESG
B163: CL1(a) | E163: Transport (air travel) | F163: tCO2e | H163: 33556 | I163: 22092 | J163: 20055 | L163: Data held | M163: ESG
B164: CL1(a) | E164: ICT services and equipment | F164: tCO2e | H164: 13849 | I164: 20458 | J164: 7239 | L164: Data held | M164: ESG
B165: CL1(a) | E165: Products | F165: tCO2e | H165: 12048 | I165: 11820 | J165: 8012 | L165: Data held | M165: ESG
B166: CL1(a) | E166: Food | F166: tCO2e | H166: 5769 | I166: 6203 | J166: 4055 | L166: Data held | M166: ESG
B167: CL1(a) | E167: Office equipment and supplies | F167: tCO2e | H167: 13961 | I167: 3893 | J167: 3536 | L167: Data held | M167: ESG
B168: CL1(a) | E168: Accommodation and facilities | F168: tCO2e | H168: 1649 | I168: 2412 | J168: 1552 | L168: Data held | M168: ESG
B169: CL1(a) | E169: Working from home | F169: tCO2e | H169: 3204 | I169: 2582 | J169: 2607 | L169: Data held | M169: ESG
... B178: CL1(a) | E178: Total Carbon offsets | F178: tCO2e | H178: 68852 | I178: 54782 | J178: 170705 | L178: Data held | M178: ESG
B179: CL1(a) | E179: Carbon offsets for scope 1 | F179: tCO2e | H179: N/A | I179: N/A | J179: 16485 | L179: Data held | M179: ESG
B180: CL1(a) | E180: Carbon offsets for scope 2 | F180: tCO2e | H180: N/A | I180: N/A | J180: 0 | L180: Data held | M180: ESG
B181: CL1(a) | E181: Carbon offsets for scope 3 | F181: tCO2e | H181: N/A | I181: N/A | J181: 154220 | L181: Data held | M181: ESG
B182: CL1(a) | E182: Net total emissions | F182: tCO2e | H182: 172276 | I182: 165457 | J182: 0 | L182: Data held | M182: ESG
B183: CL1(a) | E183: Total Electricity Usage | F183: MWh | H183: 115156 | I183: 117811 | J183: 119826 | L183: Data held | M183: ESG
B184: CL1(a) | E184: Total on-campus solar | F184: MWh | H184: 3439 | I184: 3795 | J184: 3879 | L184: Data held | M184: ESG
B185: CL1(a) | E185: Total grid (incl. affiliates) | F185: # | H185: 111717 | I185: 114016 | J185: 115947 | L185: Data held | M185: ESG
B186: CL1(b) | C186: Climate Leadership | D186: Development of Greenhouse Gas Intensity metrics | E186: Net emissions /m2 GFA | F186: tCO2e / m² | H186: 0.17 | I186: 0.16 | J186: 0 | L186: Data held | M186: ESG
B187: CL1(b) | E187: Net emissions /FTE | F187: tCO2e / FTE | H187: 16.39 | I187: 14.96 | J187: 0 | L187: Data held | M187: ESG
B188: CL1(b) | E188: Net emissions /EFTSL | F188: tCO2e / EFTSL | H188: 3.19 | I188: 2.86 | J188: 0 | L188: Data held | M188: ESG
B189: CL1(b) | E189: Net emissions /(FTE + EFTSL) | F189: tCO2e / (FTE + EFTSL) | H189: 2.67 | I189: 2.4 | J189: 0 | L189: Data held | M189: ESG
B190: CL1(b) | E190: Gross emissions /m2 GFA | F190: tCO2e / m² | H190: 0.23 | I190: 0.21 | J190: 0.16 | L190: Data held | M190: ESG
B191: CL1(b) | E191: Gross emissions /FTE | F191: tCO2e / FTE | H191: 23.13 | I191: 19.91 | J191: 15.3 | L191: Data held | M191: ESG
B192: CL1(b) | E192: Gross emissions /EFTSL | F192: tCO2e / EFTSL | H192: 4.51 | I192: 3.8 | J192: 2.94 | L192: Data held | M192: ESG
B193: CL1(b) | E193: Gross emissions /(FTE + EFTSL) | F193: tCO2e / (FTE + EFTSL) | H193: 3.77 | I193: 3.19 | J193: 2.46 | L193: Data held | M193: ESG
B194: CL2(a) | C194: Climate Leadership | D194: By 2028, develop and document institutional mapping of research and education activities that are designed to contribute to global decarbonisation | E194: Number of relevant research projects/programs mapped | F194: # | L194: No data yet | M194: SST
B195: CL2(a) | E195: Number of relevant subjects mapped | F195: # | L195: No data yet | M195: SST
B196: CL2(b) | C196: Climate Leadership | D196: Prioritised pipeline of decarbonisation focused research and education opportunities aligned with University emissions reduction priorities from 2028 | E196: Number of pipelined projects or research transitioned from opportunity to active | F196: # | L196: No data yet | M196: SST
B197: CL2(c) | C197: Climate Leadership | D197: Ongoing communications that evidence the university's climate action, research and learning to inform policy, sector and community decarbonisation efforts | E197: Published documents, policy brief, and public engagement events | F197: # | L197: No data yet | M197: SST
B198: CL2(c) | E198: Views of communication material | F198: # | L198: No data yet | M198: SST
B199: CL3(a) | C199: Climate Leadership | D199: Maturity assessment of the University's preparedness for climate-related impacts and capability to respond | E199: Average Total Maturity Score
B200: CL3(a) | E200: Maturitu Score - Governance and strategy | L200: No data yet | M200: CI&S
B201: CL3(a) | E201: Maturity Score - Health and safety | L201: No data yet | M201: CI&S
B202: CL3(a) | E202: Maturity Score - Business continuity | L202: No data yet | M202: CI&S
B203: CL3(a) | E203: Maturity Score - Emergency management and critical incidence management | L203: No data yet | M203: CI&S
B204: CL3(a) | E204: Maturity Score - Estate and buildings | L204: No data yet | M204: CI&S
...

Sheet 3. Stakeholder map
A1: ↑ | B1: End-2026 target status assessment and reporting
B2: 3. Stakeholder map (SR25 → SR26)
B4: SR26 unit | C4: SR26 full name | D4: SR25 equivalent (2025 master) | E4: Section / team | F4: Key contact | G4: Status / notes
B5: Faculty | C5: Faculty of Architecture, Building and Planning | D5: Faculties tab – ABP | E5: Associate Dean Sustainability / faculty sustainability lead | F5: TBC | G5: Pilot faculty
B6: Faculty | C6: Faculty of Arts | D6: Faculties tab – ARTS | E6: Associate Dean Sustainability / faculty sustainability lead | F6: TBC | G6: Pilot faculty
B7: Faculty | C7: Faculty of Business and Economics | D7: Faculties tab – FBE | E7: Associate Dean Sustainability / faculty sustainability lead | F7: TBC | G7: Pilot faculty
B8: Faculty | C8: Faculty of Science | D8: Faculties tab – SCI | E8: Associate Dean Sustainability / faculty sustainability lead | F8: TBC | G8: Pilot faculty
B9: CI&S | C9: Commercial, Infrastructure & Sustainability (CI&S) | D9: Corporate Development (CD Development & Estate Planning teams; CD Sustainability Strategy) | E9: CI&S – Estate Planning & Development (TBC: confirm with Gerard) | F9: TBC
B10: CI&S | C10: Commercial, Infrastructure & Sustainability (CI&S) | D10: Corporate Development (CD Development & Estate Planning teams; CD Sustainability Strategy) | E10: CI&S – Sustainability Strategy (incl. CLLAP) | F10: TBC
B11: CFOG | C11: Chief Finance Officer Group (CFOG) | D11: CFOG (Procurement; Accounting; Treasury & Investments; Enterprise Portfolio & Investments) | E11: CFOG – Procurement | F11: TBC
B12: CFOG | C12: Chief Finance Officer Group (CFOG) | D12: CFOG (Procurement; Accounting; Treasury & Investments; Enterprise Portfolio & Investments) | E12: CFOG – Treasury & Investments | F12: TBC
B13: ESG | C13: Enterprise Services Group (ESG) | D13: Business Services – Sustainability Delivery (nature & biodiversity, waste & circular economy, part of quant. climate leadership) | E13: ESG – Campus Operations & Sustainability Delivery | F13: TBC
B14: CIOG | C14: Chief Information Officer Group (CIOG) | D14: Business Services (AI – not requested in SR25) | E14: CIOG – Responsible AI & digital | F14: TBC
B15: MRE | C15: Melbourne Research and Enterprise (MRE) | D15: Chancellery Research and Enterprise | E15: MRE – Research (incl. MBI – TBC) | F15: TBC
B16: AC&M | C16: Advancement, Communication and Marketing (AC&M) | D16: Chancellery – Advancement, Communications & Marketing | E16: AC&M – Advancement, Communication and Marketing | F16: TBC
B17: GCE | C17: Global, Culture and Engagement (GCE) | D17: Chancellery – Global, Culture and Engagement | E17: GCE – Global, Culture and Engagement | F17: TBC
B18: Education | C18: Chancellery Education | D18: Chancellery – Chancellery Education | E18: Education – Chancellery Education | F18: TBC
B19: SaSS | C19: Student and Scholarly Services (SaSS) | D19: Chancellery – Student and scholarly services | E19: SaSS – Student and Scholarly Services | F19: TBC
B20: Indigenous | C20: Chancellery Indigenous | D20: Chancellery – Chancellery Indigenous | E20: Indigenous – Chancellery Indigenous | F20: TBC
B21: L&R | C21: Legal and Risk | D21: Legal and Risk | E21: Legal & Risk – Risk & resilience | F21: TBC
B22: TBC | C22: CGOP / CDEP / CDSS | D22: Not in SR25 master | E22: — | F22: TBC | G22: Structure changes TBC – confirm before requests are issued.
B25: Who is responsible for each indicator: see '3b. RASCI matrix'.

Sheet 3b. RASCI matrix
B1: Sustainability 2030 – SR26 reporting roles (RASCI)
B2: Who is Accountable / Responsible / Support / Consulted / Informed for reporting each Sustainability 2030 indicator in SR26. Green columns are consolidated portfolios (click [+]/[–] above to show or hide their areas). Codes are pre-filled from the requests issued; edit with the dropdown. Accountable owners (A) are TBC – to confirm with the Director, Sustainability.
H3: SST contact (SR25 – confirm) >> | I3: Director | J3: Gerard | K3: Rose | L3: Katie | M3: Katie | N3: Director | O3: Gerard and Davina | P3: Director | Q3: Chris | R3: Chris | S3: All | T3: TBC | U3: Gerard | V3: Director | W3: Director | X3: Rose | Y3: Gerard | Z3: Katie | AA3: Rose | AB3: Gerard | AC3: All
H4: Portfolio / Faculty >> | I4: Faculty (consolidated) | J4: Faculty | K4: Faculty | L4: Faculty | M4: Faculty | N4: COO portfolio (consolidated) | O4: COO portfolio | P4: COO portfolio | Q4: COO portfolio | R4: COO portfolio | S4: COO portfolio | T4: COO portfolio | U4: COO portfolio | V4: Chancellery (consolidated) | W4: Chancellery | X4: Chancellery | Y4: Chancellery | Z4: Chancellery | AA4: Chancellery | AB4: Chancellery | AC4: Sustainability Strategy
I5: Areas Accountable and/or Responsible for SR26 reporting (green = consolidated portfolio, white = individual area)
A6: Number | B6: Category | C6: Domain | D6: Priority area | E6: Target / indicator | F6: Type | G6: Related SR25 ref | H6: Activity area >> | I6: Faculties – pilot (all) | J6: ABP – Architecture, Building and Planning | K6: ARTS – Arts | L6: FBE – Business and Economics | M6: SCI – Science | N6: COO portfolio (all) | O6: CI&S – Estate Planning & Development | P6: CI&S – Sustainability Strategy | Q6: CFOG – Procurement | R6: CFOG – Treasury & Investments | S6: ESG – Campus Operations & Sustainability Delivery | T6: CIOG – Responsible AI & digital | U6: Legal & Risk – Risk & resilience | V6: Chancellery (all) | W6: MRE – Research | X6: AC&M – Advancement, Communication and Marketing | Y6: GCE – Global, Culture and Engagement | Z6: Education – Chancellery Education | AA6: SaSS – Student and Scholarly Services | AB6: Indigenous – Chancellery Indigenous | AC6: SST (compiles / Databook)
A7: D1 | B7: Domain | E7: Education and research
A8: EE | B8: Priority | E8: Exceptional education
A9: EE1 | B9: Target | C9: Education and research | D9: Exceptional education | E9: Provide our students with learning experiences that help them build the knowledge, skills and relationships to lead change for sustainable societies.
A10: EE1(a) | B10: Indicator | C10: Education and research | D10: Exceptional education | E10: Evidence of innovative approaches to sustainability teaching and learning | F10: Qualitative | G10: 4a(ii) | I10: A and R | J10: R | K10: R | L10: R | M10: R | N10: A and R | P10: R | V10: A and R | Z10: R | AC10: S
A11: EE1(b) | B11: Indicator | C11: Education and research | D11: Exceptional education | E11: Pilots of possible approaches for understanding and developing students’ sustainability self-efficacy | F11: Qualitative | I11: A and R | J11: R | K11: R | L11: R | M11: R | N11: A and R | P11: R | V11: A and R | Z11: R | AC11: S
A12: EE1(c) | B12: Indicator | C12: Education and research | D12: Exceptional education | E12: Evidence of sustainability focused experiential and co curricular learning (eg Wattle Fellowship; Melbourne Plus) | F12: Mixed | N12: A and R | P12: R | V12: A and R | AA12: R | AC12: S
A13: EE1(d) | B13: Indicator | C13: Education and research | D13: Exceptional education | E13: Alumni profiles demonstrating how graduates contribute to sustainability through their careers or communities. | F13: Mixed | G13: 4b(i) | V13: A and R | AA13: R | AC13: S
A14: TR | B14: Priority | E14: Transformational research
A15: TR1 | B15: Target | C15: Education and research | D15: Transformational research | E15: Utilise the expertise of the University’s researchers through mutually beneficial partnerships to help address the University’s operational sustainability challenges.
A16: TR1(a) | B16: Indicator | C16: Education and research | D16: Transformational research | E16: Expert-reviewed evidence of researchers contributing to operational sustainability priorities through partnerships, advisory input, living labs, applied projects or decision-support | F16: Qualitative | G16: 2a | I16: A and R | J16: R | K16: R | L16: R | M16: R | N16: A and R | P16: R | AC16: S
A17: TR1(b) | B17: Indicator | C17: Education and research | D17: Transformational research | E17: Evidence of institutional pathways that enable ongoing collaboration between academic and professional staff | F17: Qualitative | V17: A and R | W17: R | AC17: S
A18: TR1(c) | B18: Indicator | C18: Education and research | D18: Transformational research | E18: Expert assessment of the quality, relevance and continuity of these collaborations | F18: Qualitative | V18: A and R | W18: R | AC18: S
A19: TR1(d) | B19: Indicator | C19: Education and research | D19: Transformational research | E19: Periodic feedback from participants on the effectiveness and mutual benefit of collaboration mechanisms. | F19: Qualitative | V19: A and R | W19: R | AC19: S
A20: TR2 | B20: Target | C20: Education and research | D20: Transformational research | E20: Deliver high-quality research and partnerships that contribute to sustainability outcomes and demonstrable societal benefit.
A21: TR2(a) | B21: Indicator | C21: Education and research | D21: Transformational research | E21: Evidence of sustainability-related research impact across diverse pathways, could include policy, industry, community, practice, cultural and institutional outcomes | F21: Qualitative | G21: 5b(i) | I21: A and R | J21: R | K21: R | L21: R | M21: R | V21: A and R | X21: R | AC21: S
A22: TR2(b) | B22: Indicator | C22: Education and research | D22: Transformational research | E22: Documented progress of relevant strategic initiatives, including Impact Accelerators | F22: Quantitative | V22: A and R | W22: R (quant) | AC22: S
A23: TR2(c) | B23: Indicator | C23: Education and research | D23: Transformational research | E23: Expert-reviewed summary of sustainability-related research outputs, outcomes and influence using available institutional evidence sources | F23: Mixed | V23: A and R | W23: R | AC23: S
A24: TR2(d) | B24: Indicator | C24: Education and research | D24: Transformational research | E24: Case-based evidence demonstrating how research has contributed to meaningful sustainability outcomes. | F24: Qualitative | G24: 5b(i) | I24: A and R | J24: R | K24: R | L24: R | M24: R | N24: A and R | P24: R | AC24: S
A25: TR3 | B25: Target | C25: Education and research | D25: Transformational research | E25: Embed sustainability within research systems, processes, capability and culture, so research is conducted responsibly, efficiently and with reduced environmental impact.
A26: TR3(a) | B26: Indicator | C26: Education and research | D26: Transformational research | E26: Evidence that sustainability considerations are integrated into relevant research systems, planning processes, guidance, training, induction or support services | F26: Qualitative | G26: 5c(ii) | V26: A and R | W26: R | AC26: S
A27: TR3(b) | B27: Indicator | C27: Education and research | D27: Transformational research | E27: Demonstrated examples of more sustainable research practices in laboratories, fieldwork, procurement, travel or infrastructure use | F27: Mixed | G27: 5c(ii) | I27: A and R | J27: R | K27: R | L27: R | M27: R | N27: A and R | P27: R | Q27: R | V27: A and R | W27: R (quant) | AC27: S
A28: TR3(c) | B28: Indicator | C28: Education and research | D28: Transformational research | E28: Evidence of progress in sustainability-related research culture, capability and awareness, informed by periodic staff and graduate researcher surveys | F28: Qualitative | V28: A and R | W28: R | AC28: S
A29: TR3(d) | B29: Indicator | C29: Education and research | D29: Transformational research | E29: Expert assessment of progress in embedding sustainable research practices across the institution. | F29: Qualitative | V29: A and R | W29: R | AC29: S
A30: D2 | B30: Domain | E30: Sustainability leadership
A31: CL | B31: Priority | E31: Climate leadership
A32: CL1 | B32: Target | C32: Sustainability leadership | D32: Climate leadership | E32: Achieve net zero emissions by 2050: Interim target Reduce emissions by 20% across all emissions scopes by CY2030 on the CY2023 re-baseline including: • Scopes 1 and 2: 66% reduction • Scope 3: 12% reduction. Long-term target Reduce emissions by 90% across all emissions scopes by CY2050 on the CY2023 re-baseline and invest in carbon removal credits for residual emissions from hard-to-abate sources (up to 10%).
A33: CL1(a) | B33: Indicator | C33: Sustainability leadership | D33: Climate leadership | E33: Annual Greenhouse Gas Inventory (including emissions scopes 1, 2 and 3) demonstrates carbon emission reductions, including maintaining procurement of 100% renewable electricity for all scope 2 sources[1] | F33: Quantitative | N33: A and R | S33: R (quant) | AC33: S
A34: CL1(b) | B34: Indicator | C34: Sustainability leadership | D34: Climate leadership | E34: Development of Greenhouse Gas intensity metrics | F34: Quantitative | N34: A and R | S34: R (quant) | AC34: S
A35: CL1(c) | B35: Indicator | C35: Sustainability leadership | D35: Climate leadership | E35: Review of Climate Leadership targets by 2030.[2] | F35: Mixed | N35: A and R | P35: R | AC35: S
A36: CL2 | B36: Target | C36: Sustainability leadership | D36: Climate leadership | E36: Develop understanding of our research and education programs that contribute to accelerating global decarbonisation and our own climate transition.
A37: CL2(a) | B37: Indicator | C37: Sustainability leadership | D37: Climate leadership | E37: By 2028, develop and document institutional mapping of research and education activities that are designed to contribute to global decarbonisation | F37: Mixed | V37: A and R | X37: R | AC37: R (compile)
A38: CL2(b) | B38: Indicator | C38: Sustainability leadership | D38: Climate leadership | E38: Prioritised pipeline of decarbonisation focused research and education opportunities aligned with University emissions reduction priorities from 2028 | F38: Quantitative | AC38: R (compile)
A39: CL2(c) | B39: Indicator | C39: Sustainability leadership | D39: Climate leadership | E39: Ongoing communications that evidence the University’s climate action, research and learning to inform policy, sector and community decarbonisation efforts. | F39: Mixed | V39: A and R | X39: R | AC39: R (compile)
A40: CL3 | B40: Target | C40: Sustainability leadership | D40: Climate leadership | E40: Reach and maintain high levels of climate-change resilience maturity
A41: CL3(a) | B41: Indicator | C41: Sustainability leadership | D41: Climate leadership | E41: Maturity assessment of the University’s preparedness for climate-related impacts and capability to respond, assessed across relevant organisational functions: o Governance and strategy o Health and safety o Business continuity o Emergency management and critical incidence management o Estate and buildings o Water management o Financial planning and reporting. | F41: Mixed | N41: A and R | O41: R | U41: R | AC41: S
A42: NB | B42: Priority | E42: Nature and biodiversity
A43: NB1 | B43: Target | C43: Sustainability leadership | D43: Nature and biodiversity | E43: Achieve an increase of biodiversity relative to defined baseline years for each campus.
A44: NB1(a) | B44: Indicator | C44: Sustainability leadership | D44: Nature and biodiversity | E44: Monitoring of biodiversity metrics from the Biodiversity Baseline Data Project | F44: Quantitative | N44: A and R | S44: R (quant) | AC44: S
A45: NB1(b) | B45: Indicator | C45: Sustainability leadership | D45: Nature and biodiversity | E45: Size, health and diversity of remnant vegetation at the Dookie and Creswick campuses | F45: Mixed | N45: A and R | S45: R | AC45: S
A46: NB1(c) | B46: Indicator | C46: Sustainability leadership | D46: Nature and biodiversity | E46: Defined quality measurement framework | F46: Mixed | N46: A and R | S46: R | AC46: S
A47: NB1(d) | B47: Indicator | C47: Sustainability leadership | D47: Nature and biodiversity | E47: Defined and quantified campus connectivity | F47: Mixed | N47: A and R | S47: R | AC47: S
A48: NB2 | B48: Target | C48: Sustainability leadership | D48: Nature and biodiversity | E48: Improve our understanding of our supply chain impacts on nature.
A49: NB2(a) | B49: Indicator | C49: Sustainability leadership | D49: Nature and biodiversity | E49: Documented baseline nature footprint analysis | F49: Mixed | V49: A and R | W49: R | AC49: S
A50: NB2(b) | B50: Indicator | C50: Sustainability leadership | D50: Nature and biodiversity | E50: Evidence of established framework to monitor and track supply-chain nature impacts over time | F50: Qualitative | N50: A and R | S50: R | AC50: S
A51: NB2(c) | B51: Indicator | C51: Sustainability leadership | D51: Nature and biodiversity | E51: Evidence of prioritised high risk procurement categories or suppliers for nature impact management | F51: Qualitative | N51: A and R | Q51: R | S51: R | AC51: S
A52: AI | B52: Priority | E52: Responsible AI
A53: AI1 | B53: Target | C53: Sustainability leadership | D53: Responsible AI | E53: Improve understanding of our sustainability-related risks and opportunities of AI technologies by 2028.
A54: AI1(a) | B54: Indicator | C54: Sustainability leadership | D54: Responsible AI | E54: Established measurement of estimated operational impacts and opportunities (eg operational impacts could include energy, water, emissions and intensity measures) | F54: Mixed | N54: A and R | P54: R | T54: R | AC54: S
A55: AI1(b) | B55: Indicator | C55: Sustainability leadership | D55: Responsible AI | E55: Case studies of sustainability and AI-related education, research and collaboration activities. | F55: Qualitative | N55: A and R | P55: R | T55: R | AC55: S
A56: D3 | B56: Domain | E56: Resilient University
A57: EI | B57: Priority | E57: Estate and infrastructure
A58: EI1 | B58: Target | C58: Resilient University | D58: Estate and infrastructure | E58: Integrate environmental sustainability in the way that the University achieves strategic and operational objectives for our estate and infrastructure.
A59: EI1(a) | B59: Indicator | C59: Resilient University | D59: Estate and infrastructure | E59: Evidence of increased maturity of estate and infrastructure planning, development and operations to support the other priority areas in Sustainability 2030 | F59: Mixed | N59: A and R | O59: R | AC59: S
A60: EI1(b) | B60: Indicator | C60: Resilient University | D60: Estate and infrastructure | E60: Estimated sustainability impacts of the University’s estate and infrastructure capital plan to inform progress towards emissions reduction targets and other priority areas (to the extent enabled by available information) | F60: Mixed | N60: A and R | O60: R | AC60: S
A61: EI1(c) | B61: Indicator | C61: Resilient University | D61: Estate and infrastructure | E61: Reporting on relevant activities and impacts for the University’s major estate and infrastructure projects and programs aligned with the other priority areas in Sustainability 2030 | F61: Mixed | N61: A and R | O61: R | AC61: S
A62: EI1(d) | B62: Indicator | C62: Resilient University | D62: Estate and infrastructure | E62: Evidence of understanding and integration of Indigenous approaches to sustainability in estate planning and development programs and projects. | F62: Qualitative | N62: A and R | O62: R | AC62: S
A63: CE | B63: Priority | E63: Circular economy
A64: CE1 | B64: Target | C64: Resilient University | D64: Circular economy | E64: Reduce waste to landfill by 10% by CY2030 on the CY2025 baseline.
A65: CE1(a) | B65: Indicator | C65: Resilient University | D65: Circular economy | E65: Comparison of year-to-year tonnes of waste (absolute). | F65: Quantitative | N65: A and R | S65: R (quant) | AC65: S
A66: CE2 | B66: Target | C66: Resilient University | D66: Circular economy | E66: Increase diversion of recyclable materials from landfill by 10% by CY2030 on the CY2025 baseline.
A67: CE2(a) | B67: Indicator | C67: Resilient University | D67: Circular economy | E67: Comparison of year-to-year tonnes of recyclables (absolute). | F67: Quantitative | N67: A and R | S67: R (quant) | AC67: S
A68: RP | B68: Priority | E68: Responsible procurement
A69: RP1 | B69: Target | C69: Resilient University | D69: Responsible procurement | E69: Strengthen our ethical and sustainable procurement approach.
A70: RP1(a) | B70: Indicator | C70: Resilient University | D70: Responsible procurement | E70: Case studies of maturity improvement related to responsible procurement process and systems. | F70: Mixed | N70: A and R | Q70: R | AC70: S
A71: RP2 | B71: Target | C71: Resilient University | D71: Responsible procurement | E71: Increase our Indigenous and social spend, reaching 3% Indigenous and 1% social spend of addressable procurement by 2030.
A72: RP2(a) | B72: Indicator | C72: Resilient University | D72: Responsible procurement | E72: Percentage of Indigenous spend of total addressable procurement spend | F72: Quantitative | N72: A and R | Q72: R (quant) | AC72: S
A73: RP2(b) | B73: Indicator | C73: Resilient University | D73: Responsible procurement | E73: Percentage of social spend of total addressable procurement spend. | F73: Quantitative | N73: A and R | Q73: R (quant) | AC73: S
A74: MS | B74: Priority | E74: Modern slavery and human rights
A75: MS1 | B75: Target | C75: Resilient University | D75: Modern slavery and human rights | E75: Manage our approach to modern slavery and human rights-related risks and opportunities.
A76: MS1(a) | B76: Indicator | C76: Resilient University | D76: Modern slavery and human rights | E76: Annual progress reporting via the Modern Slavery Statement | F76: Qualitative | N76: A and R | P76: R | Q76: R | AC76: S
A77: RI | B77: Priority | E77: Responsible investments
A78: RI1 | B78: Target | C78: Resilient University | D78: Responsible investments | E78: Achieve net zero financed emissions for the University’s investment portfolio by 2050.
A79: RI1(a) | B79: Indicator | C79: Resilient University | D79: Responsible investments | E79: Annual monitoring and reporting on the investment portfolio’s net zero transition progress, including tracking the percentage of assets under management (AUM) managed by investment managers aligned with (or committed to) net zero by 2050 | F79: Quantitative | N79: A and R | R79: R (quant) | AC79: S
A80: RI1(b) | B80: Indicator | C80: Resilient University | D80: Responsible investments | E80: Continuous improvement of the reporting of the University’s sustainability-related investment profile metrics, could include investment in climate mitigation and transition solutions, and compliance with related obligations (eg UNPRI). | F80: Mixed | N80: A and R | P80: R | R80: R | AC80: S
A81: D4 | B81: Domain | E81: Enablers
A82: EN | B82: Priority | E82: Enablers
A83: EN1 | B83: Target | C83: Enablers | D83: Enablers | E83: Enablers
A84: EN1(a) | B84: Indicator | C84: Enablers | D84: Enablers | E84: Evidence of sustainability outcomes informed by Indigenous knowledges | F84: Qualitative | G84: 6a | I84: A and R | J84: R | K84: R | L84: R | M84: R | V84: A and R | Y84: R | AB84: R | AC84: S
A85: EN1(b) | B85: Indicator | C85: Enablers | D85: Enablers | E85: Living laboratories enabling applied learning, research and operational sustainability outcomes | F85: Mixed | G85: 2a | I85: A and R | J85: R | K85: R | L85: R | M85: R | N85: A and R | O85: R (quant) | P85: R | AC85: S
A86: EN1(c) | B86: Indicator | C86: Enablers | D86: Enablers | E86: Coordinated internal engagement and external partnerships contributing to delivery of sustainability outcomes across priority areas. | F86: Qualitative | G86: 3a(ii) | I86: A and R | J86: R | K86: R | L86: R | M86: R | N86: A and R | P86: R | Q86: R | S86: R | T86: R | V86: A and R | X86: R | Y86: R | Z86: R | AC86: S
A87: EN1(d) | B87: Indicator | C87: Enablers | D87: Enablers | E87: Sustainability objectives integrated into governance and decision‑making processes, supported by transparent reporting. | F87: Qualitative | N87: A and R | P87: R | Q87: R | S87: R | T87: R | AC87: S
E89: Summary
E90: Area >> | I90: =I6 | J90: =J6 | K90: =K6 | L90: =L6 | M90: =M6 | N90: =N6 | O90: =O6 | P90: =P6 | ... AC90: =AC6
E91: Accountable | F91: A | I91: =COUNTIF(I10:I87,$F91) | J91: =COUNTIF(J10:J87,$F91) | K91: =COUNTIF(K10:K87,$F91) | L91: =COUNTIF(L10:L87,$F91) | M91: =COUNTIF(M10:M87,$F91) | N91: =COUNTIF(N10:N87,$F91) | O91: =COUNTIF(O10:O87,$F91) | P91: =COUNTIF(P10:P87,$F91) | ... AC91: =COUNTIF(AC10:AC87,$F91)
E92: Accountable and Responsible | F92: A and R | I92: =COUNTIF(I10:I87,$F92) | J92: =COUNTIF(J10:J87,$F92) | K92: =COUNTIF(K10:K87,$F92) | L92: =COUNTIF(L10:L87,$F92) | M92: =COUNTIF(M10:M87,$F92) | N92: =COUNTIF(N10:N87,$F92) | O92: =COUNTIF(O10:O87,$F92) | P92: =COUNTIF(P10:P87,$F92) | ... AC92: =COUNTIF(AC10:AC87,$F92)
E93: Responsible – narrative request | F93: R | I93: =COUNTIF(I10:I87,$F93) | J93: =COUNTIF(J10:J87,$F93) | K93: =COUNTIF(K10:K87,$F93) | L93: =COUNTIF(L10:L87,$F93) | M93: =COUNTIF(M10:M87,$F93) | N93: =COUNTIF(N10:N87,$F93) | O93: =COUNTIF(O10:O87,$F93) | P93: =COUNTIF(P10:P87,$F93) | ... AC93: =COUNTIF(AC10:AC87,$F93)
E94: Responsible – figures for the Databook (Tab 4) | F94: R (quant) | I94: =COUNTIF(I10:I87,$F94) | J94: =COUNTIF(J10:J87,$F94) | K94: =COUNTIF(K10:K87,$F94) | L94: =COUNTIF(L10:L87,$F94) | M94: =COUNTIF(M10:M87,$F94) | N94: =COUNTIF(N10:N87,$F94) | O94: =COUNTIF(O10:O87,$F94) | P94: =COUNTIF(P10:P87,$F94) | ... AC94: =COUNTIF(AC10:AC87,$F94)
E95: SST compiles from other responses / no request | F95: R (compile) | I95: =COUNTIF(I10:I87,$F95) | J95: =COUNTIF(J10:J87,$F95) | K95: =COUNTIF(K10:K87,$F95) | L95: =COUNTIF(L10:L87,$F95) | M95: =COUNTIF(M10:M87,$F95) | N95: =COUNTIF(N10:N87,$F95) | O95: =COUNTIF(O10:O87,$F95) | P95: =COUNTIF(P10:P87,$F95) | ... AC95: =COUNTIF(AC10:AC87,$F95)
E96: Support | F96: S | I96: =COUNTIF(I10:I87,$F96) | J96: =COUNTIF(J10:J87,$F96) | K96: =COUNTIF(K10:K87,$F96) | L96: =COUNTIF(L10:L87,$F96) | M96: =COUNTIF(M10:M87,$F96) | N96: =COUNTIF(N10:N87,$F96) | O96: =COUNTIF(O10:O87,$F96) | P96: =COUNTIF(P10:P87,$F96) | ... AC96: =COUNTIF(AC10:AC87,$F96)
E97: Consulted | F97: C | I97: =COUNTIF(I10:I87,$F97) | J97: =COUNTIF(J10:J87,$F97) | K97: =COUNTIF(K10:K87,$F97) | L97: =COUNTIF(L10:L87,$F97) | M97: =COUNTIF(M10:M87,$F97) | N97: =COUNTIF(N10:N87,$F97) | O97: =COUNTIF(O10:O87,$F97) | P97: =COUNTIF(P10:P87,$F97) | ... AC97: =COUNTIF(AC10:AC87,$F97)
E98: Informed | F98: I | I98: =COUNTIF(I10:I87,$F98) | J98: =COUNTIF(J10:J87,$F98) | K98: =COUNTIF(K10:K87,$F98) | L98: =COUNTIF(L10:L87,$F98) | M98: =COUNTIF(M10:M87,$F98) | N98: =COUNTIF(N10:N87,$F98) | O98: =COUNTIF(O10:O87,$F98) | P98: =COUNTIF(P10:P87,$F98) | ... AC98: =COUNTIF(AC10:AC87,$F98)
E99: Total A | I99: =I91+I92 | J99: =J91+J92 | K99: =K91+K92 | L99: =L91+L92 | M99: =M91+M92 | N99: =N91+N92 | O99: =O91+O92 | P99: =P91+P92 | ... AC99: =AC91+AC92
E100: Total R (all types) | I100: =I92+I93+I94+I95 | J100: =J92+J93+J94+J95 | K100: =K92+K93+K94+K95 | L100: =L92+L93+L94+L95 | M100: =M92+M93+M94+M95 | N100: =N92+N93+N94+N95 | O100: =O92+O93+O94+O95 | P100: =P92+P93+P94+P95 | ... AC100: =AC92+AC93+AC94+AC95
E101: Total indicators involved | I101: =SUM(I91:I98) | J101: =SUM(J91:J98) | K101: =SUM(K91:K98) | L101: =SUM(L91:L98) | M101: =SUM(M91:M98) | N101: =SUM(N91:N98) | O101: =SUM(O91:O98) | P101: =SUM(P91:P98) | ... AC101: =SUM(AC91:AC98)

Sheet 3c. RASCI triangulation
A1: ↑ | B1: End-2026 target status assessment and reporting
B2: 3c. RASCI triangulation (SR25 → SR26)
B3: Cross-check of the SR26 RASCI (3b) against the SR25 RASCI. Each SR26 indicator is mapped to its equivalent SR25 target(s) (judgement – see column D); SR25 areas are translated to the SR26 structure. 'SR25 only' flags an area that held a responsibility in SR25 but has no SR26 role – check whether it should be asked, consulted or informed. Non-pilot faculties are excluded from gaps (pilot only). SR26 codes are not changed by this tab.
B5: Ref | C5: Indicator | D5: Equivalent SR25 target(s) | E5: SR25 responsibilities (translated to SR26 areas) | F5: SR26 responsibilities (3b) | G5: In both | H5: SR25 only – check | I5: New in SR26 | J5: Suggested action | K5: Decision / notes
B6: EE1(a) | C6: Evidence of innovative approaches to sustainability teaching and learning | D6: 4a – Sustainability is integrated into curriculum to an extent that conscie | E6: ABP – Architecture, Building and Planning: A and R ARTS – Arts: A and R Education – Chancellery Education: A and R FBE – Business and Economics: A and R ⚠ Academic Board: Support SCI – Science: A and R SaSS – Student and Scholarly Services: Support | F6: ABP – Architecture, Building and Planning: R ARTS – Arts: R CI&S – Sustainability Strategy: R Education – Chancellery Education: R FBE – Business and Economics: R SCI – Science: R | G6: ABP – Architecture, Building and Planning ARTS – Arts Education – Chancellery Education FBE – Business and Economics SCI – Science | I6: CI&S – Sustainability Strategy | J6: Consistent with SR25. New areas added in SR26.
B7: EE1(b) | C7: Pilots of possible approaches for understanding and developing students’ sustainability self-efficacy | D7: 4b – Graduates have increased capabilities to shape, lead and succeed in th | E7: ABP – Architecture, Building and Planning: A and R ARTS – Arts: A and R Education – Chancellery Education: A and R FBE – Business and Economics: A and R SCI – Science: A and R | F7: ABP – Architecture, Building and Planning: R ARTS – Arts: R CI&S – Sustainability Strategy: R Education – Chancellery Education: R FBE – Business and Economics: R SCI – Science: R | G7: ABP – Architecture, Building and Planning ARTS – Arts Education – Chancellery Education FBE – Business and Economics SCI – Science | I7: CI&S – Sustainability Strategy | J7: Consistent with SR25. New areas added in SR26.
B8: EE1(c) | C8: Evidence of sustainability focused experiential and co curricular learning (eg Wattle Fellowship; Melbourne Plus) | D8: 3c – The University offers a suite of student-centered, formal and non-form | E8: ABP – Architecture, Building and Planning: A and R ARTS – Arts: A and R ESG – Campus Operations & Sustainability Delivery: R FBE – Business and Economics: A and R SCI – Science: A and R SaSS – Student and Scholarly Services: R | F8: CI&S – Sustainability Strategy: R SaSS – Student and Scholarly Services: R | G8: SaSS – Student and Scholarly Services | H8: ABP – Architecture, Building and Planning ARTS – Arts ESG – Campus Operations & Sustainability Delivery FBE – Business and Economics SCI – Science | I8: CI&S – Sustainability Strategy | J8: Team decision (v0.7): for faculties, covered by the merged EE1(a) question.
B9: EE1(d) | C9: Alumni profiles demonstrating how graduates contribute to sustainability through their careers or communities. | D9: 4b – Graduates have increased capabilities to shape, lead and succeed in th 3e – The University has increased its engagement with alumni regarding sust | E9: ABP – Architecture, Building and Planning: A and R AC&M – Advancement, Communication and Marketing: A and R ARTS – Arts: A and R Education – Chancellery Education: A and R FBE – Business and Economics: A and R SCI – Science: A and R | F9: SaSS – Student and Scholarly Services: R | H9: ABP – Architecture, Building and Planning AC&M – Advancement, Communication and Marketing ARTS – Arts Education – Chancellery Education FBE – Business and Economics SCI – Science | I9: SaSS – Student and Scholarly Services | J9: Team decision (v0.7): asked of SaSS only.
B10: TR1(a) | C10: Expert-reviewed evidence of researchers contributing to operational sustainability priorities through partnerships, advisory input, living labs, applied projects or decision-support | D10: 5a – Sustainability research is integrated with campus operations and plann 2a – The University has curated living labs covering the priority areas of | E10: ABP – Architecture, Building and Planning: R ARTS – Arts: R CFOG – Procurement: R CI&S – Sustainability Strategy: A ESG – Campus Operations & Sustainability Delivery: R FBE – Business and Economics: R MRE – Research: R ⚠ CFOG Finance: R ⚠ RIC: Support SCI – Science: R | F10: ABP – Architecture, Building and Planning: R ARTS – Arts: R CI&S – Sustainability Strategy: R FBE – Business and Economics: R SCI – Science: R | G10: ABP – Architecture, Building and Planning ARTS – Arts CI&S – Sustainability Strategy FBE – Business and Economics SCI – Science | H10: CFOG – Procurement ESG – Campus Operations & Sustainability Delivery MRE – Research Not in SR26: CFOG Finance | J10: Check why CFOG, ESG, MRE is not asked (was responsible in SR25); Consider request or 'C/I' for CFOG Finance.
B11: TR1(b) | C11: Evidence of institutional pathways that enable ongoing collaboration between academic and professional staff | D11: 5a – Sustainability research is integrated with campus operations and plann | E11: ABP – Architecture, Building and Planning: R ARTS – Arts: R CFOG – Procurement: R CI&S – Sustainability Strategy: A ESG – Campus Operations & Sustainability Delivery: R FBE – Business and Economics: R MRE – Research: R ⚠ CFOG Finance: R ⚠ RIC: Support SCI – Science: R | F11: MRE – Research: R | G11: MRE – Research | H11: ABP – Architecture, Building and Planning ARTS – Arts CFOG – Procurement CI&S – Sustainability Strategy ESG – Campus Operations & Sustainability Delivery FBE – Business and Economics Not in SR26: CFOG Finance SCI – Science | J11: Team decision (v0.7): asked of MRE only.
B12: TR1(c) | C12: Expert assessment of the quality, relevance and continuity of these collaborations | D12: 5a – Sustainability research is integrated with campus operations and plann | E12: ABP – Architecture, Building and Planning: R ARTS – Arts: R CFOG – Procurement: R CI&S – Sustainability Strategy: A ESG – Campus Operations & Sustainability Delivery: R FBE – Business and Economics: R MRE – Research: R ⚠ CFOG Finance: R ⚠ RIC: Support SCI – Science: R | F12: MRE – Research: R | G12: MRE – Research | H12: ABP – Architecture, Building and Planning ARTS – Arts CFOG – Procurement CI&S – Sustainability Strategy ESG – Campus Operations & Sustainability Delivery FBE – Business and Economics Not in SR26: CFOG Finance SCI – Science | J12: Team decision (v0.7): asked of MRE only.
B13: TR1(d) | C13: Periodic feedback from participants on the effectiveness and mutual benefit of collaboration mechanisms. | D13: 5a – Sustainability research is integrated with campus operations and plann | E13: ABP – Architecture, Building and Planning: R ARTS – Arts: R CFOG – Procurement: R CI&S – Sustainability Strategy: A ESG – Campus Operations & Sustainability Delivery: R FBE – Business and Economics: R MRE – Research: R ⚠ CFOG Finance: R ⚠ RIC: Support SCI – Science: R | F13: MRE – Research: R | G13: MRE – Research | H13: ABP – Architecture, Building and Planning ARTS – Arts CFOG – Procurement CI&S – Sustainability Strategy ESG – Campus Operations & Sustainability Delivery FBE – Business and Economics Not in SR26: CFOG Finance SCI – Science | J13: Team decision (v0.7): asked of MRE only.
B14: TR2(a) | C14: Evidence of sustainability-related research impact across diverse pathways, could include policy, industry, community, practice, cultural and institutional outcomes | D14: 5b – The highest quality research is conducted that contributes to knowledg | E14: ABP – Architecture, Building and Planning: A and R ARTS – Arts: A and R FBE – Business and Economics: A and R MRE – Research: R ⚠ RIC: R SCI – Science: A and R | F14: ABP – Architecture, Building and Planning: R AC&M – Advancement, Communication and Marketing: R ARTS – Arts: R FBE – Business and Economics: R SCI – Science: R | G14: ABP – Architecture, Building and Planning ARTS – Arts FBE – Business and Economics SCI – Science | H14: MRE – Research Not in SR26: RIC | I14: AC&M – Advancement, Communication and Marketing | J14: Check why MRE is not asked (was responsible in SR25); Consider request or 'C/I' for RIC.
B15: TR2(b) | C15: Documented progress of relevant strategic initiatives, including Impact Accelerators | D15: 5b – The highest quality research is conducted that contributes to knowledg | E15: ABP – Architecture, Building and Planning: A and R ARTS – Arts: A and R FBE – Business and Economics: A and R MRE – Research: R ⚠ RIC: R SCI – Science: A and R | F15: MRE – Research: R (quant) | G15: MRE – Research | H15: ABP – Architecture, Building and Planning ARTS – Arts FBE – Business and Economics Not in SR26: RIC SCI – Science | J15: Check why ABP, ARTS, FBE, SCI is not asked (was responsible in SR25); Consider request or 'C/I' for RIC.
B16: TR2(c) | C16: Expert-reviewed summary of sustainability-related research outputs, outcomes and influence using available institutional evidence sources | D16: 5b – The highest quality research is conducted that contributes to knowledg | E16: ABP – Architecture, Building and Planning: A and R ARTS – Arts: A and R FBE – Business and Economics: A and R MRE – Research: R ⚠ RIC: R SCI – Science: A and R | F16: MRE – Research: R | G16: MRE – Research | H16: ABP – Architecture, Building and Planning ARTS – Arts FBE – Business and Economics Not in SR26: RIC SCI – Science | J16: Check why ABP, ARTS, FBE, SCI is not asked (was responsible in SR25); Consider request or 'C/I' for RIC.
B17: TR2(d) | C17: Case-based evidence demonstrating how research has contributed to meaningful sustainability outcomes. | D17: 5b – The highest quality research is conducted that contributes to knowledg | E17: ABP – Architecture, Building and Planning: A and R ARTS – Arts: A and R FBE – Business and Economics: A and R MRE – Research: R ⚠ RIC: R SCI – Science: A and R | F17: ABP – Architecture, Building and Planning: R ARTS – Arts: R CI&S – Sustainability Strategy: R FBE – Business and Economics: R SCI – Science: R | G17: ABP – Architecture, Building and Planning ARTS – Arts FBE – Business and Economics SCI – Science | H17: MRE – Research Not in SR26: RIC | I17: CI&S – Sustainability Strategy | J17: Check why MRE is not asked (was responsible in SR25); Consider request or 'C/I' for RIC.
B18: TR3(a) | C18: Evidence that sustainability considerations are integrated into relevant research systems, planning processes, guidance, training, induction or support services | D18: 5c – Researchers make considered decisions on the sustainability impact of | E18: ABP – Architecture, Building and Planning: R ARTS – Arts: R FBE – Business and Economics: R MRE – Research: A ⚠ RIC: A and R SCI – Science: R | F18: MRE – Research: R | G18: MRE – Research | H18: ABP – Architecture, Building and Planning ARTS – Arts FBE – Business and Economics Not in SR26: RIC SCI – Science | J18: Team decision (v0.7): asked of MRE only.
B19: TR3(b) | C19: Demonstrated examples of more sustainable research practices in laboratories, fieldwork, procurement, travel or infrastructure use | D19: 5c – Researchers make considered decisions on the sustainability impact of | E19: ABP – Architecture, Building and Planning: R ARTS – Arts: R FBE – Business and Economics: R MRE – Research: A ⚠ RIC: A and R SCI – Science: R | F19: ABP – Architecture, Building and Planning: R ARTS – Arts: R CFOG – Procurement: R CI&S – Sustainability Strategy: R FBE – Business and Economics: R MRE – Research: R (quant) SCI – Science: R | G19: ABP – Architecture, Building and Planning ARTS – Arts FBE – Business and Economics MRE – Research SCI – Science | H19: Not in SR26: RIC | I19: CFOG – Procurement CI&S – Sustainability Strategy | J19: Consider request or 'C/I' for RIC.
B20: TR3(c) | C20: Evidence of progress in sustainability-related research culture, capability and awareness, informed by periodic staff and graduate researcher surveys | D20: 5c – Researchers make considered decisions on the sustainability impact of 3d – Academic and professional staff have increased their participation in | E20: ABP – Architecture, Building and Planning: R ARTS – Arts: R ESG – Campus Operations & Sustainability Delivery: A Education – Chancellery Education: A and R FBE – Business and Economics: R MRE – Research: A ⚠ RIC: A and R SCI – Science: R | F20: MRE – Research: R | G20: MRE – Research | H20: ABP – Architecture, Building and Planning ARTS – Arts ESG – Campus Operations & Sustainability Delivery Education – Chancellery Education FBE – Business and Economics Not in SR26: RIC SCI – Science | J20: Team decision (v0.7): asked of MRE only.
B21: TR3(d) | C21: Expert assessment of progress in embedding sustainable research practices across the institution. | D21: 5c – Researchers make considered decisions on the sustainability impact of | E21: ABP – Architecture, Building and Planning: R ARTS – Arts: R FBE – Business and Economics: R MRE – Research: A ⚠ RIC: A and R SCI – Science: R | F21: MRE – Research: R | G21: MRE – Research | H21: ABP – Architecture, Building and Planning ARTS – Arts FBE – Business and Economics Not in SR26: RIC SCI – Science | J21: Team decision (v0.7): asked of MRE only.
B22: CL1(a) | C22: Annual Greenhouse Gas Inventory (including emissions scopes 1, 2 and 3) demonstrates carbon emission reductions, including maintaining procurement of 100% renewable electricity for all scope 2 sources[1] | D22: 1a – The University is certified carbon neutral by 2025 | E22: ABP – Architecture, Building and Planning: R ARTS – Arts: R CFOG – Procurement: R CFOG – Treasury & Investments: R CI&S – Sustainability Strategy: A and R ESG – Campus Operations & Sustainability Delivery: R Education – Chancellery Education: R (air travel) FBE – Business and Economics: R GCE – Global, Culture and Engagement: R (air travel) Indigenous – Chancellery Indigenous: R (air travel) MRE – Research: R (air travel) ⚠ CFOG Finance: R ⚠ People strategy: R (air travel) SCI – Science: R | F22: ESG – Campus Operations & Sustainability Delivery: R (quant) | G22: ESG – Campus Operations & Sustainability Delivery | H22: ABP – Architecture, Building and Planning ARTS – Arts CFOG – Procurement CFOG – Treasury & Investments CI&S – Sustainability Strategy Education – Chancellery Education FBE – Business and Economics GCE – Global, Culture and Engagement Indigenous – Chancellery Indigenous MRE – Research Not in SR26: CFOG Finance Not in SR26: People strategy SCI – Science | J22: Check why ABP, ARTS, CFOG, CFOG, CI&S, Education, FBE, GCE, Indigenous, MRE, SCI is not asked (was responsible in SR25); Consider request or 'C/I' for CFOG Finance, People strategy.
B23: CL1(b) | C23: Development of Greenhouse Gas intensity metrics | D23: 1a – The University is certified carbon neutral by 2025 | E23: ABP – Architecture, Building and Planning: R ARTS – Arts: R CFOG – Procurement: R CFOG – Treasury & Investments: R CI&S – Sustainability Strategy: A and R ESG – Campus Operations & Sustainability Delivery: R Education – Chancellery Education: R (air travel) FBE – Business and Economics: R GCE – Global, Culture and Engagement: R (air travel) Indigenous – Chancellery Indigenous: R (air travel) MRE – Research: R (air travel) ⚠ CFOG Finance: R ⚠ People strategy: R (air travel) SCI – Science: R | F23: ESG – Campus Operations & Sustainability Delivery: R (quant) | G23: ESG – Campus Operations & Sustainability Delivery | H23: ABP – Architecture, Building and Planning ARTS – Arts CFOG – Procurement CFOG – Treasury & Investments CI&S – Sustainability Strategy Education – Chancellery Education FBE – Business and Economics GCE – Global, Culture and Engagement Indigenous – Chancellery Indigenous MRE – Research Not in SR26: CFOG Finance Not in SR26: People strategy SCI – Science | J23: Check why ABP, ARTS, CFOG, CFOG, CI&S, Education, FBE, GCE, Indigenous, MRE, SCI is not asked (was responsible in SR25); Consider request or 'C/I' for CFOG Finance, People strategy.
B24: CL1(c) | C24: Review of Climate Leadership targets by 2030.[2] | D24: 1a – The University is certified carbon neutral by 2025 1b – The University has achieved climate positive status by 2030 | E24: ABP – Architecture, Building and Planning: R ARTS – Arts: R CFOG – Procurement: R CFOG – Treasury & Investments: R CI&S – Sustainability Strategy: A and R ESG – Campus Operations & Sustainability Delivery: R Education – Chancellery Education: R (air travel) FBE – Business and Economics: R GCE – Global, Culture and Engagement: R (air travel) Indigenous – Chancellery Indigenous: R (air travel) MRE – Research: R (air travel) ⚠ CFOG Finance: R ⚠ People strategy: R (air travel) SCI – Science: R | F24: CI&S – Sustainability Strategy: R | G24: CI&S – Sustainability Strategy | H24: ABP – Architecture, Building and Planning ARTS – Arts CFOG – Procurement CFOG – Treasury & Investments ESG – Campus Operations & Sustainability Delivery Education – Chancellery Education FBE – Business and Economics GCE – Global, Culture and Engagement Indigenous – Chancellery Indigenous MRE – Research Not in SR26: CFOG Finance Not in SR26: People strategy SCI – Science | J24: Check why ABP, ARTS, CFOG, CFOG, ESG, Education, FBE, GCE, Indigenous, MRE, SCI is not asked (was responsible in SR25); Consider request or 'C/I' for CFOG Finance, People strategy.
B25: CL2(a) | C25: By 2028, develop and document institutional mapping of research and education activities that are designed to contribute to global decarbonisation | D25: 1b – The University has achieved climate positive status by 2030 | E25: ABP – Architecture, Building and Planning: R ARTS – Arts: R FBE – Business and Economics: R MRE – Research: Support SCI – Science: R | F25: AC&M – Advancement, Communication and Marketing: R | H25: ABP – Architecture, Building and Planning ARTS – Arts FBE – Business and Economics SCI – Science | I25: AC&M – Advancement, Communication and Marketing | J25: Team decision (v0.7): asked of AC&M only.
B26: CL2(b) | C26: Prioritised pipeline of decarbonisation focused research and education opportunities aligned with University emissions reduction priorities from 2028 | D26: 1b – The University has achieved climate positive status by 2030 | E26: ABP – Architecture, Building and Planning: R ARTS – Arts: R FBE – Business and Economics: R MRE – Research: Support SCI – Science: R | F26: SST compiles | H26: ABP – Architecture, Building and Planning ARTS – Arts FBE – Business and Economics SCI – Science | J26: Check why ABP, ARTS, FBE, SCI is not asked (was responsible in SR25).
B27: CL2(c) | C27: Ongoing communications that evidence the University’s climate action, research and learning to inform policy, sector and community decarbonisation efforts. | D27: 1b – The University has achieved climate positive status by 2030 | E27: ABP – Architecture, Building and Planning: R ARTS – Arts: R FBE – Business and Economics: R MRE – Research: Support SCI – Science: R | F27: AC&M – Advancement, Communication and Marketing: R | H27: ABP – Architecture, Building and Planning ARTS – Arts FBE – Business and Economics SCI – Science | I27: AC&M – Advancement, Communication and Marketing | J27: Team decision (v0.7): asked of AC&M only.
B28: CL3(a) | C28: Maturity assessment of the University’s preparedness for climate-related impacts and capability to respond, assessed across relevant organisational functions: o Governance and strategy o Health and safety o Business continuity o Emergency management and critical incidence management o Estate and buildings o Water management o Financial planning and reporting. | D28: 8a – The University reaches and maintains a 'high' climate change preparedn | E28: CFOG – Procurement: R CI&S – Estate Planning & Development: R CI&S – Sustainability Strategy: A and R ESG – Campus Operations & Sustainability Delivery: R Legal & Risk – Risk & resilience: Support ⚠ CFOG Finance: R ⚠ EPMO & investment office: R | F28: CI&S – Estate Planning & Development: R Legal & Risk – Risk & resilience: R | G28: CI&S – Estate Planning & Development | H28: CFOG – Procurement CI&S – Sustainability Strategy ESG – Campus Operations & Sustainability Delivery Not in SR26: CFOG Finance Not in SR26: EPMO & investment office | J28: Check why CFOG, CI&S, ESG is not asked (was responsible in SR25); Consider request or 'C/I' for CFOG Finance, EPMO & investment office.
B29: NB1(a) | C29: Monitoring of biodiversity metrics from the Biodiversity Baseline Data Project | D29: 9a – Each campus achieves no net loss of biodiversity relative to defined b 9b – Each campus achieves an increase of biodiversity relative to defined b | E29: CI&S – Estate Planning & Development: R ESG – Campus Operations & Sustainability Delivery: A and R | F29: ESG – Campus Operations & Sustainability Delivery: R (quant) | G29: ESG – Campus Operations & Sustainability Delivery | H29: CI&S – Estate Planning & Development | J29: Check why CI&S is not asked (was responsible in SR25).
B30: NB1(b) | C30: Size, health and diversity of remnant vegetation at the Dookie and Creswick campuses | D30: 9a – Each campus achieves no net loss of biodiversity relative to defined b | E30: CI&S – Estate Planning & Development: R ESG – Campus Operations & Sustainability Delivery: A and R | F30: ESG – Campus Operations & Sustainability Delivery: R | G30: ESG – Campus Operations & Sustainability Delivery | H30: CI&S – Estate Planning & Development | J30: Check why CI&S is not asked (was responsible in SR25).
B31: NB1(c) | C31: Defined quality measurement framework | D31: 9b – Each campus achieves an increase of biodiversity relative to defined b | E31: CI&S – Estate Planning & Development: R ESG – Campus Operations & Sustainability Delivery: A and R | F31: ESG – Campus Operations & Sustainability Delivery: R | G31: ESG – Campus Operations & Sustainability Delivery | H31: CI&S – Estate Planning & Development | J31: Check why CI&S is not asked (was responsible in SR25).
B32: NB1(d) | C32: Defined and quantified campus connectivity | D32: 9b – Each campus achieves an increase of biodiversity relative to defined b | E32: CI&S – Estate Planning & Development: R ESG – Campus Operations & Sustainability Delivery: A and R | F32: ESG – Campus Operations & Sustainability Delivery: R | G32: ESG – Campus Operations & Sustainability Delivery | H32: CI&S – Estate Planning & Development | J32: Check why CI&S is not asked (was responsible in SR25).
B33: NB2(a) | C33: Documented baseline nature footprint analysis | D33: 11c – The University has principles for ethical and sustainable consumption | E33: CFOG – Procurement: A and R CI&S – Sustainability Strategy: Support ESG – Campus Operations & Sustainability Delivery: A and R | F33: MRE – Research: R | H33: CFOG – Procurement ESG – Campus Operations & Sustainability Delivery | I33: MRE – Research | J33: Check why CFOG, ESG is not asked (was responsible in SR25).
B34: NB2(b) | C34: Evidence of established framework to monitor and track supply-chain nature impacts over time | D34: 11c – The University has principles for ethical and sustainable consumption | E34: CFOG – Procurement: A and R CI&S – Sustainability Strategy: Support ESG – Campus Operations & Sustainability Delivery: A and R | F34: ESG – Campus Operations & Sustainability Delivery: R | G34: ESG – Campus Operations & Sustainability Delivery | H34: CFOG – Procurement | J34: Check why CFOG is not asked (was responsible in SR25).
B35: NB2(c) | C35: Evidence of prioritised high risk procurement categories or suppliers for nature impact management | D35: 11c – The University has principles for ethical and sustainable consumption | E35: CFOG – Procurement: A and R CI&S – Sustainability Strategy: Support ESG – Campus Operations & Sustainability Delivery: A and R | F35: CFOG – Procurement: R ESG – Campus Operations & Sustainability Delivery: R | G35: CFOG – Procurement ESG – Campus Operations & Sustainability Delivery | J35: Consistent with SR25.
B36: AI1(a) | C36: Established measurement of estimated operational impacts and opportunities (eg operational impacts could include energy, water, emissions and intensity measures) | D36: None (new in Sustainability 2030) | E36: – | F36: CI&S – Sustainability Strategy: R CIOG – Responsible AI & digital: R | I36: CI&S – Sustainability Strategy CIOG – Responsible AI & digital | J36: New indicator – no SR25 equivalent; SR26 roles stand.
B37: AI1(b) | C37: Case studies of sustainability and AI-related education, research and collaboration activities. | D37: None (new in Sustainability 2030) | E37: – | F37: CI&S – Sustainability Strategy: R CIOG – Responsible AI & digital: R | I37: CI&S – Sustainability Strategy CIOG – Responsible AI & digital | J37: New indicator – no SR25 equivalent; SR26 roles stand.
B38: EI1(a) | C38: Evidence of increased maturity of estate and infrastructure planning, development and operations to support the other priority areas in Sustainability 2030 | D38: 7b – The University has led or influenced discussions with precinct partner 8a – The University reaches and maintains a 'high' climate change preparedn | E38: ABP – Architecture, Building and Planning: Faculty specific ARTS – Arts: Faculty specific CFOG – Procurement: R CI&S – Estate Planning & Development: A and R CI&S – Sustainability Strategy: A and R ESG – Campus Operations & Sustainability Delivery: R FBE – Business and Economics: Faculty specific Legal & Risk – Risk & resilience: Support ⚠ CFOG Finance: R ⚠ EPMO & investment office: R SCI – Science: Faculty specific | F38: CI&S – Estate Planning & Development: R | G38: CI&S – Estate Planning & Development | H38: CFOG – Procurement CI&S – Sustainability Strategy ESG – Campus Operations & Sustainability Delivery Not in SR26: CFOG Finance Not in SR26: EPMO & investment office | J38: Check why CFOG, CI&S, ESG is not asked (was responsible in SR25); Consider request or 'C/I' for CFOG Finance, EPMO & investment office.
B39: EI1(b) | C39: Estimated sustainability impacts of the University’s estate and infrastructure capital plan to inform progress towards emissions reduction targets and other priority areas (to the extent enabled by available information) | D39: 7b – The University has led or influenced discussions with precinct partner | E39: ABP – Architecture, Building and Planning: Faculty specific ARTS – Arts: Faculty specific CI&S – Estate Planning & Development: A and R ESG – Campus Operations & Sustainability Delivery: Support FBE – Business and Economics: Faculty specific SCI – Science: Faculty specific | F39: CI&S – Estate Planning & Development: R | G39: CI&S – Estate Planning & Development | J39: Consistent with SR25.
B40: EI1(c) | C40: Reporting on relevant activities and impacts for the University’s major estate and infrastructure projects and programs aligned with the other priority areas in Sustainability 2030 | D40: 7b – The University has led or influenced discussions with precinct partner | E40: ABP – Architecture, Building and Planning: Faculty specific ARTS – Arts: Faculty specific CI&S – Estate Planning & Development: A and R ESG – Campus Operations & Sustainability Delivery: Support FBE – Business and Economics: Faculty specific SCI – Science: Faculty specific | F40: CI&S – Estate Planning & Development: R | G40: CI&S – Estate Planning & Development | J40: Consistent with SR25.
B41: EI1(d) | C41: Evidence of understanding and integration of Indigenous approaches to sustainability in estate planning and development programs and projects. | D41: 7b – The University has led or influenced discussions with precinct partner 6a – The University has an increased understanding of sustainability from a | E41: ABP – Architecture, Building and Planning: Faculty specific ARTS – Arts: Faculty specific CI&S – Estate Planning & Development: A and R ESG – Campus Operations & Sustainability Delivery: Support FBE – Business and Economics: Faculty specific GCE – Global, Culture and Engagement: R Indigenous – Chancellery Indigenous: A and R SCI – Science: Faculty specific | F41: CI&S – Estate Planning & Development: R | G41: CI&S – Estate Planning & Development | H41: GCE – Global, Culture and Engagement Indigenous – Chancellery Indigenous | J41: Check why GCE, Indigenous is not asked (was responsible in SR25).
B42: CE1(a) | C42: Comparison of year-to-year tonnes of waste (absolute). | D42: 11a – The University has reduced waste to landfill to 10kg per person | E42: CFOG – Procurement: Support (proc) CI&S – Estate Planning & Development: R ESG – Campus Operations & Sustainability Delivery: A and R | F42: ESG – Campus Operations & Sustainability Delivery: R (quant) | G42: ESG – Campus Operations & Sustainability Delivery | H42: CI&S – Estate Planning & Development | J42: Check why CI&S is not asked (was responsible in SR25).
B43: CE2(a) | C43: Comparison of year-to-year tonnes of recyclables (absolute). | D43: 11a – The University has reduced waste to landfill to 10kg per person 11b – The University has reduced the flow and improved the circularity of ma | E43: CFOG – Procurement: A and R CI&S – Estate Planning & Development: R ESG – Campus Operations & Sustainability Delivery: A and R | F43: ESG – Campus Operations & Sustainability Delivery: R (quant) | G43: ESG – Campus Operations & Sustainability Delivery | H43: CFOG – Procurement CI&S – Estate Planning & Development | J43: Check why CFOG, CI&S is not asked (was responsible in SR25).
B44: RP1(a) | C44: Case studies of maturity improvement related to responsible procurement process and systems. | D44: 11c – The University has principles for ethical and sustainable consumption | E44: CFOG – Procurement: A and R CI&S – Sustainability Strategy: Support ESG – Campus Operations & Sustainability Delivery: A and R | F44: CFOG – Procurement: R | G44: CFOG – Procurement | H44: ESG – Campus Operations & Sustainability Delivery | J44: Check why ESG is not asked (was responsible in SR25).
B45: RP2(a) | C45: Percentage of Indigenous spend of total addressable procurement spend | D45: 11d – The University tracks spend with social and Indigenous suppliers, sett | E45: CFOG – Procurement: A and R | F45: CFOG – Procurement: R (quant) | G45: CFOG – Procurement | J45: Consistent with SR25.
B46: RP2(b) | C46: Percentage of social spend of total addressable procurement spend. | D46: 11d – The University tracks spend with social and Indigenous suppliers, sett | E46: CFOG – Procurement: A and R | F46: CFOG – Procurement: R (quant) | G46: CFOG – Procurement | J46: Consistent with SR25.
B47: MS1(a) | C47: Annual progress reporting via the Modern Slavery Statement | D47: 11c – The University has principles for ethical and sustainable consumption | E47: CFOG – Procurement: A and R CI&S – Sustainability Strategy: Support ESG – Campus Operations & Sustainability Delivery: A and R | F47: CFOG – Procurement: R CI&S – Sustainability Strategy: R | G47: CFOG – Procurement | H47: ESG – Campus Operations & Sustainability Delivery | J47: Check why ESG is not asked (was responsible in SR25).
B48: RI1(a) | C48: Annual monitoring and reporting on the investment portfolio’s net zero transition progress, including tracking the percentage of assets under management (AUM) managed by investment managers aligned with (or committed to) net zero by 2050 | D48: 12a – The University’s investment portfolio will be included in our commitme | E48: CFOG – Treasury & Investments: A and R CI&S – Sustainability Strategy: R | F48: CFOG – Treasury & Investments: R (quant) | G48: CFOG – Treasury & Investments | H48: CI&S – Sustainability Strategy | J48: Check why CI&S is not asked (was responsible in SR25).
B49: RI1(b) | C49: Continuous improvement of the reporting of the University’s sustainability-related investment profile metrics, could include investment in climate mitigation and transition solutions, and compliance with related obligations (eg UNPRI). | D49: 12b – Enhanced transparent reporting of the University’s investment portfoli | E49: CFOG – Treasury & Investments: A and R CI&S – Sustainability Strategy: R | F49: CFOG – Treasury & Investments: R CI&S – Sustainability Strategy: R | G49: CFOG – Treasury & Investments CI&S – Sustainability Strategy | J49: Consistent with SR25.
B50: EN1(a) | C50: Evidence of sustainability outcomes informed by Indigenous knowledges | D50: 6a – The University has an increased understanding of sustainability from a | E50: GCE – Global, Culture and Engagement: R Indigenous – Chancellery Indigenous: A and R | F50: ABP – Architecture, Building and Planning: R ARTS – Arts: R FBE – Business and Economics: R GCE – Global, Culture and Engagement: R Indigenous – Chancellery Indigenous: R SCI – Science: R | G50: GCE – Global, Culture and Engagement Indigenous – Chancellery Indigenous | I50: ABP – Architecture, Building and Planning ARTS – Arts FBE – Business and Economics SCI – Science | J50: Consistent with SR25. New areas added in SR26.
B51: EN1(b) | C51: Living laboratories enabling applied learning, research and operational sustainability outcomes | D51: 2a – The University has curated living labs covering the priority areas of | E51: ABP – Architecture, Building and Planning: R ARTS – Arts: R CFOG – Procurement: R CI&S – Sustainability Strategy: A and R ESG – Campus Operations & Sustainability Delivery: R FBE – Business and Economics: R ⚠ CFOG Finance: R SCI – Science: R | F51: ABP – Architecture, Building and Planning: R ARTS – Arts: R CI&S – Estate Planning & Development: R (quant) CI&S – Sustainability Strategy: R FBE – Business and Economics: R SCI – Science: R | G51: ABP – Architecture, Building and Planning ARTS – Arts CI&S – Sustainability Strategy FBE – Business and Economics SCI – Science | H51: CFOG – Procurement ESG – Campus Operations & Sustainability Delivery Not in SR26: CFOG Finance | I51: CI&S – Estate Planning & Development | J51: Check why CFOG, ESG is not asked (was responsible in SR25); Consider request or 'C/I' for CFOG Finance.
B52: EN1(c) | C52: Coordinated internal engagement and external partnerships contributing to delivery of sustainability outcomes across priority areas. | D52: 7a – The University’s community partnerships demonstrate localised and co-c 7c – The University is playing a leading and convening role on sustainabili 3a – The University's Academic Divisions and portfolios support and learn f | E52: ABP – Architecture, Building and Planning: R ARTS – Arts: R ESG – Campus Operations & Sustainability Delivery: Support Education – Chancellery Education: A FBE – Business and Economics: R GCE – Global, Culture and Engagement: A and R ⚠ Academic Board: Support SCI – Science: R | F52: ABP – Architecture, Building and Planning: R AC&M – Advancement, Communication and Marketing: R ARTS – Arts: R CFOG – Procurement: R CI&S – Sustainability Strategy: R CIOG – Responsible AI & digital: R ESG – Campus Operations & Sustainability Delivery: R Education – Chancellery Education: R FBE – Business and Economics: R GCE – Global, Culture and Engagement: R SCI – Science: R | G52: ABP – Architecture, Building and Planning ARTS – Arts Education – Chancellery Education FBE – Business and Economics GCE – Global, Culture and Engagement SCI – Science | I52: AC&M – Advancement, Communication and Marketing CFOG – Procurement CI&S – Sustainability Strategy CIOG – Responsible AI & digital | J52: Consistent with SR25. New areas added in SR26.
B53: EN1(d) | C53: Sustainability objectives integrated into governance and decision‑making processes, supported by transparent reporting. | D53: 3a – The University's Academic Divisions and portfolios support and learn f | E53: ABP – Architecture, Building and Planning: R ARTS – Arts: R Education – Chancellery Education: A FBE – Business and Economics: R ⚠ Academic Board: Support SCI – Science: R | F53: CFOG – Procurement: R CI&S – Sustainability Strategy: R CIOG – Responsible AI & digital: R ESG – Campus Operations & Sustainability Delivery: R | H53: ABP – Architecture, Building and Planning ARTS – Arts Education – Chancellery Education FBE – Business and Economics SCI – Science | I53: CFOG – Procurement CI&S – Sustainability Strategy CIOG – Responsible AI & digital ESG – Campus Operations & Sustainability Delivery | J53: Team decision (v0.8): not asked of faculties; central units keep it.
B56: SR25 areas with responsibilities but no SR26 role (number of indicators)
B57: Area | C57: Indicators | D57: In SR26 structure?
B58: ABP – Architecture, Building and Planning | C58: 17 | D58: Yes – check
B59: ARTS – Arts | C59: 17 | D59: Yes – check
B60: FBE – Business and Economics | C60: 17 | D60: Yes – check
B61: SCI – Science | C61: 17 | D61: Yes – check
B62: ESG – Campus Operations & Sustainability Delivery | C62: 13 | D62: Yes – check
B63: CFOG – Procurement | C63: 13 | D63: Yes – check
B64: CFOG Finance | C64: 10 | D64: No – no SR26 request
B65: CI&S – Sustainability Strategy | C65: 8 | D65: Yes – check
B66: RIC | C66: 8 | D66: No – no SR26 request
B67: Education – Chancellery Education | C67: 6 | D67: Yes – check
B68: MRE – Research | C68: 6 | D68: Yes – check
B69: CI&S – Estate Planning & Development | C69: 6 | D69: Yes – check
... B75: AC&M – Advancement, Communication and Marketing | C75: 1 | D75: Yes – check

Sheet 4. Request tracker
A1: ↑ | B1: End-2026 target status assessment and reporting
B2: 4. Request tracker
B4: Summary
C5: Not sent | E5: Sent | G5: 1:1 meeting | I5: Received | L5: Response rate | N5: Owner confirmed
C6: =COUNTIF($N$10:$N$26,"Not sent") | E6: =COUNTIF($N$10:$N$26,"Sent") | G6: =COUNTIF($N$10:$N$26,"1:1 meeting") | I6: =COUNTIF($N$10:$N$26,"Received") | L6: =IFERROR((COUNTIF($N$10:$N$26,"Received")+COUNTIF($N$10:$N$26,"Under review")+COUNTIF($N$10:$N$26,"Complete"))/(COUNTA($N$10:$N$26)-COUNTIF($N$10:$N$26,"Not required")),0) | N6: =COUNTIF($M$10:$M$26,"Yes")&" / "&COUNTA($C$10:$C$26)
C7: First review | E7: Follow-up | G7: Complete | I7: Not required
C8: =COUNTIF($N$10:$N$26,"First review") | E8: =COUNTIF($N$10:$N$26,"Follow-up") | G8: =COUNTIF($N$10:$N$26,"Complete") | I8: =COUNTIF($N$10:$N$26,"Not required")
B9: # | C9: Group | D9: Unit / section | E9: Key contact | F9: No. of indicators requested | G9: Request workbook | H9: Date sent | I9: Due date | J9: Reminder date | K9: Optional 1:1 meeting (date) | L9: Response received | M9: Owner confirmed | N9: Status | O9: Days overdue | P9: Notes / follow-up
B10: F1 | C10: Faculty | D10: ABP – Faculty of Architecture, Building and Planning | E10: TBC | F10: 9 | G10: ABP - end-2026 sustainability reporting request - v0.9.xlsx | I10: 46371 | J10: =IF(I10="","",I10-7) | N10: Not sent | O10: =IF(OR(I10="",L10<>""),"",MAX(0,TODAY()-I10))
B11: F2 | C11: Faculty | D11: ARTS – Faculty of Arts | E11: TBC | F11: 9 | G11: ARTS - end-2026 sustainability reporting request - v0.9.xlsx | I11: 46371 | J11: =IF(I11="","",I11-7) | N11: Not sent | O11: =IF(OR(I11="",L11<>""),"",MAX(0,TODAY()-I11))
B12: F3 | C12: Faculty | D12: FBE – Faculty of Business and Economics | E12: TBC | F12: 9 | G12: FBE - end-2026 sustainability reporting request - v0.9.xlsx | I12: 46371 | J12: =IF(I12="","",I12-7) | N12: Not sent | O12: =IF(OR(I12="",L12<>""),"",MAX(0,TODAY()-I12))
B13: F4 | C13: Faculty | D13: SCI – Faculty of Science | E13: TBC | F13: 9 | G13: SCI - end-2026 sustainability reporting request - v0.9.xlsx | I13: 46371 | J13: =IF(I13="","",I13-7) | N13: Not sent | O13: =IF(OR(I13="",L13<>""),"",MAX(0,TODAY()-I13))
B14: C1 | C14: Central | D14: CI&S – Estate Planning & Development (TBC: confirm with Gerard) | E14: TBC | F14: 5 | G14: CIandS - end-2026 sustainability reporting request - v0.9.xlsx | I14: 46371 | J14: =IF(I14="","",I14-7) | N14: Not sent | O14: =IF(OR(I14="",L14<>""),"",MAX(0,TODAY()-I14))
B15: C2 | C15: Central | D15: CI&S – Sustainability Strategy (incl. CLLAP) | E15: TBC | F15: 14 | G15: CIandS - end-2026 sustainability reporting request - v0.9.xlsx | I15: 46371 | J15: =IF(I15="","",I15-7) | N15: Not sent | O15: =IF(OR(I15="",L15<>""),"",MAX(0,TODAY()-I15))
B16: C3 | C16: Central | D16: CFOG – Procurement | E16: TBC | F16: 6 | G16: CFOG - end-2026 sustainability reporting request - v0.9.xlsx | I16: 46371 | J16: =IF(I16="","",I16-7) | N16: Not sent | O16: =IF(OR(I16="",L16<>""),"",MAX(0,TODAY()-I16))
B17: C4 | C17: Central | D17: CFOG – Treasury & Investments | E17: TBC | F17: 1 | G17: CFOG - end-2026 sustainability reporting request - v0.9.xlsx | I17: 46371 | J17: =IF(I17="","",I17-7) | N17: Not sent | O17: =IF(OR(I17="",L17<>""),"",MAX(0,TODAY()-I17))
B18: C5 | C18: Central | D18: ESG – Campus Operations & Sustainability Delivery | E18: TBC | F18: 7 | G18: ESG - end-2026 sustainability reporting request - v0.9.xlsx | I18: 46371 | J18: =IF(I18="","",I18-7) | N18: Not sent | O18: =IF(OR(I18="",L18<>""),"",MAX(0,TODAY()-I18))
B19: C6 | C19: Central | D19: CIOG – Responsible AI & digital | E19: TBC | F19: 4 | G19: CIOG - end-2026 sustainability reporting request - v0.9.xlsx | I19: 46371 | J19: =IF(I19="","",I19-7) | N19: Not sent | O19: =IF(OR(I19="",L19<>""),"",MAX(0,TODAY()-I19))
B20: C7 | C20: Central | D20: MRE – Research (incl. MBI – TBC) | E20: TBC | F20: 8 | G20: MRE - end-2026 sustainability reporting request - v0.9.xlsx | I20: 46371 | J20: =IF(I20="","",I20-7) | N20: Not sent | O20: =IF(OR(I20="",L20<>""),"",MAX(0,TODAY()-I20))
B21: C8 | C21: Central | D21: AC&M – Advancement, Communication and Marketing | E21: TBC | F21: 4 | G21: ACM - end-2026 sustainability reporting request - v0.9.xlsx | I21: 46371 | J21: =IF(I21="","",I21-7) | N21: Not sent | O21: =IF(OR(I21="",L21<>""),"",MAX(0,TODAY()-I21))
... B26: C13 | C26: Central | D26: Legal & Risk – Risk & resilience | E26: TBC | F26: 1 | G26: LandR - end-2026 sustainability reporting request - v0.9.xlsx | I26: 46371 | J26: =IF(I26="","",I26-7) | N26: Not sent | O26: =IF(OR(I26="",L26<>""),"",MAX(0,TODAY()-I26))

Sheet Faculties
A1: ↑ | B1: End-2026 target status assessment and reporting
B2: Faculties
B3: Consolidated responses – paste from returned request workbooks (identical column layout). Click [+] above Columns H–K for end-2025 responses.
B5: 1.1 ABP – Faculty of Architecture, Building and Planning
C7: Sustainability 2030 target and indicator | H7: End-2025 reporting (click the ref to see your full SR25 response; [+] above expands a summary) | L7: End-2026 reporting (PLEASE COMPLETE THIS SECTION)
B8: Ref | C8: Priority area | D8: Sustainability 2030 target | E8: Indicator | F8: 2026 Reporting request | G8: How SST will use this data | H8: Related SR25 ref | I8: End-2025 confirmed status | J8: End-2025 reporting response | K8: Links and supporting information | L8: Confirm end-2026 target status | M8: OPTION 1: Target-level reporting (Column D) | N8: OPTION 2: Indicator level reporting (Column E/F) | O8: Supporting information/comments | P8: Data source and limitations | Q8: Data owner confirms information is accurate | R8: Confirmed by (name, role, date)
L9: (Met or exceeded; partially met; not met; not yet started) | M9: Provide further evidence of target status assessment in the form of: A general update on activities in relation to the overarching target (Column D) | N9: Provide further evidence of target status assessment in the form of: Data and commentary in direct response to the reporting request (Column F) | O9: Provide any additional information to support the target status assessment (e.g. links, images, rationale for selection of target status) | P9: Where did this information come from (system, report, survey, person)? Note any gaps or limitations. | Q9: Select 'Yes' to confirm the information provided is accurate and can be used for reporting | R9: Name, role and date of the person confirming
B10: EE1(a) | C10: Exceptional education | D10: Provide our students with learning experiences that help them build the knowledge, skills and relationships to lead change for sustainable societies. | E10: Evidence of innovative approaches to sustainability teaching and learning | F10: In end-2025 reporting your faculty reported on the related SP2030 target 4a(ii) and rated it 'Partially met' (see Column J – click [+] above Columns I–K). Please build on this rather than repeating it, focusing on what is new in 2026. Please give any examples from 2026 of how your faculty has embedded sustainability in teaching and learning. This could include innovative approaches (e.g. new or redesigned subjects, curriculum design, pedagogies, assessment or learning resources) and sustainability-focused experiential or co-curricular learning (e.g. industry or community projects, fieldwork, internships, student challenges). Include links and approximate student participation where known. This question also covers indicator EE1(c). Melbourne Plus and the Wattle Fellowship will be collected separately – no need to report these. | G10: We will collate examples of sustainability teaching and learning, including experiential and co-curricular learning, across faculties to inform the Exceptional education section of the 2026 Sustainability Report. Strong examples may be followed up for the report. | H10: 4a(ii) | I10: Partially met | J10: The Faculty has continued to make substantial and discipline-wide progress in embedding sustainability into the curriculum in ways that extend well beyond baseline requirements, ensuring that students critically engage with both the beneficial and harmful impacts of the built environment on environmental and human systems. A central mechanism for this work in 2025 has been the forward planning and strategic renewal of all Master’s programs across the Faculty, led by Professor Dan Hill under the Designing Futures strategy. This process goes beyond incremental subject updates and instead focuses on holistic program-level reform, explicitly positioning sustainability as a core organising principle rather than an add-on topic. In practice, this has involved structured, discipline-specific workshops bringing together all academic staff within each program to reflect on: - the current state of sustainability integration across subjects, - emerging societal, environmental and industry challenges, - the skills and capabilities graduates will require to respond responsibly and effectively, - how sustainability is communicated, scaffolded and reinforced across the program. A recent example is the Master of Construction Management, where a half-day, facilitated workshop brought together the full academic teaching team to collectively review the program’s direction. Guided by Professor Hill, the session examined course narratives, subject sequencing, learning outcomes and focus areas, with particular attention to how issues such as embodied carbon, circular construction, climate risk, systems thinking and ethical responsibility are integrated throughout the degree. The outcome of this process is a clearer, more coherent approach to sustainability that is embedded across core and specialist subjects, rather than confined to standalone units. Complementing this program-level work, the Faculty has continued the development of two new sustainability-focused subjects—one at undergraduate level and one at graduate level—both designed to foster interdisciplinary, applied engagement with climate and sustainability challenges. Ongoing curriculum mapping across programs further supports this effort by identifying sustainability-rich learning pathways and informing both subject development and student advising. Together, these initiatives demonstrate a deliberate and sustained commitment to embedding sustainability deeply and coherently across the curriculum, ensuring that graduates across all disciplines develop a critical understanding of the environmental and human systems they shape through professional practice.
B11: EE1(b) | C11: Exceptional education | D11: Provide our students with learning experiences that help them build the knowledge, skills and relationships to lead change for sustainable societies. | E11: Pilots of possible approaches for understanding and developing students’ sustainability self-efficacy | F11: Has your faculty piloted or trialled any approach in 2026 to understand or build students' confidence and capability to act on sustainability (sustainability self-efficacy)? If yes, briefly describe the approach, participating cohort, what was learned and next steps. If not, please respond 'none in 2026' – this is a new indicator and a nil response is useful. We are aware of the Sustainability Strengths Compass Living Lab project (CLLAP) and will collect it separately. | G11: This is a new indicator. We will use responses to establish a baseline of how (and whether) faculties are understanding student sustainability self-efficacy, and report on early pilots in the 2026 Sustainability Report. A nil response is useful to us. | H11: N/A – new indicator
B12: TR1(a) | C12: Transformational research | D12: Utilise the expertise of the University’s researchers through mutually beneficial partnerships to help address the University’s operational sustainability challenges. | E12: Expert-reviewed evidence of researchers contributing to operational sustainability priorities through partnerships, advisory input, living labs, applied projects or decision-support | F12: In end-2025 reporting your faculty reported on the related SP2030 target 2a and rated it 'Met or exceeded' (see Column J – click [+] above Columns I–K). Please build on this rather than repeating it, focusing on what is new in 2026. Please give any examples from 2026 of researchers in your faculty contributing to the University's own operational sustainability challenges (e.g. advising on campus energy, biodiversity, waste or buildings; applied projects; decision-support tools). Briefly describe the operational challenge, the researchers' contribution, the University team involved and the result. We will collect Campus Living Lab Accelerator Program (CLLAP) projects separately from CI&S – please include other examples only. | G12: We will report on examples of researchers helping solve the University's own operational sustainability challenges, alongside CLLAP projects reported by CI&S, and share them with operational teams to identify further collaboration. | H12: 2a | I12: Met or exceeded | J12: Across 2025, the Faculty of Architecture, Building and Planning has significantly strengthened and formalised its Living Labs approach, building on progress reported at mid-year and embedding sustainability experimentation as a core mode of practice across teaching, research, and operations. A major development in the second half of 2025 was the establishment of the ABP Sustainability Grant. This new internal funding scheme provides up to $10,000 annually to catalyse staff-led, cross-disciplinary sustainability initiatives that operate as Living Labs within the Faculty. The scheme supports projects that use real faculty contexts—spaces, systems, practices, and communities—as testbeds for sustainability innovation, with strong encouragement for student involvement, particularly graduate researchers. The Sustainability Grant marks a shift from ad hoc Living Lab activity toward a curated, faculty-wide framework that empowers staff to design, trial, and document practical sustainability interventions. The inaugural funding round attracted multiple applications from across disciplines and professional areas, and a formal selection process is currently underway, demonstrating strong engagement and appetite for Living Lab activity within ABP. In parallel, the Faculty has continued to develop and refine larger-scale Living Lab concepts at the precinct level. While the delivery of the Fishermans Bend campus project has been postponed, the Faculty remains committed to a Living Lab approach and has retained and further clarified the conceptual and methodological groundwork. This positions the Faculty to rapidly mobilise Living Lab activities once the project recommences, ensuring that sustainability, circularity, and environmental performance are embedded from the earliest stages of planning and development. Collectively, these initiatives demonstrate that ABP is not only contributing to the University’s Living Labs agenda, but actively curating, resourcing, and governing Living Labs as a sustained and scalable approach to sustainability action. A flagship example of the Faculty’s Living Labs approach in 2025 is the Interactive Campus Material and Carbon Atlas, which reached completion during the year. Funded through the Learning and Teaching Initiative (LTI), the project brought together academic staff, professional colleagues, and students to map and analyse the material stock and embodied carbon of selected University buildings. The Atlas has been developed as an interactive digital tool that enables users to explore building-level data, including construction materials, embodied carbon intensities, and potential opportunities for material reuse and circularity. Importantly, the project moves beyond retrospective analysis: the underlying framework enables forward projection of material requirements and carbon implications under different development and renewal scenarios. As such, the Atlas demonstrates the value of a Living Lab that directly integrates sustainability research with campus operations. It provides a practical decision-support tool with clear relevance for estate planning, capital works prioritisation, and long-term carbon reduction strategies. With the research and development phase now complete, the Faculty is committed to working with University stakeholders to present the tool to relevant professional teams and explore pathways for embedding it into institutional planning and sustainability processes. This next phase reflects the Faculty’s intent to ensure that Living Lab outputs translate into operational insight and long-term impact, rather than remaining standalone research artefacts. Together with the newly established ABP Sustainability Grant, the Interactive Campus Material and Carbon Atlas illustrates how the Faculty is operationalising Living Labs across scales—from grassroots initiatives to faculty-wide decision-support infrastructure.
B13: TR2(a) | C13: Transformational research | D13: Deliver high-quality research and partnerships that contribute to sustainability outcomes and demonstrable societal benefit. | E13: Evidence of sustainability-related research impact across diverse pathways, could include policy, industry, community, practice, cultural and institutional outcomes | F13: In end-2025 reporting your faculty reported on the related SP2030 target 5b(i) and rated it 'Met or exceeded' (see Column J – click [+] above Columns I–K). Please build on this rather than repeating it, focusing on what is new in 2026. Please give any examples from 2026 of sustainability-related research from your faculty that has had impact beyond academia – on policy, industry, community, practice, cultural or institutional outcomes. Briefly describe the research, the partner or user, and the resulting change or influence, with links (e.g. Pursuit articles, policy submissions, reports). We will source University-wide research metrics (e.g. SDG-mapped publications via SciVal) from MRE – publication counts are not required. | G13: We will collate research impact examples across faculties to show the breadth of sustainability-related research impact in the Transformational research section of the 2026 Sustainability Report, complementing University-wide metrics from MRE. | H13: 5b(i) | I13: Met or exceeded | J13: The Faculty continues to be a national and international leader in sustainability research across the built environment, supported by a diverse ecosystem of specialist research hubs, laboratories, and collaborative initiatives. Together, these centres span disciplinary and interdisciplinary research, linking fundamental inquiry with applied outcomes that inform practice, policy, and industry transformation. Sustainability-, climate-, and environment-focused research institutes and hubs within the Faculty include: - Melbourne Centre for Cities – urban governance, policy innovation, and climate-responsive city-making - InfUr – Informal Urbanism Research Hub – environmental justice, resilience, and community-led urbanism - Transport, Health and Urban Design (THUD) – healthy and sustainable cities through mobility and planning research - Urban Ecology and Design Lab (UED Lab) – ecological design strategies, biodiversity, and nature-based solutions - Sustainable and Healthy Environments (SHE) Lab – materials, thermal comfort, indoor environmental quality, and health–environment linkages - The Retrofit Lab – decarbonisation of existing building stock, circular design, and retrofit decision-making - Advanced Digital Design + Fabrication – sustainable construction, digital materials, and low-carbon manufacturing These research hubs collectively contribute to advancing knowledge across design, planning, construction, and policy, while also creating pathways for translation into real-world impact. A flagship example of the Faculty’s research impact in 2025 is Beyond EPiC, a research-led spin-off emerging from long-standing work within the Faculty on life cycle assessment (LCA), embodied carbon, and environmental performance of the built environment. Beyond EPiC provides a clear example of how the Faculty’s sustainability research translates into action and impact at scale. Emerging directly from decades of peer-reviewed research at the University of Melbourne, Beyond EPiC develops environmental data, digital tools, and applied insights that help architects, engineers, planners, developers, and policymakers make evidence-based decisions across the built environment. Grounded in internationally recognised hybrid life cycle assessment (LCA) methodologies, Beyond EPiC transforms complex environmental research into clear, consistent, and actionable intelligence—maintaining scientific rigour while enabling real-world application. This approach exemplifies the Faculty’s ethos of where science meets the design of buildings and cities. A key research impact in 2025 has been direct policy influence. Beyond EPiC’s embodied carbon data underpins the BASIX Materials Index used by the New South Wales Government for residential development applications. Every project lodged under BASIX must report embodied emissions using these coefficients, making Beyond EPiC’s research a core component of the state’s environmental compliance framework. Since this integration, tens of thousands of homes have been designed and certified using Beyond EPiC data, driving lower-impact material choices and design optimisation at scale. This represents a significant shift from sustainability research as advisory input to sustainability research as embedded policy infrastructure, shaping decisions across an entire construction sector. Beyond EPiC’s impact extends beyond regulation. Its tools and datasets support industry training, consulting, and early-stage design decision-making, enabling practitioners to compare materials, optimise assemblies, and understand embodied carbon trade-offs in ways that were previously inaccessible. This creates a continuous feedback loop between research, teaching, practice, and policy—ensuring that academic inquiry remains responsive to real-world constraints while raising the baseline of environmental accountability. As such, Beyond EPiC exemplifies the Faculty’s model of sustainability research impact: scientifically rigorous, trusted by government, used at scale, and capable of shaping policy, professional practice, and environmental outcomes simultaneously. | K13: www.beyondepic.io
B14: TR2(d) | C14: Transformational research | D14: Deliver high-quality research and partnerships that contribute to sustainability outcomes and demonstrable societal benefit. | E14: Case-based evidence demonstrating how research has contributed to meaningful sustainability outcomes. | F14: In end-2025 reporting your faculty reported on the related SP2030 target 5b(i) and rated it 'Met or exceeded' (see Column J – click [+] above Columns I–K). Please build on this rather than repeating it, focusing on what is new in 2026. Please give any examples of research activity from your faculty that has contributed to a meaningful sustainability outcome: the research, stakeholders involved, pathway to impact and evidence of the outcome. These can be the examples from TR2(a) described in more detail. We are also seeking examples from Melbourne Climate Futures, the Melbourne Biodiversity Institute and Strategic Communications. | G14: We will select the strongest examples to develop as full research case studies for the 2026 Sustainability Report (we may contact you for more detail and images). | H14: 5b(i) | I14: Met or exceeded | J14: The Faculty continues to be a national and international leader in sustainability research across the built environment, supported by a diverse ecosystem of specialist research hubs, laboratories, and collaborative initiatives. Together, these centres span disciplinary and interdisciplinary research, linking fundamental inquiry with applied outcomes that inform practice, policy, and industry transformation. Sustainability-, climate-, and environment-focused research institutes and hubs within the Faculty include: - Melbourne Centre for Cities – urban governance, policy innovation, and climate-responsive city-making - InfUr – Informal Urbanism Research Hub – environmental justice, resilience, and community-led urbanism - Transport, Health and Urban Design (THUD) – healthy and sustainable cities through mobility and planning research - Urban Ecology and Design Lab (UED Lab) – ecological design strategies, biodiversity, and nature-based solutions - Sustainable and Healthy Environments (SHE) Lab – materials, thermal comfort, indoor environmental quality, and health–environment linkages - The Retrofit Lab – decarbonisation of existing building stock, circular design, and retrofit decision-making - Advanced Digital Design + Fabrication – sustainable construction, digital materials, and low-carbon manufacturing These research hubs collectively contribute to advancing knowledge across design, planning, construction, and policy, while also creating pathways for translation into real-world impact. A flagship example of the Faculty’s research impact in 2025 is Beyond EPiC, a research-led spin-off emerging from long-standing work within the Faculty on life cycle assessment (LCA), embodied carbon, and environmental performance of the built environment. Beyond EPiC provides a clear example of how the Faculty’s sustainability research translates into action and impact at scale. Emerging directly from decades of peer-reviewed research at the University of Melbourne, Beyond EPiC develops environmental data, digital tools, and applied insights that help architects, engineers, planners, developers, and policymakers make evidence-based decisions across the built environment. Grounded in internationally recognised hybrid life cycle assessment (LCA) methodologies, Beyond EPiC transforms complex environmental research into clear, consistent, and actionable intelligence—maintaining scientific rigour while enabling real-world application. This approach exemplifies the Faculty’s ethos of where science meets the design of buildings and cities. A key research impact in 2025 has been direct policy influence. Beyond EPiC’s embodied carbon data underpins the BASIX Materials Index used by the New South Wales Government for residential development applications. Every project lodged under BASIX must report embodied emissions using these coefficients, making Beyond EPiC’s research a core component of the state’s environmental compliance framework. Since this integration, tens of thousands of homes have been designed and certified using Beyond EPiC data, driving lower-impact material choices and design optimisation at scale. This represents a significant shift from sustainability research as advisory input to sustainability research as embedded policy infrastructure, shaping decisions across an entire construction sector. Beyond EPiC’s impact extends beyond regulation. Its tools and datasets support industry training, consulting, and early-stage design decision-making, enabling practitioners to compare materials, optimise assemblies, and understand embodied carbon trade-offs in ways that were previously inaccessible. This creates a continuous feedback loop between research, teaching, practice, and policy—ensuring that academic inquiry remains responsive to real-world constraints while raising the baseline of environmental accountability. As such, Beyond EPiC exemplifies the Faculty’s model of sustainability research impact: scientifically rigorous, trusted by government, used at scale, and capable of shaping policy, professional practice, and environmental outcomes simultaneously. | K14: www.beyondepic.io
B15: TR3(b) | C15: Transformational research | D15: Embed sustainability within research systems, processes, capability and culture, so research is conducted responsibly, efficiently and with reduced environmental impact. | E15: Demonstrated examples of more sustainable research practices in laboratories, fieldwork, procurement, travel or infrastructure use | F15: In end-2025 reporting your faculty reported on the related SP2030 target 5c(ii) and rated it 'Partially met' (see Column J – click [+] above Columns I–K). Please build on this rather than repeating it, focusing on what is new in 2026. Are there any efforts within the faculty to make research practices more sustainable (e.g. green lab certification, equipment sharing, reduced research travel, sustainable fieldwork, sustainable procurement of research consumables)? If so, please give any examples and any evidence of uptake, resource savings or emissions reductions. | G15: We will report on ways the University is making research practices more sustainable in the 2026 Sustainability Report, and share practical examples (e.g. green labs) across faculties. | H15: 5c(ii) | I15: Partially met | J15: The Faculty has taken deliberate and strategic steps in 2025 to strengthen how sustainability considerations shape research practices and activities. This has focused on making sustainability explicit, visible, and rewarded within the Faculty’s research culture, while building the foundations for longer-term embedding across disciplines. A major development has been the introduction of formal recognition and incentive mechanisms that foreground sustainability in research excellence. The ABP Sustainability Award, embedded within the Faculty’s Engagement, Culture, Innovation, and Impact awards program, recognises academic and professional staff who demonstrate leadership in integrating sustainability into research practices. By celebrating approaches such as life cycle thinking, low-carbon methodologies, resource efficiency, and collaborative research models, the award signals that sustainability is a core dimension of research quality and impact within ABP. This cultural shift is reinforced through the ABP Sustainability Grants Program, which supports staff-led projects that actively trial new ways of embedding sustainability into research, teaching, and operational contexts. Grant criteria encourage interdisciplinary collaboration and require applicants to engage directly with the environmental implications of their activities—supporting experimentation, documentation, and knowledge-sharing around more sustainable research practices. In parallel, Faculty researchers continue to advance methodological leadership that enables more sustainable decision-making in research and practice. Work on hybrid life cycle assessment (LCA), embodied carbon accounting, and environmental benchmarking—particularly through collaborations with Beyond EPiC—has expanded the tools available to researchers, industry, and government to measure and reduce environmental impacts. These methods increasingly inform how research questions are framed, evaluated, and translated into policy and practice. Together, these initiatives reflect a maturing research culture in which sustainability is increasingly normalised, recognised, and actively shaped through incentives, methods, and shared expectations. While this work will continue to evolve and scale, 2025 represents a clear step change in positioning sustainability as a defining feature of responsible research practice within the Faculty.
B16: EN1(a) | C16: Enablers | D16: Enablers | E16: Evidence of sustainability outcomes informed by Indigenous knowledges | F16: In end-2025 reporting your faculty reported on the related SP2030 target 6a and rated it 'Met or exceeded' (see Column J – click [+] above Columns I–K). Please build on this rather than repeating it, focusing on what is new in 2026. Please give any examples of activity in your faculty (education, research, engagement or operations) where Indigenous knowledges informed a sustainability outcome. Describe the activity, how Indigenous knowledges were incorporated or co-created and with whom, and the result. Please confirm that appropriate permissions are in place for sharing. | G16: We will report on the ways Indigenous knowledges inform sustainability activities across the University, and develop selected examples into case studies with appropriate permissions. | H16: 6a | I16: Met or exceeded | J16: In 2025, the Faculty has continued to deepen its engagement with sustainability through Indigenous-led and co-created learning, research, and partnerships, strengthening understanding of sustainability as a Country-centred, relational, and long-term responsibility rather than a purely technical or extractive concept. A major development is the award of an ARC Linkage Project: Co-designing Housing for First Nations Prosperity, which will commence in 2026. This project represents a significant example of sustainability research grounded in First Nations leadership, knowledge, and lived experience, operating at the intersection of architecture, housing policy, economics, and Indigenous wellbeing. Led by Associate Professor Rory Hyde and a multidisciplinary team across architecture, public health, policy and design, the project is being co-developed with First Nations organisations and partners in Shepparton, Victoria, including the Kaiela Institute, Beyond Housing, and VACCHO, alongside industry and government partners. The research places First Nations knowledge, lore, and priorities at the centre of housing design and delivery, challenging conventional Western models that have historically failed to meet cultural, social, and environmental needs. Sustainability in this project is understood holistically: as cultural continuity, social connection, climate resilience, economic viability, and care for Country. Through participatory co-design and strategic design methods, the project will produce a design catalogue and investment model that enables the delivery of housing that is affordable, culturally appropriate, climate-responsive, and socially sustaining. These outcomes directly address the Closing the Gap agenda while also offering transferable insights for broader housing challenges nationally. Complementing this work, the Faculty continues to support longstanding Indigenous-led collaborations such as Professor Alex Felson’s project on the Great Birrarung Parklands, developed in partnership with the Wurundjeri Woi Wurrung Cultural Heritage Aboriginal Corporation, the Birrarung Council, and other stakeholders. This project brings Indigenous knowledge and climate science together to explore future scenarios for the Yarra River corridor, modelling two-way learning that informs long-term ecological stewardship, governance, and design. Indigenous perspectives on sustainability are also embedded across teaching and learning in the Faculty, particularly within architecture, landscape architecture, and urban planning studios. These studios engage students with questions of Country, custodianship, and cultural practice, often in dialogue with Indigenous collaborators, reinforcing sustainability as a relational and ethical practice rather than a purely technical one. Collectively, these initiatives demonstrate that the Faculty’s approach to sustainability is increasingly shaped through Indigenous-led knowledge systems, reciprocal learning, and co-creation, contributing to more just, culturally grounded, and enduring sustainability outcomes across education, research, and practice.
B17: EN1(b) | C17: Enablers | D17: Enablers | E17: Living laboratories enabling applied learning, research and operational sustainability outcomes | F17: In end-2025 reporting your faculty reported on the related SP2030 target 2a and rated it 'Met or exceeded' (see Column J – click [+] above Columns I–K). Please build on this rather than repeating it, focusing on what is new in 2026. Please give any examples of sustainability-related living labs operating within your faculty in 2026 – their activities, who is involved (students, researchers, operational staff) and their outputs, outcomes or impact. Please note we will approach living labs funded through the Campus Living Lab Accelerator Program (CLLAP) separately. | G17: We will share examples of sustainability-related living labs from across the University in the 2026 Sustainability Report, alongside CLLAP projects reported by CI&S. | H17: 2a | I17: Met or exceeded | J17: Across 2025, the Faculty of Architecture, Building and Planning has significantly strengthened and formalised its Living Labs approach, building on progress reported at mid-year and embedding sustainability experimentation as a core mode of practice across teaching, research, and operations. A major development in the second half of 2025 was the establishment of the ABP Sustainability Grant. This new internal funding scheme provides up to $10,000 annually to catalyse staff-led, cross-disciplinary sustainability initiatives that operate as Living Labs within the Faculty. The scheme supports projects that use real faculty contexts—spaces, systems, practices, and communities—as testbeds for sustainability innovation, with strong encouragement for student involvement, particularly graduate researchers. The Sustainability Grant marks a shift from ad hoc Living Lab activity toward a curated, faculty-wide framework that empowers staff to design, trial, and document practical sustainability interventions. The inaugural funding round attracted multiple applications from across disciplines and professional areas, and a formal selection process is currently underway, demonstrating strong engagement and appetite for Living Lab activity within ABP. In parallel, the Faculty has continued to develop and refine larger-scale Living Lab concepts at the precinct level. While the delivery of the Fishermans Bend campus project has been postponed, the Faculty remains committed to a Living Lab approach and has retained and further clarified the conceptual and methodological groundwork. This positions the Faculty to rapidly mobilise Living Lab activities once the project recommences, ensuring that sustainability, circularity, and environmental performance are embedded from the earliest stages of planning and development. Collectively, these initiatives demonstrate that ABP is not only contributing to the University’s Living Labs agenda, but actively curating, resourcing, and governing Living Labs as a sustained and scalable approach to sustainability action. A flagship example of the Faculty’s Living Labs approach in 2025 is the Interactive Campus Material and Carbon Atlas, which reached completion during the year. Funded through the Learning and Teaching Initiative (LTI), the project brought together academic staff, professional colleagues, and students to map and analyse the material stock and embodied carbon of selected University buildings. The Atlas has been developed as an interactive digital tool that enables users to explore building-level data, including construction materials, embodied carbon intensities, and potential opportunities for material reuse and circularity. Importantly, the project moves beyond retrospective analysis: the underlying framework enables forward projection of material requirements and carbon implications under different development and renewal scenarios. As such, the Atlas demonstrates the value of a Living Lab that directly integrates sustainability research with campus operations. It provides a practical decision-support tool with clear relevance for estate planning, capital works prioritisation, and long-term carbon reduction strategies. With the research and development phase now complete, the Faculty is committed to working with University stakeholders to present the tool to relevant professional teams and explore pathways for embedding it into institutional planning and sustainability processes. This next phase reflects the Faculty’s intent to ensure that Living Lab outputs translate into operational insight and long-term impact, rather than remaining standalone research artefacts. Together with the newly established ABP Sustainability Grant, the Interactive Campus Material and Carbon Atlas illustrates how the Faculty is operationalising Living Labs across scales—from grassroots initiatives to faculty-wide decision-support infrastructure.
B18: EN1(c) | C18: Enablers | D18: Enablers | E18: Coordinated internal engagement and external partnerships contributing to delivery of sustainability outcomes across priority areas. | F18: In end-2025 reporting your faculty reported on the related SP2030 target 3a(ii) and rated it 'Met or exceeded' (see Column J – click [+] above Columns I–K). Please build on this rather than repeating it, focusing on what is new in 2026. Please list the key sustainability-focused communities of practice, internal networks or external partnerships active in your faculty in 2026 (name, partners, priority area), and give any examples of activity that contributed to a Sustainability 2030 outcome. | G18: We will report on internal engagement and partnerships contributing to Sustainability 2030 outcomes, and update our record of sustainability-focused communities of practice and contacts across the University. | H18: 3a(ii) | I18: Met or exceeded | J18: In 2025, ABP continued to support sustainability-focused communities of practice that enable staff to learn from one another and embed sustainability across formal, non-formal, and informal learning contexts. These communities operate through a combination of structured forums, shared initiatives, and recognition mechanisms that make sustainability practice visible, valued, and transferable across the Faculty. Core to this ecosystem is the Faculty’s Climate Action Group, which continues to provide a cross-disciplinary forum for peer learning, curriculum coordination, and shared reflection on sustainability pedagogy and practice. The Group has supported sustained collaboration across academic and professional staff and has played a key role in aligning Faculty initiatives with University sustainability priorities. In 2025, the Faculty also played a leading role in hosting the Architectural Science Association (ASA) Conference, which focused strongly on sustainability, environmental performance, and design-led research. The conference was the largest attended in the 60-year history of the organisation, bringing together academics, practitioners, and industry partners from across Australia and the region. It provided a major platform for knowledge exchange on sustainability-focused teaching, research, and practice, and significantly strengthened both intra- and inter-institutional communities of practice. Complementing these collaborative forums, the Faculty introduced the ABP Sustainability Award as a mechanism for amplifying and connecting sustainability practice across teaching, research, operations, and Faculty culture. Together, these initiatives demonstrate a mature and multi-layered approach to building sustainability-focused communities of practice—combining regular peer engagement, high-impact knowledge exchange, and recognition of exemplary work to support ongoing learning and leadership in sustainability. Introduced in 2025, the ABP Sustainability Award functions as a Faculty-wide community-of-practice mechanism by recognising, showcasing, and disseminating exemplary sustainability initiatives led by academic and professional staff. Rather than operating solely as an individual award, the scheme is designed to surface transferable practices and create shared reference points for sustainability leadership across ABP. The Award recognises excellence across a broad set of criteria, including innovation and leadership, collaboration and engagement, measurable environmental outcomes, integration of sustainability into teaching and learning, influence on policy and professional practice, and contributions to a culture of sustainability within the Faculty. Eligible initiatives span teaching, research, operations, and cultural change, reflecting the diverse ways sustainability is embedded across ABP. By highlighting concrete examples of effective practice—such as projects that reduce environmental footprints, embed circularity into learning environments, or foster cross-disciplinary collaboration—the Award enables staff to learn from peers and adapt successful approaches within their own contexts. The selection process, chaired by the Assistant Dean (Sustainability) and involving senior Faculty leadership and staff representatives, further reinforces shared standards and collective ownership of sustainability goals. In this way, the Sustainability Award complements more formal communities of practice by creating a visible, Faculty-wide platform for knowledge sharing, inspiration, and peer learning. It supports sustainability not only as a technical or curricular concern, but as a shared professional and cultural endeavour.
B21: 1.2 ARTS – Faculty of Arts
C23: Sustainability 2030 target and indicator | H23: End-2025 reporting (click the ref to see your full SR25 response; [+] above expands a summary) | L23: End-2026 reporting (PLEASE COMPLETE THIS SECTION)
B24: Ref | C24: Priority area | D24: Sustainability 2030 target | E24: Indicator | F24: 2026 Reporting request | G24: How SST will use this data | H24: Related SR25 ref | I24: End-2025 confirmed status | J24: End-2025 reporting response | K24: Links and supporting information | L24: Confirm end-2026 target status | M24: OPTION 1: Target-level reporting (Column D) | N24: OPTION 2: Indicator level reporting (Column E/F) | O24: Supporting information/comments | P24: Data source and limitations | Q24: Data owner confirms information is accurate | R24: Confirmed by (name, role, date)
L25: (Met or exceeded; partially met; not met; not yet started) | M25: Provide further evidence of target status assessment in the form of: A general update on activities in relation to the overarching target (Column D) | N25: Provide further evidence of target status assessment in the form of: Data and commentary in direct response to the reporting request (Column F) | O25: Provide any additional information to support the target status assessment (e.g. links, images, rationale for selection of target status) | P25: Where did this information come from (system, report, survey, person)? Note any gaps or limitations. | Q25: Select 'Yes' to confirm the information provided is accurate and can be used for reporting | R25: Name, role and date of the person confirming
B26: EE1(a) | C26: Exceptional education | D26: Provide our students with learning experiences that help them build the knowledge, skills and relationships to lead change for sustainable societies. | E26: Evidence of innovative approaches to sustainability teaching and learning | F26: In end-2025 reporting your faculty reported on the related SP2030 target 4a(ii) and rated it 'Partially met' (see Column J – click [+] above Columns I–K). Please build on this rather than repeating it, focusing on what is new in 2026. Please give any examples from 2026 of how your faculty has embedded sustainability in teaching and learning. This could include innovative approaches (e.g. new or redesigned subjects, curriculum design, pedagogies, assessment or learning resources) and sustainability-focused experiential or co-curricular learning (e.g. industry or community projects, fieldwork, internships, student challenges). Include links and approximate student participation where known. This question also covers indicator EE1(c). Melbourne Plus and the Wattle Fellowship will be collected separately – no need to report these. | G26: We will collate examples of sustainability teaching and learning, including experiential and co-curricular learning, across faculties to inform the Exceptional education section of the 2026 Sustainability Report. Strong examples may be followed up for the report. | H26: 4a(ii) | I26: Partially met | J26: This target poses some specific challenges for the Faculty of Arts because we are a large and diverse entity overwhelmingly teaching academic-focused degrees—the BA, MAs and PhDs (in addition to other smaller initiatives)—across many domains in the Humanities and Social Sciences. As such, it's important to acknowledge and respect that it would not be appropriate for 'sustainability' to be integrated equally into all components in such a varied curriculum. For example, while the SSPS Capstone intensively focused on sustainability through rich and complex case-studies, this cannot be said and should not be expected of a 2nd-year subject in French. However, we have begun discussions with colleagues about putting in place a minor within the BA which we believe would be the best way of meeting this target, amongst other things. In 2026, that discussion will be further elaborated and, we hope, concretised.
B27: EE1(b) | C27: Exceptional education | D27: Provide our students with learning experiences that help them build the knowledge, skills and relationships to lead change for sustainable societies. | E27: Pilots of possible approaches for understanding and developing students’ sustainability self-efficacy | F27: Has your faculty piloted or trialled any approach in 2026 to understand or build students' confidence and capability to act on sustainability (sustainability self-efficacy)? If yes, briefly describe the approach, participating cohort, what was learned and next steps. If not, please respond 'none in 2026' – this is a new indicator and a nil response is useful. We are aware of the Sustainability Strengths Compass Living Lab project (CLLAP) and will collect it separately. | G27: This is a new indicator. We will use responses to establish a baseline of how (and whether) faculties are understanding student sustainability self-efficacy, and report on early pilots in the 2026 Sustainability Report. A nil response is useful to us. | H27: N/A – new indicator
B28: TR1(a) | C28: Transformational research | D28: Utilise the expertise of the University’s researchers through mutually beneficial partnerships to help address the University’s operational sustainability challenges. | E28: Expert-reviewed evidence of researchers contributing to operational sustainability priorities through partnerships, advisory input, living labs, applied projects or decision-support | F28: In end-2025 reporting your faculty reported on the related SP2030 target 2a and rated it 'Met or exceeded' (see Column J – click [+] above Columns I–K). Please build on this rather than repeating it, focusing on what is new in 2026. Please give any examples from 2026 of researchers in your faculty contributing to the University's own operational sustainability challenges (e.g. advising on campus energy, biodiversity, waste or buildings; applied projects; decision-support tools). Briefly describe the operational challenge, the researchers' contribution, the University team involved and the result. We will collect Campus Living Lab Accelerator Program (CLLAP) projects separately from CI&S – please include other examples only. | G28: We will report on examples of researchers helping solve the University's own operational sustainability challenges, alongside CLLAP projects reported by CI&S, and share them with operational teams to identify further collaboration. | H28: 2a | I28: Met or exceeded | J28: See attached report. (RH note: Saved in responses folder) | K28: Draft report on the Living Lab project is here: Report John Medley Living Lab Project FINAL.docx
B29: TR2(a) | C29: Transformational research | D29: Deliver high-quality research and partnerships that contribute to sustainability outcomes and demonstrable societal benefit. | E29: Evidence of sustainability-related research impact across diverse pathways, could include policy, industry, community, practice, cultural and institutional outcomes | F29: In end-2025 reporting your faculty reported on the related SP2030 target 5b(i) and rated it 'Met or exceeded' (see Column J – click [+] above Columns I–K). Please build on this rather than repeating it, focusing on what is new in 2026. Please give any examples from 2026 of sustainability-related research from your faculty that has had impact beyond academia – on policy, industry, community, practice, cultural or institutional outcomes. Briefly describe the research, the partner or user, and the resulting change or influence, with links (e.g. Pursuit articles, policy submissions, reports). We will source University-wide research metrics (e.g. SDG-mapped publications via SciVal) from MRE – publication counts are not required. | G29: We will collate research impact examples across faculties to show the breadth of sustainability-related research impact in the Transformational research section of the 2026 Sustainability Report, complementing University-wide metrics from MRE. | H29: 5b(i) | I29: Met or exceeded | J29: In addition to the matters listed at mid-2025, the Ass Dean joined the Board of MBI and hosted a major showcase of MBI activities to Arts Faculty researchers which boosted involvement in the BDI's researech clusters
B30: TR2(d) | C30: Transformational research | D30: Deliver high-quality research and partnerships that contribute to sustainability outcomes and demonstrable societal benefit. | E30: Case-based evidence demonstrating how research has contributed to meaningful sustainability outcomes. | F30: In end-2025 reporting your faculty reported on the related SP2030 target 5b(i) and rated it 'Met or exceeded' (see Column J – click [+] above Columns I–K). Please build on this rather than repeating it, focusing on what is new in 2026. Please give any examples of research activity from your faculty that has contributed to a meaningful sustainability outcome: the research, stakeholders involved, pathway to impact and evidence of the outcome. These can be the examples from TR2(a) described in more detail. We are also seeking examples from Melbourne Climate Futures, the Melbourne Biodiversity Institute and Strategic Communications. | G30: We will select the strongest examples to develop as full research case studies for the 2026 Sustainability Report (we may contact you for more detail and images). | H30: 5b(i) | I30: Met or exceeded | J30: In addition to the matters listed at mid-2025, the Ass Dean joined the Board of MBI and hosted a major showcase of MBI activities to Arts Faculty researchers which boosted involvement in the BDI's researech clusters
B31: TR3(b) | C31: Transformational research | D31: Embed sustainability within research systems, processes, capability and culture, so research is conducted responsibly, efficiently and with reduced environmental impact. | E31: Demonstrated examples of more sustainable research practices in laboratories, fieldwork, procurement, travel or infrastructure use | F31: In end-2025 reporting your faculty reported on the related SP2030 target 5c(ii) and rated it 'Not met' (see Column J – click [+] above Columns I–K). Please build on this rather than repeating it, focusing on what is new in 2026. Are there any efforts within the faculty to make research practices more sustainable (e.g. green lab certification, equipment sharing, reduced research travel, sustainable fieldwork, sustainable procurement of research consumables)? If so, please give any examples and any evidence of uptake, resource savings or emissions reductions. | G31: We will report on ways the University is making research practices more sustainable in the 2026 Sustainability Report, and share practical examples (e.g. green labs) across faculties. | H31: 5c(ii) | I31: Not met | J31: This needs more specific attention In general terms, the Faculty has focused on reducing air travel, the major environmental impact of our research activity.
B32: EN1(a) | C32: Enablers | D32: Enablers | E32: Evidence of sustainability outcomes informed by Indigenous knowledges | F32: In end-2025 reporting your faculty reported on the related SP2030 target 6a and rated it 'Partially met' (see Column J – click [+] above Columns I–K). Please build on this rather than repeating it, focusing on what is new in 2026. Please give any examples of activity in your faculty (education, research, engagement or operations) where Indigenous knowledges informed a sustainability outcome. Describe the activity, how Indigenous knowledges were incorporated or co-created and with whom, and the result. Please confirm that appropriate permissions are in place for sharing. | G32: We will report on the ways Indigenous knowledges inform sustainability activities across the University, and develop selected examples into case studies with appropriate permissions. | H32: 6a | I32: Partially met | J32: See previous response. (copied below) In addition to housing the Indigenous Studies Program, academic staff have contributed to University-wide Indigenous-led initiatives with important sustainability consequences, and more broadly, champsion such values in their scholarly work.
B33: EN1(b) | C33: Enablers | D33: Enablers | E33: Living laboratories enabling applied learning, research and operational sustainability outcomes | F33: In end-2025 reporting your faculty reported on the related SP2030 target 2a and rated it 'Met or exceeded' (see Column J – click [+] above Columns I–K). Please build on this rather than repeating it, focusing on what is new in 2026. Please give any examples of sustainability-related living labs operating within your faculty in 2026 – their activities, who is involved (students, researchers, operational staff) and their outputs, outcomes or impact. Please note we will approach living labs funded through the Campus Living Lab Accelerator Program (CLLAP) separately. | G33: We will share examples of sustainability-related living labs from across the University in the 2026 Sustainability Report, alongside CLLAP projects reported by CI&S. | H33: 2a | I33: Met or exceeded | J33: See attached report. (RH note: Saved in responses folder) | K33: Draft report on the Living Lab project is here: Report John Medley Living Lab Project FINAL.docx
B34: EN1(c) | C34: Enablers | D34: Enablers | E34: Coordinated internal engagement and external partnerships contributing to delivery of sustainability outcomes across priority areas. | F34: In end-2025 reporting your faculty reported on the related SP2030 target 3a(ii) and rated it 'Partially met' (see Column J – click [+] above Columns I–K). Please build on this rather than repeating it, focusing on what is new in 2026. Please list the key sustainability-focused communities of practice, internal networks or external partnerships active in your faculty in 2026 (name, partners, priority area), and give any examples of activity that contributed to a Sustainability 2030 outcome. | G34: We will report on internal engagement and partnerships contributing to Sustainability 2030 outcomes, and update our record of sustainability-focused communities of practice and contacts across the University. | H34: 3a(ii) | I34: Partially met | J34: Academics in the Faculty have supported and learned from each other in new ways through the Living Lab and through using the sustainability networks in the Faculty and beyond to showcase and develop T&L initiatives. This is, of course, an ongoing process.
B37: 1.3 FBE – Faculty of Business and Economics
C39: Sustainability 2030 target and indicator | H39: End-2025 reporting (click the ref to see your full SR25 response; [+] above expands a summary) | L39: End-2026 reporting (PLEASE COMPLETE THIS SECTION)
B40: Ref | C40: Priority area | D40: Sustainability 2030 target | E40: Indicator | F40: 2026 Reporting request | G40: How SST will use this data | H40: Related SR25 ref | I40: End-2025 confirmed status | J40: End-2025 reporting response | K40: Links and supporting information | L40: Confirm end-2026 target status | M40: OPTION 1: Target-level reporting (Column D) | N40: OPTION 2: Indicator level reporting (Column E/F) | O40: Supporting information/comments | P40: Data source and limitations | Q40: Data owner confirms information is accurate | R40: Confirmed by (name, role, date)
L41: (Met or exceeded; partially met; not met; not yet started) | M41: Provide further evidence of target status assessment in the form of: A general update on activities in relation to the overarching target (Column D) | N41: Provide further evidence of target status assessment in the form of: Data and commentary in direct response to the reporting request (Column F) | O41: Provide any additional information to support the target status assessment (e.g. links, images, rationale for selection of target status) | P41: Where did this information come from (system, report, survey, person)? Note any gaps or limitations. | Q41: Select 'Yes' to confirm the information provided is accurate and can be used for reporting | R41: Name, role and date of the person confirming
B42: EE1(a) | C42: Exceptional education | D42: Provide our students with learning experiences that help them build the knowledge, skills and relationships to lead change for sustainable societies. | E42: Evidence of innovative approaches to sustainability teaching and learning | F42: In end-2025 reporting your faculty reported on the related SP2030 target 4a(ii) and rated it 'Partially met' (see Column J – click [+] above Columns I–K). Please build on this rather than repeating it, focusing on what is new in 2026. Please give any examples from 2026 of how your faculty has embedded sustainability in teaching and learning. This could include innovative approaches (e.g. new or redesigned subjects, curriculum design, pedagogies, assessment or learning resources) and sustainability-focused experiential or co-curricular learning (e.g. industry or community projects, fieldwork, internships, student challenges). Include links and approximate student participation where known. This question also covers indicator EE1(c). Melbourne Plus and the Wattle Fellowship will be collected separately – no need to report these. | G42: We will collate examples of sustainability teaching and learning, including experiential and co-curricular learning, across faculties to inform the Exceptional education section of the 2026 Sustainability Report. Strong examples may be followed up for the report. | H42: 4a(ii) | I42: Partially met | J42: The refresh of the Bachelor of Commerce BCOM refresh included explicitly embedding sustainability in course level learning outcomes, major level learning outcomes, and is now a specialisation (Ethics and Sustainability) available to students across all majors. See also Sust teaching case study p2
B43: EE1(b) | C43: Exceptional education | D43: Provide our students with learning experiences that help them build the knowledge, skills and relationships to lead change for sustainable societies. | E43: Pilots of possible approaches for understanding and developing students’ sustainability self-efficacy | F43: Has your faculty piloted or trialled any approach in 2026 to understand or build students' confidence and capability to act on sustainability (sustainability self-efficacy)? If yes, briefly describe the approach, participating cohort, what was learned and next steps. If not, please respond 'none in 2026' – this is a new indicator and a nil response is useful. We are aware of the Sustainability Strengths Compass Living Lab project (CLLAP) and will collect it separately. | G43: This is a new indicator. We will use responses to establish a baseline of how (and whether) faculties are understanding student sustainability self-efficacy, and report on early pilots in the 2026 Sustainability Report. A nil response is useful to us. | H43: N/A – new indicator
B44: TR1(a) | C44: Transformational research | D44: Utilise the expertise of the University’s researchers through mutually beneficial partnerships to help address the University’s operational sustainability challenges. | E44: Expert-reviewed evidence of researchers contributing to operational sustainability priorities through partnerships, advisory input, living labs, applied projects or decision-support | F44: In end-2025 reporting your faculty reported on the related SP2030 target 2a and rated it 'Partially met' (see Column J – click [+] above Columns I–K). Please build on this rather than repeating it, focusing on what is new in 2026. Please give any examples from 2026 of researchers in your faculty contributing to the University's own operational sustainability challenges (e.g. advising on campus energy, biodiversity, waste or buildings; applied projects; decision-support tools). Briefly describe the operational challenge, the researchers' contribution, the University team involved and the result. We will collect Campus Living Lab Accelerator Program (CLLAP) projects separately from CI&S – please include other examples only. | G44: We will report on examples of researchers helping solve the University's own operational sustainability challenges, alongside CLLAP projects reported by CI&S, and share them with operational teams to identify further collaboration. | H44: 2a | I44: Partially met | J44: CLLAP report on University Investor Stewardship provided separately
B45: TR2(a) | C45: Transformational research | D45: Deliver high-quality research and partnerships that contribute to sustainability outcomes and demonstrable societal benefit. | E45: Evidence of sustainability-related research impact across diverse pathways, could include policy, industry, community, practice, cultural and institutional outcomes | F45: In end-2025 reporting your faculty reported on the related SP2030 target 5b(i) and rated it 'Partially met' (see Column J – click [+] above Columns I–K). Please build on this rather than repeating it, focusing on what is new in 2026. Please give any examples from 2026 of sustainability-related research from your faculty that has had impact beyond academia – on policy, industry, community, practice, cultural or institutional outcomes. Briefly describe the research, the partner or user, and the resulting change or influence, with links (e.g. Pursuit articles, policy submissions, reports). We will source University-wide research metrics (e.g. SDG-mapped publications via SciVal) from MRE – publication counts are not required. | G45: We will collate research impact examples across faculties to show the breadth of sustainability-related research impact in the Transformational research section of the 2026 Sustainability Report, complementing University-wide metrics from MRE. | H45: 5b(i) | I45: Partially met | J45: Several departments have completed high quality sustainability-focused research, which includes papers published in peer reviwed research journals and a range of commissioned research for diverse industry partners including the national accounting standard setting body, which focus on a range of sustainability-related topics. See M&M Sust Research Hub case study p2 | K45: https://fbe.unimelb.edu.au/research/our-research-at-a-glance
B46: TR2(d) | C46: Transformational research | D46: Deliver high-quality research and partnerships that contribute to sustainability outcomes and demonstrable societal benefit. | E46: Case-based evidence demonstrating how research has contributed to meaningful sustainability outcomes. | F46: In end-2025 reporting your faculty reported on the related SP2030 target 5b(i) and rated it 'Partially met' (see Column J – click [+] above Columns I–K). Please build on this rather than repeating it, focusing on what is new in 2026. Please give any examples of research activity from your faculty that has contributed to a meaningful sustainability outcome: the research, stakeholders involved, pathway to impact and evidence of the outcome. These can be the examples from TR2(a) described in more detail. We are also seeking examples from Melbourne Climate Futures, the Melbourne Biodiversity Institute and Strategic Communications. | G46: We will select the strongest examples to develop as full research case studies for the 2026 Sustainability Report (we may contact you for more detail and images). | H46: 5b(i) | I46: Partially met | J46: Several departments have completed high quality sustainability-focused research, which includes papers published in peer reviwed research journals and a range of commissioned research for diverse industry partners including the national accounting standard setting body, which focus on a range of sustainability-related topics. See M&M Sust Research Hub case study p2 | K46: https://fbe.unimelb.edu.au/research/our-research-at-a-glance
